Workbook
Name CATEGORIAS: 'UNIVERSO PRODUCTOS'!$A$1:$H$961
Name central: #REF!
Name samu: #REF!
Name samuel: #REF!

Sheet Ingredientes
A1: ID Ingrediente | B1: Nombre Ingrediente | C1: Cantidad | D1: Costo Total

Sheet UNIVERSO PRODUCTOS
A1: ID | B1: Nombre | C1: Precio | D1: Unidad de medida | E1: Conversiones | F1: ID externo | G1: ID Categoria | H1: Nombre Categoria | I1: ID Categoria Externo | J1: ID Bodegas | K1: Nombre Bodegas | L1: Impuestos
A2: ti-ing-b69bd6ae-ccae-4801-af83-bece901d304f | B2: Aceite oliva extra virgen 5 lts | C2: 4646.2 | D2: LT | G2: ti-incat-dbb4ab5d-d383-44df-bb1b-2819d297b20d | H2: Abarrotes | J2: ti-str-e3696e4b-7915-4d18-83e7-077d2c42d9bc,ti-str-bbb1d66c-36dd-47af-85d8-583c26959146,ti-str-36f261ca-0b74-4d79-8a50-81324d9ac308 | K2: Principal,Stock Cocina,Stock Panaderia | L2: iva_19
A3: ti-ing-5a1041f6-5fed-4ae0-8d00-dee7d47968a3 | B3: Aceite vegetal 900 ml | C3: 1540.6 | D3: UN | G3: ti-incat-dbb4ab5d-d383-44df-bb1b-2819d297b20d | H3: Abarrotes | J3: ti-str-e3696e4b-7915-4d18-83e7-077d2c42d9bc,ti-str-e0754139-882f-4237-83fa-744442ed825f,ti-str-bbb1d66c-36dd-47af-85d8-583c26959146,ti-str-36f261ca-0b74-4d79-8a50-81324d9ac308 | K3: Principal,Stock Pasteleria,Stock Cocina,Stock Panaderia | L3: iva_19
A4: ti-ing-0ab486df-7d4d-4782-82bb-c30b4209e5fb | B4: Aceituna Morada kg | C4: 7130 | D4: KG | G4: ti-incat-dbb4ab5d-d383-44df-bb1b-2819d297b20d | H4: Abarrotes | J4: ti-str-bbb1d66c-36dd-47af-85d8-583c26959146 | K4: Stock Cocina | L4: iva_19
A5: ti-ing-581e5046-d41b-44fd-981a-fa5ec2c4d4ba | B5: Ajinomoto | C5: 3354 | D5: kg | G5: ti-incat-dbb4ab5d-d383-44df-bb1b-2819d297b20d | H5: Abarrotes | J5: ti-str-e3696e4b-7915-4d18-83e7-077d2c42d9bc,ti-str-bbb1d66c-36dd-47af-85d8-583c26959146 | K5: Principal,Stock Cocina | L5: iva_19
A6: ti-ing-65292276-c9a9-4569-b8ff-19a5a3fea424 | B6: Anis kg | C6: 13854 | D6: Kg | G6: ti-incat-dbb4ab5d-d383-44df-bb1b-2819d297b20d | H6: Abarrotes | J6: ti-str-e3696e4b-7915-4d18-83e7-077d2c42d9bc,ti-str-36f261ca-0b74-4d79-8a50-81324d9ac308 | K6: Principal,Stock Panaderia | L6: iva_19
A7: ti-ing-bfd5d10e-d265-4e6e-b05a-79c836269380 | B7: Arroz (colacion) | C7: 905 | D7: KG | G7: ti-incat-dbb4ab5d-d383-44df-bb1b-2819d297b20d | H7: Abarrotes | J7: ti-str-e3696e4b-7915-4d18-83e7-077d2c42d9bc,ti-str-bbb1d66c-36dd-47af-85d8-583c26959146 | K7: Principal,Stock Cocina | L7: iva_19
A8: ti-ing-5c316419-1759-4d90-bb2e-e9025a87d122 | B8: Atun Coliseo Al Agua | C8: 879 | D8: UN | G8: ti-incat-dbb4ab5d-d383-44df-bb1b-2819d297b20d | H8: Abarrotes | J8: ti-str-e3696e4b-7915-4d18-83e7-077d2c42d9bc,ti-str-bbb1d66c-36dd-47af-85d8-583c26959146 | K8: Principal,Stock Cocina | L8: iva_19
A9: ti-ing-363a5ec1-8d6b-4612-be6a-7a19b61ab7e2 | B9: Atun Dorasol Al Agua | C9: 879 | D9: UN | G9: ti-incat-dbb4ab5d-d383-44df-bb1b-2819d297b20d | H9: Abarrotes | J9: ti-str-e3696e4b-7915-4d18-83e7-077d2c42d9bc,ti-str-bbb1d66c-36dd-47af-85d8-583c26959146 | K9: Principal,Stock Cocina | L9: iva_19
A10: ti-ing-c1414efc-1614-40c6-a7e8-2f6efb3e0401 | B10: Avena | C10: 1050 | D10: KG | G10: ti-incat-dbb4ab5d-d383-44df-bb1b-2819d297b20d | H10: Abarrotes | J10: ti-str-e3696e4b-7915-4d18-83e7-077d2c42d9bc,ti-str-36f261ca-0b74-4d79-8a50-81324d9ac308 | K10: Principal,Stock Panaderia | L10: iva_19
A11: ti-ing-531d1d9b-814d-49bc-9bbf-06be4ae2e6d5 | B11: Azucar blanca | C11: 939.9985 | D11: KG | G11: ti-incat-dbb4ab5d-d383-44df-bb1b-2819d297b20d | H11: Abarrotes | J11: ti-str-e3696e4b-7915-4d18-83e7-077d2c42d9bc,ti-str-e0754139-882f-4237-83fa-744442ed825f,ti-str-bbb1d66c-36dd-47af-85d8-583c26959146,ti-str-36f261ca-0b74-4d79-8a50-81324d9ac308,ti-str-eafdd243-ca10-4e67-89d4-50a191eb8e12 | K11: Principal,Stock Pasteleria,Stock Cocina,Stock Panaderia,Stock Servicio | L11: iva_19
B12: Azúcar blanca por kilo | C12: 930 | D12: KG | G12: ti-incat-dbb4ab5d-d383-44df-bb1b-2819d297b20d | H12: Abarrotes | K12: Principal,Stock Cocina | L12: iva_19
A13: ti-ing-c4486ce7-85c4-49c5-ac82-4d98b0798d01 | B13: Azucar rubia | C13: 1047 | D13: KG | G13: ti-incat-dbb4ab5d-d383-44df-bb1b-2819d297b20d | H13: Abarrotes | J13: ti-str-e3696e4b-7915-4d18-83e7-077d2c42d9bc,ti-str-e0754139-882f-4237-83fa-744442ed825f,ti-str-bbb1d66c-36dd-47af-85d8-583c26959146,ti-str-36f261ca-0b74-4d79-8a50-81324d9ac308,ti-str-eafdd243-ca10-4e67-89d4-50a191eb8e12 | K13: Principal,Stock Pasteleria,Stock Cocina,Stock Panaderia,Stock Servicio | L13: iva_19
A14: ti-ing-63a7f9f9-77ff-45f4-9e3f-3feff0b73432 | B14: Café tarro grande (desayuno) | C14: 12032 | D14: UN | G14: ti-incat-dbb4ab5d-d383-44df-bb1b-2819d297b20d | H14: Abarrotes | J14: ti-str-e3696e4b-7915-4d18-83e7-077d2c42d9bc,ti-str-e0754139-882f-4237-83fa-744442ed825f,ti-str-bbb1d66c-36dd-47af-85d8-583c26959146,ti-str-36f261ca-0b74-4d79-8a50-81324d9ac308,ti-str-eafdd243-ca10-4e67-89d4-50a191eb8e12 | K14: Principal,Stock Pasteleria,Stock Cocina,Stock Panaderia,Stock Servicio | L14: iva_19
A15: ti-ing-f57e1d6d-2d59-440c-a741-794a5d5d1359 | B15: Chia kg | C15: 4152 | D15: UN | G15: ti-incat-dbb4ab5d-d383-44df-bb1b-2819d297b20d | H15: Abarrotes | J15: ti-str-e3696e4b-7915-4d18-83e7-077d2c42d9bc,ti-str-36f261ca-0b74-4d79-8a50-81324d9ac308 | K15: Principal,Stock Panaderia | L15: iva_19
A16: ti-ing-b908bdf8-4d68-4e4a-bca8-67edb76d6236 | B16: Chips Chocolate Negro kg | C16: 6977.75 | D16: KG | G16: ti-incat-dbb4ab5d-d383-44df-bb1b-2819d297b20d | H16: Abarrotes | J16: ti-str-e3696e4b-7915-4d18-83e7-077d2c42d9bc,ti-str-e0754139-882f-4237-83fa-744442ed825f,ti-str-36f261ca-0b74-4d79-8a50-81324d9ac308 | K16: Principal,Stock Pasteleria,Stock Panaderia | L16: iva_19
A17: ti-ing-89800579-a778-4a4e-8895-e0cc7ed6a986 | B17: Coco Laminado | C17: 8474 | D17: KG | G17: ti-incat-dbb4ab5d-d383-44df-bb1b-2819d297b20d | H17: Abarrotes | J17: ti-str-e3696e4b-7915-4d18-83e7-077d2c42d9bc,ti-str-e0754139-882f-4237-83fa-744442ed825f,ti-str-36f261ca-0b74-4d79-8a50-81324d9ac308 | K17: Principal,Stock Pasteleria,Stock Panaderia | L17: iva_19
A18: ti-ing-a396335b-a1d5-46a1-874a-de8bd1a3a0de | B18: Coco Rallado | C18: 4188 | D18: KG | G18: ti-incat-dbb4ab5d-d383-44df-bb1b-2819d297b20d | H18: Abarrotes | J18: ti-str-e3696e4b-7915-4d18-83e7-077d2c42d9bc,ti-str-36f261ca-0b74-4d79-8a50-81324d9ac308,ti-str-e0754139-882f-4237-83fa-744442ed825f | K18: Principal,Stock Panaderia,Stock Pasteleria | L18: iva_19
A19: ti-ing-280562df-e2c6-469c-bfaf-8f7361fb5c74 | B19: COMINO | C19: 5250 | D19: KG | G19: ti-incat-dbb4ab5d-d383-44df-bb1b-2819d297b20d | H19: Abarrotes | J19: ti-str-e3696e4b-7915-4d18-83e7-077d2c42d9bc,ti-str-bbb1d66c-36dd-47af-85d8-583c26959146 | K19: Principal,Stock Cocina | L19: iva_19
A20: ti-ing-55e22a4e-70ba-4bfe-9ef6-78d09a6c71b6 | B20: Curcuma | C20: 5437 | D20: KG | G20: ti-incat-dbb4ab5d-d383-44df-bb1b-2819d297b20d | H20: Abarrotes | J20: ti-str-e3696e4b-7915-4d18-83e7-077d2c42d9bc,ti-str-bbb1d66c-36dd-47af-85d8-583c26959146 | K20: Principal,Stock Cocina | L20: iva_19
A21: ti-ing-064cb0f3-6635-4de8-915c-d57502a19286 | B21: Esencia vainilla | C21: 1000 | D21: LT | G21: ti-incat-dbb4ab5d-d383-44df-bb1b-2819d297b20d | H21: Abarrotes | J21: ti-str-e3696e4b-7915-4d18-83e7-077d2c42d9bc,ti-str-e0754139-882f-4237-83fa-744442ed825f,ti-str-36f261ca-0b74-4d79-8a50-81324d9ac308 | K21: Principal,Stock Pasteleria,Stock Panaderia | L21: iva_19
A22: ti-ing-2fbc1c56-3286-4d64-8ddd-b547296361a3 | B22: Espaguetti | C22: 407 | D22: UN | G22: ti-incat-dbb4ab5d-d383-44df-bb1b-2819d297b20d | H22: Abarrotes | J22: ti-str-e3696e4b-7915-4d18-83e7-077d2c42d9bc,ti-str-bbb1d66c-36dd-47af-85d8-583c26959146 | K22: Principal,Stock Cocina | L22: iva_19
A23: ti-ing-446530ff-42dc-41f9-9208-1b6c8dded86f | B23: Espirales | C23: 399 | D23: UN | G23: ti-incat-dbb4ab5d-d383-44df-bb1b-2819d297b20d | H23: Abarrotes | J23: ti-str-e3696e4b-7915-4d18-83e7-077d2c42d9bc,ti-str-bbb1d66c-36dd-47af-85d8-583c26959146 | K23: Principal,Stock Cocina | L23: iva_19
A24: ti-ing-150d078f-94cc-4527-a524-b16516d0adfa | B24: Fruta Confitada | C24: 3500 | D24: KG | G24: ti-incat-dbb4ab5d-d383-44df-bb1b-2819d297b20d | H24: Abarrotes | J24: ti-str-e3696e4b-7915-4d18-83e7-077d2c42d9bc,ti-str-36f261ca-0b74-4d79-8a50-81324d9ac308 | K24: Principal,Stock Panaderia | L24: iva_19
... A27: ti-ing-af062f27-295c-456a-9ce5-77fbb725f339 | B27: Helado Chocolate | C27: 2360.6 | D27: LT | G27: ti-incat-dbb4ab5d-d383-44df-bb1b-2819d297b20d | H27: Abarrotes | J27: ti-str-eafdd243-ca10-4e67-89d4-50a191eb8e12,ti-str-e3696e4b-7915-4d18-83e7-077d2c42d9bc | K27: Stock Servicio,Principal | L27: iva_19
B28: Helado frutilla | C28: 3469 | D28: LT | G28: ti-incat-dbb4ab5d-d383-44df-bb1b-2819d297b20d | H28: Abarrotes | J28: ti-str-eafdd243-ca10-4e67-89d4-50a191eb8e12,ti-str-e3696e4b-7915-4d18-83e7-077d2c42d9bc | K28: Stock Servicio,Principal | L28: iva_19
A29: ti-ing-12dbd538-5012-4d25-8c02-7d0b4f3fdf45 | B29: Helado Vainilla | C29: 2979 | D29: LT | G29: ti-incat-dbb4ab5d-d383-44df-bb1b-2819d297b20d | H29: Abarrotes | J29: ti-str-eafdd243-ca10-4e67-89d4-50a191eb8e12,ti-str-e3696e4b-7915-4d18-83e7-077d2c42d9bc | K29: Stock Servicio,Principal | L29: iva_19
A30: ti-ing-e6ff2cd2-0729-44b9-b0d3-457299c1ead8 | B30: Huevos Arizona | C30: 138 | D30: UN | G30: ti-incat-dbb4ab5d-d383-44df-bb1b-2819d297b20d | H30: Abarrotes | J30: ti-str-e3696e4b-7915-4d18-83e7-077d2c42d9bc,ti-str-e0754139-882f-4237-83fa-744442ed825f,ti-str-bbb1d66c-36dd-47af-85d8-583c26959146,ti-str-36f261ca-0b74-4d79-8a50-81324d9ac308 | K30: Principal,Stock Pasteleria,Stock Cocina,Stock Panaderia | L30: iva_19
A31: ti-ing-06898fd0-9448-431b-9bad-3526a93cf181 | B31: Ketchup kg | C31: 1550 | D31: KG | G31: ti-incat-dbb4ab5d-d383-44df-bb1b-2819d297b20d | H31: Abarrotes | J31: ti-str-e3696e4b-7915-4d18-83e7-077d2c42d9bc,ti-str-bbb1d66c-36dd-47af-85d8-583c26959146 | K31: Principal,Stock Cocina | L31: iva_19
A32: ti-ing-f3eeca8c-b308-4136-a438-0f68fc53c279 | B32: Lasagne Chef | C32: 3831.8 | D32: kg | G32: ti-incat-dbb4ab5d-d383-44df-bb1b-2819d297b20d | H32: Abarrotes | J32: ti-str-e3696e4b-7915-4d18-83e7-077d2c42d9bc,ti-str-bbb1d66c-36dd-47af-85d8-583c26959146 | K32: Principal,Stock Cocina | L32: iva_19
A33: ti-ing-20a9682d-4a6c-42c4-a3ed-312cab8df904 | B33: Laurel | C33: 75280 | D33: KG | G33: ti-incat-dbb4ab5d-d383-44df-bb1b-2819d297b20d | H33: Abarrotes | J33: ti-str-e3696e4b-7915-4d18-83e7-077d2c42d9bc,ti-str-bbb1d66c-36dd-47af-85d8-583c26959146 | K33: Principal,Stock Cocina | L33: iva_19
A34: ti-ing-772eef79-e2de-41fa-b52c-f097abd8b4a8 | B34: Leche Entera En Polvo | C34: 7079.167 | D34: KG | G34: ti-incat-dbb4ab5d-d383-44df-bb1b-2819d297b20d | H34: Abarrotes | J34: ti-str-e3696e4b-7915-4d18-83e7-077d2c42d9bc,ti-str-e0754139-882f-4237-83fa-744442ed825f,ti-str-36f261ca-0b74-4d79-8a50-81324d9ac308 | K34: Principal,Stock Pasteleria,Stock Panaderia | L34: iva_19
A35: ti-ing-a5f32751-2fe1-4388-acd1-977dd4d921a6 | B35: Lentejas (colacion personal) | C35: 2118 | D35: KG | G35: ti-incat-dbb4ab5d-d383-44df-bb1b-2819d297b20d | H35: Abarrotes | J35: ti-str-e3696e4b-7915-4d18-83e7-077d2c42d9bc,ti-str-bbb1d66c-36dd-47af-85d8-583c26959146 | K35: Principal,Stock Cocina | L35: iva_19
A36: ti-ing-0ec3786c-eec8-4a04-af8d-bda30eac5549 | B36: Levadura seca (Unidad) | C36: 1711 | D36: UN | G36: ti-incat-dbb4ab5d-d383-44df-bb1b-2819d297b20d | H36: Abarrotes | J36: ti-str-e3696e4b-7915-4d18-83e7-077d2c42d9bc,ti-str-e0754139-882f-4237-83fa-744442ed825f,ti-str-36f261ca-0b74-4d79-8a50-81324d9ac308 | K36: Principal,Stock Pasteleria,Stock Panaderia | L36: iva_19
A37: ti-ing-b41eeb59-c8ac-4580-b11d-bbd7dc537fd3 | B37: Linaza kg | C37: 2995 | D37: KG | G37: ti-incat-dbb4ab5d-d383-44df-bb1b-2819d297b20d | H37: Abarrotes | J37: ti-str-e3696e4b-7915-4d18-83e7-077d2c42d9bc,ti-str-36f261ca-0b74-4d79-8a50-81324d9ac308 | K37: Principal,Stock Panaderia | L37: iva_19
A38: ti-ing-69061f8d-e4d9-4fc4-b44e-0cd173ebf8f3 | B38: Maicena kg | C38: 1582 | D38: KG | G38: ti-incat-dbb4ab5d-d383-44df-bb1b-2819d297b20d | H38: Abarrotes | J38: ti-str-e3696e4b-7915-4d18-83e7-077d2c42d9bc,ti-str-e0754139-882f-4237-83fa-744442ed825f,ti-str-bbb1d66c-36dd-47af-85d8-583c26959146,ti-str-36f261ca-0b74-4d79-8a50-81324d9ac308 | K38: Principal,Stock Pasteleria,Stock Cocina,Stock Panaderia | L38: iva_19
A39: ti-ing-3dba6697-1589-49e0-8e6e-951b48b7d160 | B39: Mayonesa Hellmans | C39: 3989.362 | D39: Kg | G39: ti-incat-dbb4ab5d-d383-44df-bb1b-2819d297b20d | H39: Abarrotes | J39: ti-str-e3696e4b-7915-4d18-83e7-077d2c42d9bc,ti-str-bbb1d66c-36dd-47af-85d8-583c26959146 | K39: Principal,Stock Cocina | L39: iva_19
B40: Metabisulfito de sodio | C40: 14958 | D40: KG | G40: ti-incat-dbb4ab5d-d383-44df-bb1b-2819d297b20d | H40: Abarrotes | K40: Principal,Stock Cocina | L40: iva_19
A41: ti-ing-2758a41a-4b82-4e9c-b888-e1e3498bbd24 | B41: Miel | C41: 4117 | D41: UN | G41: ti-incat-dbb4ab5d-d383-44df-bb1b-2819d297b20d | H41: Abarrotes | J41: ti-str-e3696e4b-7915-4d18-83e7-077d2c42d9bc,ti-str-eafdd243-ca10-4e67-89d4-50a191eb8e12 | K41: Principal,Stock Servicio | L41: iva_19
A42: ti-ing-55acf21a-55c1-406f-a76b-b81347750e20 | B42: Mostaza | C42: 1336 | D42: KG | G42: ti-incat-dbb4ab5d-d383-44df-bb1b-2819d297b20d | H42: Abarrotes | J42: ti-str-e3696e4b-7915-4d18-83e7-077d2c42d9bc,ti-str-bbb1d66c-36dd-47af-85d8-583c26959146 | K42: Principal,Stock Cocina | L42: iva_19
A43: ti-ing-1a1ad4e7-e7d7-4d58-a706-bfd83210f90b | B43: Oregano kg | C43: 4812 | D43: KG | G43: ti-incat-dbb4ab5d-d383-44df-bb1b-2819d297b20d | H43: Abarrotes | J43: ti-str-e3696e4b-7915-4d18-83e7-077d2c42d9bc,ti-str-bbb1d66c-36dd-47af-85d8-583c26959146,ti-str-36f261ca-0b74-4d79-8a50-81324d9ac308 | K43: Principal,Stock Cocina,Stock Panaderia | L43: iva_19
A44: ti-ing-dc13f521-8e90-4186-98aa-e2a49341278b | B44: Paprika | C44: 3850 | D44: KG | G44: ti-incat-dbb4ab5d-d383-44df-bb1b-2819d297b20d | H44: Abarrotes | J44: ti-str-e3696e4b-7915-4d18-83e7-077d2c42d9bc,ti-str-bbb1d66c-36dd-47af-85d8-583c26959146 | K44: Principal,Stock Cocina | L44: iva_19
A45: ti-ing-999c769d-83cf-47ce-8cb8-90e72bf3771e | B45: Pasas | C45: 2719 | D45: KG | G45: ti-incat-dbb4ab5d-d383-44df-bb1b-2819d297b20d | H45: Abarrotes | J45: ti-str-e3696e4b-7915-4d18-83e7-077d2c42d9bc,ti-str-36f261ca-0b74-4d79-8a50-81324d9ac308 | K45: Principal,Stock Panaderia | L45: iva_19
B46: Pasta aji panca | C46: 14335 | D46: KG | G46: ti-incat-dbb4ab5d-d383-44df-bb1b-2819d297b20d | H46: Abarrotes | J46: ti-str-e3696e4b-7915-4d18-83e7-077d2c42d9bc,ti-str-bbb1d66c-36dd-47af-85d8-583c26959146 | K46: Principal,Stock Cocina | L46: iva_19
A47: ti-ing-dce3151a-440e-4adc-b6f6-75fb61de8ac6 | B47: Pimienta | C47: 11258 | D47: UN | G47: ti-incat-dbb4ab5d-d383-44df-bb1b-2819d297b20d | H47: Abarrotes | J47: ti-str-e3696e4b-7915-4d18-83e7-077d2c42d9bc,ti-str-bbb1d66c-36dd-47af-85d8-583c26959146 | K47: Principal,Stock Cocina | L47: iva_19
A48: ti-ing-5406e51a-e384-417d-9b6d-dfe14303d6be | B48: Polvos de Hornear | C48: 3941.1409 | D48: KG | G48: ti-incat-dbb4ab5d-d383-44df-bb1b-2819d297b20d | H48: Abarrotes | J48: ti-str-e3696e4b-7915-4d18-83e7-077d2c42d9bc,ti-str-36f261ca-0b74-4d79-8a50-81324d9ac308,ti-str-e0754139-882f-4237-83fa-744442ed825f | K48: Principal,Stock Panaderia,Stock Pasteleria | L48: iva_19
A49: ti-ing-904468d1-7aa3-4ea8-a76b-bb2fb6b316e2 | B49: Porotos | C49: 1778 | D49: KG | G49: ti-incat-dbb4ab5d-d383-44df-bb1b-2819d297b20d | H49: Abarrotes | J49: ti-str-e3696e4b-7915-4d18-83e7-077d2c42d9bc,ti-str-bbb1d66c-36dd-47af-85d8-583c26959146 | K49: Principal,Stock Cocina | L49: iva_19
A50: ti-ing-67451d2d-c408-4de8-b583-b73d147b0c3c | B50: Porotos verde | C50: 680 | D50: KG | G50: ti-incat-dbb4ab5d-d383-44df-bb1b-2819d297b20d | H50: Abarrotes | J50: ti-str-bbb1d66c-36dd-47af-85d8-583c26959146 | K50: Stock Cocina | L50: iva_19
A51: ti-ing-2d6c0e54-94ef-4df0-a728-f28c834a70d6 | B51: Pre Mezcla Pan De Pascua (Saco 10 kg) | C51: 3760 | D51: KG | G51: ti-incat-dbb4ab5d-d383-44df-bb1b-2819d297b20d | H51: Abarrotes | J51: ti-str-e3696e4b-7915-4d18-83e7-077d2c42d9bc,ti-str-36f261ca-0b74-4d79-8a50-81324d9ac308 | K51: Principal,Stock Panaderia | L51: iva_19
A52: ti-ing-fb27813f-4cd7-443f-8a10-e933adbefc38 | B52: Puratos desmoldante "PURALIX" (bidon 10 lt) | C52: 6456.9593 | D52: KG | G52: ti-incat-dbb4ab5d-d383-44df-bb1b-2819d297b20d | H52: Abarrotes | J52: ti-str-e3696e4b-7915-4d18-83e7-077d2c42d9bc,ti-str-36f261ca-0b74-4d79-8a50-81324d9ac308 | K52: Principal,Stock Panaderia | L52: iva_19
A53: ti-ing-adcc52a1-e0e4-4266-9ae9-20d8c55afb93 | B53: Puratos granos molde "SOFT GRAIN" | C53: 4742 | D53: KG | G53: ti-incat-dbb4ab5d-d383-44df-bb1b-2819d297b20d | H53: Abarrotes | J53: ti-str-e3696e4b-7915-4d18-83e7-077d2c42d9bc,ti-str-36f261ca-0b74-4d79-8a50-81324d9ac308 | K53: Principal,Stock Panaderia | L53: iva_19
A54: ti-ing-d7848686-6931-4ec1-ba2c-64fafb54502c | B54: Puratos mejorador hallulla "JOKER" | C54: 1779.375 | D54: KG | G54: ti-incat-dbb4ab5d-d383-44df-bb1b-2819d297b20d | H54: Abarrotes | J54: ti-str-e3696e4b-7915-4d18-83e7-077d2c42d9bc,ti-str-36f261ca-0b74-4d79-8a50-81324d9ac308 | K54: Principal,Stock Panaderia | L54: iva_19
A55: ti-ing-0788472c-969e-4253-a6aa-9419b979f617 | B55: puratos mejorador marraqueta "TOUPAN" (caja 20 un./400 gr) | C55: 1968 | D55: KG | G55: ti-incat-dbb4ab5d-d383-44df-bb1b-2819d297b20d | H55: Abarrotes | J55: ti-str-e3696e4b-7915-4d18-83e7-077d2c42d9bc,ti-str-36f261ca-0b74-4d79-8a50-81324d9ac308 | K55: Principal,Stock Panaderia | L55: iva_19
A56: ti-ing-2c5ed605-f331-4f63-bc96-caf004c9d9f1 | B56: puratos mejorador molde "TRIM SOFTER" (caja 12un./1kg) | C56: 4816 | D56: KG | G56: ti-incat-dbb4ab5d-d383-44df-bb1b-2819d297b20d | H56: Abarrotes | J56: ti-str-e3696e4b-7915-4d18-83e7-077d2c42d9bc,ti-str-36f261ca-0b74-4d79-8a50-81324d9ac308 | K56: Principal,Stock Panaderia | L56: iva_19
B57: Quinua mixta | C57: 4596 | D57: KG | G57: ti-incat-dbb4ab5d-d383-44df-bb1b-2819d297b20d | H57: Abarrotes | J57: ti-str-e3696e4b-7915-4d18-83e7-077d2c42d9bc,ti-str-bbb1d66c-36dd-47af-85d8-583c26959146 | K57: Principal,Stock Cocina | L57: iva_19
A58: ti-ing-93b9bb76-8e33-404b-b4a2-19bddccf01ff | B58: Romero | C58: 7135.19 | D58: UN | G58: ti-incat-dbb4ab5d-d383-44df-bb1b-2819d297b20d | H58: Abarrotes | J58: ti-str-e3696e4b-7915-4d18-83e7-077d2c42d9bc,ti-str-bbb1d66c-36dd-47af-85d8-583c26959146 | K58: Principal,Stock Cocina | L58: iva_19
A59: ti-ing-4818468c-bc91-40f7-9fa4-eb19def3bff7 | B59: Sal fina | C59: 290 | D59: KG | G59: ti-incat-dbb4ab5d-d383-44df-bb1b-2819d297b20d | H59: Abarrotes | J59: ti-str-e3696e4b-7915-4d18-83e7-077d2c42d9bc,ti-str-e0754139-882f-4237-83fa-744442ed825f,ti-str-bbb1d66c-36dd-47af-85d8-583c26959146,ti-str-36f261ca-0b74-4d79-8a50-81324d9ac308 | K59: Principal,Stock Pasteleria,Stock Cocina,Stock Panaderia | L59: iva_19
A60: ti-ing-562ebc87-5bd7-439e-9451-999b88fdd759 | B60: Salsa De Tomate | C60: 1587 | D60: KG | G60: ti-incat-dbb4ab5d-d383-44df-bb1b-2819d297b20d | H60: Abarrotes | J60: ti-str-e3696e4b-7915-4d18-83e7-077d2c42d9bc,ti-str-bbb1d66c-36dd-47af-85d8-583c26959146 | K60: Principal,Stock Cocina | L60: iva_19
A61: ti-ing-4f8ac25a-9411-4a59-806f-62cee4c4e0f1 | B61: Salsa inglesa | C61: 4035 | D61: Kg | G61: ti-incat-dbb4ab5d-d383-44df-bb1b-2819d297b20d | H61: Abarrotes | J61: ti-str-e3696e4b-7915-4d18-83e7-077d2c42d9bc,ti-str-bbb1d66c-36dd-47af-85d8-583c26959146 | K61: Principal,Stock Cocina | L61: iva_19
A62: ti-ing-9f3dba64-3cca-408b-ac1e-45359966da75 | B62: Salsa Soya | C62: 1625 | D62: KG | G62: ti-incat-dbb4ab5d-d383-44df-bb1b-2819d297b20d | H62: Abarrotes | J62: ti-str-e3696e4b-7915-4d18-83e7-077d2c42d9bc,ti-str-bbb1d66c-36dd-47af-85d8-583c26959146 | K62: Principal,Stock Cocina | L62: iva_19
A63: ti-ing-7e2cee8d-1717-48ff-96be-290c5aa01461 | B63: Semilla cilantro | C63: 4874.396 | D63: KG | G63: ti-incat-dbb4ab5d-d383-44df-bb1b-2819d297b20d | H63: Abarrotes | J63: ti-str-e3696e4b-7915-4d18-83e7-077d2c42d9bc,ti-str-bbb1d66c-36dd-47af-85d8-583c26959146 | K63: Principal,Stock Cocina | L63: iva_19
A64: ti-ing-f3669215-5eea-4b87-8743-83d65563f01d | B64: Semilla De Zapallo kg | C64: 5550 | D64: Kg | G64: ti-incat-dbb4ab5d-d383-44df-bb1b-2819d297b20d | H64: Abarrotes | J64: ti-str-e3696e4b-7915-4d18-83e7-077d2c42d9bc,ti-str-36f261ca-0b74-4d79-8a50-81324d9ac308 | K64: Principal,Stock Panaderia | L64: iva_19
A65: ti-ing-ee9260f2-296c-423d-bf8d-ee978626dfa5 | B65: Sesamo Blanco | C65: 4164 | D65: KG | G65: ti-incat-dbb4ab5d-d383-44df-bb1b-2819d297b20d | H65: Abarrotes | J65: ti-str-e3696e4b-7915-4d18-83e7-077d2c42d9bc,ti-str-36f261ca-0b74-4d79-8a50-81324d9ac308 | K65: Principal,Stock Panaderia | L65: iva_19
A66: ti-ing-eb1cdfba-1bad-4930-a6f4-b0ad48b55576 | B66: Sesamo Negro | C66: 5441 | D66: KG | G66: ti-incat-dbb4ab5d-d383-44df-bb1b-2819d297b20d | H66: Abarrotes | J66: ti-str-e3696e4b-7915-4d18-83e7-077d2c42d9bc,ti-str-36f261ca-0b74-4d79-8a50-81324d9ac308 | K66: Principal,Stock Panaderia | L66: iva_19
A67: ti-ing-802599df-3955-46c2-9418-b1ef4176ed29 | B67: STEVIA LIQUIDA | C67: 3444 | D67: un | G67: ti-incat-dbb4ab5d-d383-44df-bb1b-2819d297b20d | H67: Abarrotes | J67: ti-str-e0754139-882f-4237-83fa-744442ed825f,ti-str-e3696e4b-7915-4d18-83e7-077d2c42d9bc | K67: Stock Pasteleria,Principal | L67: iva_19
A68: ti-ing-c5dc548f-f0a9-4499-a4b3-23a34458dbfa | B68: Te en Bolsa Caja | C68: 46.5 | D68: UN | G68: ti-incat-dbb4ab5d-d383-44df-bb1b-2819d297b20d | H68: Abarrotes | J68: ti-str-e3696e4b-7915-4d18-83e7-077d2c42d9bc,ti-str-eafdd243-ca10-4e67-89d4-50a191eb8e12 | K68: Principal,Stock Servicio | L68: iva_19
A69: ti-ing-7a052395-bb4e-4c4d-a1cf-c498a5386bb1 | B69: Tomillo | C69: 9885 | D69: UN | G69: ti-incat-dbb4ab5d-d383-44df-bb1b-2819d297b20d | H69: Abarrotes | J69: ti-str-e3696e4b-7915-4d18-83e7-077d2c42d9bc,ti-str-bbb1d66c-36dd-47af-85d8-583c26959146 | K69: Principal,Stock Cocina | L69: iva_19
... A124: ti-ing-177ceabf-271a-400b-97bf-bba4e34859a7 | B124: PE pulpa mango mix | C124: 178 | D124: UN | G124: ti-incat-273410a5-2a0b-4153-8b12-0d0e5d529167 | H124: Bebestibles | J124: ti-str-eafdd243-ca10-4e67-89d4-50a191eb8e12 | K124: Stock Servicio | L124: iva_19
B125: Primaveral | C125: 910 | D125: UN | G125: ti-incat-273410a5-2a0b-4153-8b12-0d0e5d529167 | H125: Bebestibles | J125: ti-str-eafdd243-ca10-4e67-89d4-50a191eb8e12 | K125: Stock Servicio | L125: iva_19
A126: ti-ing-27365f0e-3bbd-48de-bc63-541a722a9716 | B126: Pulpa Chirimoya | C126: 5290 | D126: KG | G126: ti-incat-273410a5-2a0b-4153-8b12-0d0e5d529167 | H126: Bebestibles | J126: ti-str-e3696e4b-7915-4d18-83e7-077d2c42d9bc,ti-str-eafdd243-ca10-4e67-89d4-50a191eb8e12 | K126: Principal,Stock Servicio | L126: iva_19
A127: ti-ing-c61601c6-808a-4073-be84-3536b4f328af | B127: Pulpa Frambuesa | C127: 6800 | D127: KG | G127: ti-incat-273410a5-2a0b-4153-8b12-0d0e5d529167 | H127: Bebestibles | J127: ti-str-e3696e4b-7915-4d18-83e7-077d2c42d9bc,ti-str-eafdd243-ca10-4e67-89d4-50a191eb8e12 | K127: Principal,Stock Servicio | L127: iva_19
A128: ti-ing-0a6dd713-e7a7-4872-af86-42c45add6bdf | B128: Pulpa Frutilla | C128: 2950 | D128: KG | G128: ti-incat-273410a5-2a0b-4153-8b12-0d0e5d529167 | H128: Bebestibles | J128: ti-str-e3696e4b-7915-4d18-83e7-077d2c42d9bc,ti-str-eafdd243-ca10-4e67-89d4-50a191eb8e12 | K128: Principal,Stock Servicio | L128: iva_19
A129: ti-ing-cfdaf79a-6246-42a9-afab-7cba8ae515ca | B129: Pulpa Mango | C129: 4490 | D129: KG | G129: ti-incat-273410a5-2a0b-4153-8b12-0d0e5d529167 | H129: Bebestibles | J129: ti-str-e3696e4b-7915-4d18-83e7-077d2c42d9bc,ti-str-eafdd243-ca10-4e67-89d4-50a191eb8e12 | K129: Principal,Stock Servicio | L129: iva_19
A130: ti-ing-9d873397-e256-4684-ace9-5de471cf4acc | B130: Pulpa Maracuya C/Pepas | C130: 5590 | D130: KG | G130: ti-incat-273410a5-2a0b-4153-8b12-0d0e5d529167 | H130: Bebestibles | J130: ti-str-e3696e4b-7915-4d18-83e7-077d2c42d9bc,ti-str-e0754139-882f-4237-83fa-744442ed825f | K130: Principal,Stock Pasteleria | L130: iva_19
A131: ti-ing-836eb301-0b64-45eb-89be-be872a9297e4 | B131: Pulpa Maracuya S/Pepas | C131: 5990 | D131: KG | G131: ti-incat-273410a5-2a0b-4153-8b12-0d0e5d529167 | H131: Bebestibles | J131: ti-str-e3696e4b-7915-4d18-83e7-077d2c42d9bc,ti-str-eafdd243-ca10-4e67-89d4-50a191eb8e12 | K131: Principal,Stock Servicio | L131: iva_19
A132: ti-ing-f5eb30b4-794d-42f5-a2dd-41746ad30690 | B132: Pulpa Melon | C132: 3100 | D132: KG | G132: ti-incat-273410a5-2a0b-4153-8b12-0d0e5d529167 | H132: Bebestibles | J132: ti-str-e3696e4b-7915-4d18-83e7-077d2c42d9bc,ti-str-eafdd243-ca10-4e67-89d4-50a191eb8e12 | K132: Principal,Stock Servicio | L132: iva_19
A133: ti-ing-f5eb30b4-794d-42f5-a2dd-41746ad30691 | B133: Pulpa naranja | C133: 4715 | D133: KG | G133: ti-incat-273410a5-2a0b-4153-8b12-0d0e5d529167 | H133: Bebestibles | J133: ti-str-eafdd243-ca10-4e67-89d4-50a191eb8e12 | K133: Principal,Stock Servicio | L133: iva_19
A134: ti-ing-05169dad-82a2-4ad5-abca-f8039dfa9275 | B134: Pulpa Piña | C134: 3600 | D134: KG | G134: ti-incat-273410a5-2a0b-4153-8b12-0d0e5d529167 | H134: Bebestibles | J134: ti-str-e3696e4b-7915-4d18-83e7-077d2c42d9bc,ti-str-eafdd243-ca10-4e67-89d4-50a191eb8e12 | K134: Principal,Stock Servicio | L134: iva_19
A135: ti-ing-17dc3026-6b74-4df3-a8d6-9e28e708f104 | B135: Sprite 350 cc | C135: 606.5583 | D135: UN | G135: ti-incat-273410a5-2a0b-4153-8b12-0d0e5d529167 | H135: Bebestibles | J135: ti-str-e3696e4b-7915-4d18-83e7-077d2c42d9bc,ti-str-eafdd243-ca10-4e67-89d4-50a191eb8e12 | K135: Principal,Stock Servicio | L135: iva_19
A136: ti-ing-925cd36a-a250-4073-9075-f890c840ff54 | B136: Sprite Zero 350 cc | C136: 606.5583 | D136: UN | G136: ti-incat-273410a5-2a0b-4153-8b12-0d0e5d529167 | H136: Bebestibles | J136: ti-str-e3696e4b-7915-4d18-83e7-077d2c42d9bc,ti-str-eafdd243-ca10-4e67-89d4-50a191eb8e12 | K136: Principal,Stock Servicio | L136: iva_19
A137: ti-ing-f76fed7a-9b00-4997-8f9e-73bd5e249be8 | B137: Café Descafeinado 504 (caja) | C137: 519.9 | D137: un | H137: Cafetería | J137: ti-str-e3696e4b-7915-4d18-83e7-077d2c42d9bc,ti-str-eafdd243-ca10-4e67-89d4-50a191eb8e12 | K137: Principal,Stock Servicio | L137: iva_19
A138: ti-ing-7999dd71-66f3-480c-ac93-ff256e0b1f76 | B138: Café grano 1k | C138: 18705 | D138: KG | H138: Cafetería | J138: ti-str-e3696e4b-7915-4d18-83e7-077d2c42d9bc,ti-str-eafdd243-ca10-4e67-89d4-50a191eb8e12 | K138: Principal,Stock Servicio | L138: iva_19
A139: ti-ing-73128f7c-be42-49de-8aba-c9a9a60678a0 | B139: Chai En Polvo 504 (bolsa 1,8 kg) | C139: 21250 | D139: Kg | H139: Cafetería | J139: ti-str-e3696e4b-7915-4d18-83e7-077d2c42d9bc,ti-str-eafdd243-ca10-4e67-89d4-50a191eb8e12 | K139: Principal,Stock Servicio | L139: iva_19
A140: ti-ing-b9b128e7-f3d3-420f-8ded-36abfbbf64c9 | B140: Chocolate en polvo 504 (bolsa 2 kg) | C140: 13991.5 | D140: KG | H140: Cafetería | J140: ti-str-e3696e4b-7915-4d18-83e7-077d2c42d9bc,ti-str-eafdd243-ca10-4e67-89d4-50a191eb8e12 | K140: Principal,Stock Servicio | L140: iva_19
A141: ti-ing-60b67dd6-c83d-47fb-ac43-4a397918a54a | B141: Chocolate Liquido | C141: 3360 | D141: un | H141: Cafetería | J141: ti-str-e3696e4b-7915-4d18-83e7-077d2c42d9bc,ti-str-eafdd243-ca10-4e67-89d4-50a191eb8e12 | K141: Principal,Stock Servicio | L141: iva_19
A142: ti-ing-7d8d02af-ef1d-4855-8b49-db888802881d | B142: Mashmellows | C142: 1512.733 | D142: Kg | H142: Cafetería | J142: ti-str-e3696e4b-7915-4d18-83e7-077d2c42d9bc,ti-str-eafdd243-ca10-4e67-89d4-50a191eb8e12 | K142: Principal,Stock Servicio | L142: iva_19
B143: Matcha | C143: 133333 | D143: KG | H143: Cafetería | J143: ti-str-e3696e4b-7915-4d18-83e7-077d2c42d9bc,ti-str-eafdd243-ca10-4e67-89d4-50a191eb8e12 | K143: Principal,Stock Servicio | L143: iva_19
B144: Metilcelulosa | C144: 14958 | D144: KG | H144: Cafetería | J144: ti-str-e3696e4b-7915-4d18-83e7-077d2c42d9bc,ti-str-eafdd243-ca10-4e67-89d4-50a191eb8e12 | K144: Principal,Stock Servicio | L144: iva_19
A145: ti-ing-63ac2eac-77a4-4a08-942d-2708cdee1af2 | B145: Syrup Esencia Amaretto 504 (750cc) | C145: 14565.33 | D145: un | H145: Cafetería | J145: ti-str-e3696e4b-7915-4d18-83e7-077d2c42d9bc,ti-str-eafdd243-ca10-4e67-89d4-50a191eb8e12 | K145: Principal,Stock Servicio | L145: iva_19
A146: ti-ing-c849733f-e001-48f8-93bc-ba7bae902493 | B146: Syrup Esencia Avellana 504 (750cc) | C146: 14565.33 | D146: un | H146: Cafetería | J146: ti-str-e3696e4b-7915-4d18-83e7-077d2c42d9bc,ti-str-eafdd243-ca10-4e67-89d4-50a191eb8e12 | K146: Principal,Stock Servicio | L146: iva_19
A147: ti-ing-5a1c804e-222c-4669-a220-bc3d876665b0 | B147: Syrup Esencia Canela 504 (750cc) | C147: 14565.33 | D147: un | H147: Cafetería | J147: ti-str-e3696e4b-7915-4d18-83e7-077d2c42d9bc,ti-str-eafdd243-ca10-4e67-89d4-50a191eb8e12 | K147: Principal,Stock Servicio | L147: iva_19
A148: ti-ing-2afee1a4-7742-432e-9582-e7f1946d3437 | B148: Syrup Esencia Caramelo 504 (750cc) | C148: 14565.33 | D148: UN | H148: Cafetería | J148: ti-str-e3696e4b-7915-4d18-83e7-077d2c42d9bc,ti-str-eafdd243-ca10-4e67-89d4-50a191eb8e12 | K148: Principal,Stock Servicio | L148: iva_19
A149: ti-ing-19d34ff0-8607-4466-898f-87c0df45d86b | B149: Syrup Esencia Chai 504 (750cc) | C149: 16000 | D149: UN | H149: Cafetería | J149: ti-str-e3696e4b-7915-4d18-83e7-077d2c42d9bc,ti-str-eafdd243-ca10-4e67-89d4-50a191eb8e12 | K149: Principal,Stock Servicio | L149: iva_19
A150: ti-ing-6e43ce5e-9ab8-48be-8833-ad92e26a4c39 | B150: Syrup Esencia coco 504 (750cc) | C150: 14565.33 | D150: UN | H150: Cafetería | J150: ti-str-e3696e4b-7915-4d18-83e7-077d2c42d9bc,ti-str-eafdd243-ca10-4e67-89d4-50a191eb8e12 | K150: Principal,Stock Servicio | L150: iva_19
A151: ti-ing-b0ff34ea-0e7e-455b-90d0-99c07f16b527 | B151: Syrup Esencia Menta 504 (750cc) | C151: 14565.33 | D151: UN | H151: Cafetería | J151: ti-str-e3696e4b-7915-4d18-83e7-077d2c42d9bc,ti-str-eafdd243-ca10-4e67-89d4-50a191eb8e12 | K151: Principal,Stock Servicio | L151: iva_19
A152: ti-ing-6e0beb61-027c-4b38-9367-426237c4b1f2 | B152: Syrup Esencia Vainilla 504 (750cc) | C152: 14565.33 | D152: UN | H152: Cafetería | J152: ti-str-e3696e4b-7915-4d18-83e7-077d2c42d9bc,ti-str-eafdd243-ca10-4e67-89d4-50a191eb8e12 | K152: Principal,Stock Servicio | L152: iva_19
B153: Asado carnicero | C153: 6656.013 | D153: KG | G153: ti-incat-6abdda1d-9573-494b-8461-4f87db108819 | H153: Carnes y Aves | J153: ti-str-bbb1d66c-36dd-47af-85d8-583c26959146 | K153: Stock Cocina | L153: iva_19
A154: ti-ing-d1d9b75c-fbe2-43ab-ae2b-b16de0e4d23a | B154: Carne Molida kg | C154: 3552.6667 | D154: KG | G154: ti-incat-6abdda1d-9573-494b-8461-4f87db108819 | H154: Carnes y Aves | J154: ti-str-bbb1d66c-36dd-47af-85d8-583c26959146 | K154: Stock Cocina | L154: iva_19
B155: Chuleta Centro | C155: 3623 | D155: KG | G155: ti-incat-6abdda1d-9573-494b-8461-4f87db108819 | H155: Carnes y Aves | J155: ti-str-bbb1d66c-36dd-47af-85d8-583c26959146 | K155: Stock Cocina | L155: iva_19
A156: ti-ing-f9071122-333f-445e-9d6e-66ae8844a033 | B156: Jamon Ahumado kg | C156: 5034.167 | D156: UN | G156: ti-incat-6abdda1d-9573-494b-8461-4f87db108819 | H156: Carnes y Aves | J156: ti-str-bbb1d66c-36dd-47af-85d8-583c26959146,ti-str-36f261ca-0b74-4d79-8a50-81324d9ac308 | K156: Stock Cocina,Stock Panaderia | L156: iva_19
...

Sheet principal
A1: Principal | B1: Principal
A2: ID PRODUCTO | B2: PRODUCTO | C2: STOCK | D2: PEDIDO | E2: UN MEDIDA | F2: CATEGORIA | G2: Valorizado Neto | H2: IVA (19%) | I2: Total Bruto | J2: PEDIDO
A3: =IFERROR(__xludf.DUMMYFUNCTION("FILTER('UNIVERSO PRODUCTOS'!A1:B958, ISNUMBER(SEARCH(A1, 'UNIVERSO PRODUCTOS'!K1:K958)))"),"ti-ing-b69bd6ae-ccae-4801-af83-bece901d304f") -> ti-ing-b69bd6ae-ccae-4801-af83-bece901d304f | B3: =IFERROR(__xludf.DUMMYFUNCTION("""COMPUTED_VALUE"""),"Aceite oliva extra virgen 5 lts") -> Aceite oliva extra virgen 5 lts | C3: 5 | D3: =IFERROR(__xludf.DUMMYFUNCTION("FILTER('UNIVERSO PRODUCTOS'!C1:C961, ISNUMBER(SEARCH(A1, 'UNIVERSO PRODUCTOS'!K1:K961)))"),4646.2) -> 4646.2 | E3: =IFERROR(__xludf.DUMMYFUNCTION("FILTER('UNIVERSO PRODUCTOS'!D1:D958, ISNUMBER(SEARCH(A1, 'UNIVERSO PRODUCTOS'!K1:K958)))"),"LT") -> LT | F3: =IFERROR(__xludf.DUMMYFUNCTION("FILTER('UNIVERSO PRODUCTOS'!H1:H958, ISNUMBER(SEARCH(A1, 'UNIVERSO PRODUCTOS'!K1:K958)))"),"Abarrotes") -> Abarrotes | G3: =(C3)*D3 -> 23231 | H3: =G3*19% -> 4413.89 | I3: =G3+H3 -> 27644.89
A4: =IFERROR(__xludf.DUMMYFUNCTION("""COMPUTED_VALUE"""),"ti-ing-5a1041f6-5fed-4ae0-8d00-dee7d47968a3") -> ti-ing-5a1041f6-5fed-4ae0-8d00-dee7d47968a3 | B4: =IFERROR(__xludf.DUMMYFUNCTION("""COMPUTED_VALUE"""),"Aceite vegetal 900 ml") -> Aceite vegetal 900 ml | C4: 22 | D4: =IFERROR(__xludf.DUMMYFUNCTION("""COMPUTED_VALUE"""),1540.6) -> 1540.6 | E4: =IFERROR(__xludf.DUMMYFUNCTION("""COMPUTED_VALUE"""),"UN") -> UN | F4: =IFERROR(__xludf.DUMMYFUNCTION("""COMPUTED_VALUE"""),"Abarrotes") -> Abarrotes | G4: =(C4)*D4 -> 33893.2 | H4: =G4*19% -> 6439.708 | I4: =G4+H4 -> 40332.908 | L4: Abarrotes | M4: Aseo | N4: Bebestibles | O4: Cafetería | P4: Carnes y Aves | Q4: Desechables | R4: Frutas y Verduras | S4: Harinas | T4: Ovolacteos | U4: Pastelería | V4: Pescados y Mariscos | W4: P.Terminados | X4: Té | Y4: Valor Neto
A5: =IFERROR(__xludf.DUMMYFUNCTION("""COMPUTED_VALUE"""),"ti-ing-581e5046-d41b-44fd-981a-fa5ec2c4d4ba") -> ti-ing-581e5046-d41b-44fd-981a-fa5ec2c4d4ba | B5: =IFERROR(__xludf.DUMMYFUNCTION("""COMPUTED_VALUE"""),"Ajinomoto") -> Ajinomoto | C5: 0 | D5: =IFERROR(__xludf.DUMMYFUNCTION("""COMPUTED_VALUE"""),3354) -> 3354 | E5: =IFERROR(__xludf.DUMMYFUNCTION("""COMPUTED_VALUE"""),"kg") -> kg | F5: =IFERROR(__xludf.DUMMYFUNCTION("""COMPUTED_VALUE"""),"Abarrotes") -> Abarrotes | G5: =(C5)*D5 -> 0 | H5: =G5*19% -> 0 | I5: =G5+H5 -> 0
A6: =IFERROR(__xludf.DUMMYFUNCTION("""COMPUTED_VALUE"""),"ti-ing-65292276-c9a9-4569-b8ff-19a5a3fea424") -> ti-ing-65292276-c9a9-4569-b8ff-19a5a3fea424 | B6: =IFERROR(__xludf.DUMMYFUNCTION("""COMPUTED_VALUE"""),"Anis kg") -> Anis kg | C6: 0 | D6: =IFERROR(__xludf.DUMMYFUNCTION("""COMPUTED_VALUE"""),13854) -> 13854 | E6: =IFERROR(__xludf.DUMMYFUNCTION("""COMPUTED_VALUE"""),"Kg") -> Kg | F6: =IFERROR(__xludf.DUMMYFUNCTION("""COMPUTED_VALUE"""),"Abarrotes") -> Abarrotes | G6: =(C6)*D6 -> 0 | H6: =G6*19% -> 0 | I6: =G6+H6 -> 0 | L6: =SUM(G3:G69) -> 614037.05 | M6: =SUM(G70:G103) -> 181265.8 | N6: =SUM(G104:G124) -> 600175.24 | O6: =SUM(G125:G140) -> 601709.13 | P6: =SUM(G288) -> 55904.425 | Q6: =SUM(G141:G216) -> 6014459.6 | R6: =SUM(G217:G218) -> 109881 | S6: =SUM(G219:G222) -> 513224 | T6: =SUM(G223:G240,G289:G290) -> 1024809.5 | U6: =SUM(G241:G276) -> 788878.55 | W6: =SUM(G277) -> 0 | X6: =SUM(G278:G288) -> 75720.425 | Y6: =SUM(L6:X6) -> 10580065
A7: =IFERROR(__xludf.DUMMYFUNCTION("""COMPUTED_VALUE"""),"ti-ing-bfd5d10e-d265-4e6e-b05a-79c836269380") -> ti-ing-bfd5d10e-d265-4e6e-b05a-79c836269380 | B7: =IFERROR(__xludf.DUMMYFUNCTION("""COMPUTED_VALUE"""),"Arroz (colacion)") -> Arroz (colacion) | C7: 15 | D7: =IFERROR(__xludf.DUMMYFUNCTION("""COMPUTED_VALUE"""),905) -> 905 | E7: =IFERROR(__xludf.DUMMYFUNCTION("""COMPUTED_VALUE"""),"KG") -> KG | F7: =IFERROR(__xludf.DUMMYFUNCTION("""COMPUTED_VALUE"""),"Abarrotes") -> Abarrotes | G7: =(C7)*D7 -> 13575 | H7: =G7*19% -> 2579.25 | I7: =G7+H7 -> 16154.25
A8: =IFERROR(__xludf.DUMMYFUNCTION("""COMPUTED_VALUE"""),"ti-ing-5c316419-1759-4d90-bb2e-e9025a87d122") -> ti-ing-5c316419-1759-4d90-bb2e-e9025a87d122 | B8: =IFERROR(__xludf.DUMMYFUNCTION("""COMPUTED_VALUE"""),"Atun Coliseo Al Agua") -> Atun Coliseo Al Agua | C8: 0 | D8: =IFERROR(__xludf.DUMMYFUNCTION("""COMPUTED_VALUE"""),879) -> 879 | E8: =IFERROR(__xludf.DUMMYFUNCTION("""COMPUTED_VALUE"""),"UN") -> UN | F8: =IFERROR(__xludf.DUMMYFUNCTION("""COMPUTED_VALUE"""),"Abarrotes") -> Abarrotes | G8: =(C8)*D8 -> 0 | H8: =G8*19% -> 0 | I8: =G8+H8 -> 0 | L8: Abarrotes | M8: Aseo | N8: Bebestibles | O8: Cafetería | P8: Carnes y Aves | Q8: Desechables | R8: Frutas y Verduras | S8: Harinas | T8: Ovolacteos | U8: Pastelería | V8: Pescados y Mariscos | W8: P.Terminados | X8: Té | Y8: Valor Bruto
A9: =IFERROR(__xludf.DUMMYFUNCTION("""COMPUTED_VALUE"""),"ti-ing-363a5ec1-8d6b-4612-be6a-7a19b61ab7e2") -> ti-ing-363a5ec1-8d6b-4612-be6a-7a19b61ab7e2 | B9: =IFERROR(__xludf.DUMMYFUNCTION("""COMPUTED_VALUE"""),"Atun Dorasol Al Agua") -> Atun Dorasol Al Agua | C9: 0 | D9: =IFERROR(__xludf.DUMMYFUNCTION("""COMPUTED_VALUE"""),879) -> 879 | E9: =IFERROR(__xludf.DUMMYFUNCTION("""COMPUTED_VALUE"""),"UN") -> UN | F9: =IFERROR(__xludf.DUMMYFUNCTION("""COMPUTED_VALUE"""),"Abarrotes") -> Abarrotes | G9: =(C9)*D9 -> 0 | H9: =G9*19% -> 0 | I9: =G9+H9 -> 0
A10: =IFERROR(__xludf.DUMMYFUNCTION("""COMPUTED_VALUE"""),"ti-ing-c1414efc-1614-40c6-a7e8-2f6efb3e0401") -> ti-ing-c1414efc-1614-40c6-a7e8-2f6efb3e0401 | B10: =IFERROR(__xludf.DUMMYFUNCTION("""COMPUTED_VALUE"""),"Avena") -> Avena | C10: 7 | D10: =IFERROR(__xludf.DUMMYFUNCTION("""COMPUTED_VALUE"""),1050) -> 1050 | E10: =IFERROR(__xludf.DUMMYFUNCTION("""COMPUTED_VALUE"""),"KG") -> KG | F10: =IFERROR(__xludf.DUMMYFUNCTION("""COMPUTED_VALUE"""),"Abarrotes") -> Abarrotes | G10: =(C10)*D10 -> 7350 | H10: =G10*19% -> 1396.5 | I10: =G10+H10 -> 8746.5 | L10: =SUM(I3:I69) -> 730704.09 | M10: =SUM(I70:I103) -> 215706.31 | N10: =SUM(I104:I124) -> 696885.23 | O10: =SUM(I125:I140) -> 716033.87 | P10: =SUM(I288) -> 66526.265 | Q10: =SUM(I141:I216) -> 7157206.9 | R10: =SUM(I217:I218) -> 130758.39 | S10: =SUM(I219:I222) -> 610736.56 | T10: =SUM(I223:I240,I289:I290) -> 1219523.2 | U10: =SUM(I241:I276) -> 938765.48 | W10: =SUM(I277) -> 0 | X10: =SUM(I278:I288) -> 90107.305 | Y10: =SUM(L10:X10) -> 12572954
A11: =IFERROR(__xludf.DUMMYFUNCTION("""COMPUTED_VALUE"""),"ti-ing-531d1d9b-814d-49bc-9bbf-06be4ae2e6d5") -> ti-ing-531d1d9b-814d-49bc-9bbf-06be4ae2e6d5 | B11: =IFERROR(__xludf.DUMMYFUNCTION("""COMPUTED_VALUE"""),"Azucar blanca") -> Azucar blanca | C11: 50 | D11: =IFERROR(__xludf.DUMMYFUNCTION("""COMPUTED_VALUE"""),939.9985) -> 939.9985 | E11: =IFERROR(__xludf.DUMMYFUNCTION("""COMPUTED_VALUE"""),"KG") -> KG | F11: =IFERROR(__xludf.DUMMYFUNCTION("""COMPUTED_VALUE"""),"Abarrotes") -> Abarrotes | G11: =(C11)*D11 -> 46999.925 | H11: =G11*19% -> 8929.9857 | I11: =G11+H11 -> 55929.911
B12: =IFERROR(__xludf.DUMMYFUNCTION("""COMPUTED_VALUE"""),"Azúcar blanca por kilo") -> Azúcar blanca por kilo | C12: 0 | D12: =IFERROR(__xludf.DUMMYFUNCTION("""COMPUTED_VALUE"""),930) -> 930 | E12: =IFERROR(__xludf.DUMMYFUNCTION("""COMPUTED_VALUE"""),"KG") -> KG | F12: =IFERROR(__xludf.DUMMYFUNCTION("""COMPUTED_VALUE"""),"Abarrotes") -> Abarrotes | G12: =(C12)*D12 -> 0 | H12: =G12*19% -> 0 | I12: =G12+H12 -> 0 | L12: =(L10*100)/$Y$10 -> 5.8117139 | M12: =(M10*100)/$Y$10 -> 1.7156375 | N12: =(N10*100)/$Y$10 -> 5.5427329 | O12: =(O10*100)/$Y$10 -> 5.6950331 | P12: =(P10*100)/$Y$10 -> 0.52912201 | Q12: =(Q10*100)/$Y$10 -> 56.925422 | R12: =(R10*100)/$Y$10 -> 1.0399974 | S12: =(S10*100)/$Y$10 -> 4.8575424 | ... X12: =(X10*100)/$Y$10 -> 0.71667571
A13: =IFERROR(__xludf.DUMMYFUNCTION("""COMPUTED_VALUE"""),"ti-ing-c4486ce7-85c4-49c5-ac82-4d98b0798d01") -> ti-ing-c4486ce7-85c4-49c5-ac82-4d98b0798d01 | B13: =IFERROR(__xludf.DUMMYFUNCTION("""COMPUTED_VALUE"""),"Azucar rubia") -> Azucar rubia | C13: 5 | D13: =IFERROR(__xludf.DUMMYFUNCTION("""COMPUTED_VALUE"""),1047) -> 1047 | E13: =IFERROR(__xludf.DUMMYFUNCTION("""COMPUTED_VALUE"""),"KG") -> KG | F13: =IFERROR(__xludf.DUMMYFUNCTION("""COMPUTED_VALUE"""),"Abarrotes") -> Abarrotes | G13: =(C13)*D13 -> 5235 | H13: =G13*19% -> 994.65 | I13: =G13+H13 -> 6229.65
A14: =IFERROR(__xludf.DUMMYFUNCTION("""COMPUTED_VALUE"""),"ti-ing-63a7f9f9-77ff-45f4-9e3f-3feff0b73432") -> ti-ing-63a7f9f9-77ff-45f4-9e3f-3feff0b73432 | B14: =IFERROR(__xludf.DUMMYFUNCTION("""COMPUTED_VALUE"""),"Café tarro grande (desayuno)") -> Café tarro grande (desayuno) | C14: 4 | D14: =IFERROR(__xludf.DUMMYFUNCTION("""COMPUTED_VALUE"""),12032) -> 12032 | E14: =IFERROR(__xludf.DUMMYFUNCTION("""COMPUTED_VALUE"""),"UN") -> UN | F14: =IFERROR(__xludf.DUMMYFUNCTION("""COMPUTED_VALUE"""),"Abarrotes") -> Abarrotes | G14: =(C14)*D14 -> 48128 | H14: =G14*19% -> 9144.32 | I14: =G14+H14 -> 57272.32
A15: =IFERROR(__xludf.DUMMYFUNCTION("""COMPUTED_VALUE"""),"ti-ing-f57e1d6d-2d59-440c-a741-794a5d5d1359") -> ti-ing-f57e1d6d-2d59-440c-a741-794a5d5d1359 | B15: =IFERROR(__xludf.DUMMYFUNCTION("""COMPUTED_VALUE"""),"Chia kg") -> Chia kg | C15: 0 | D15: =IFERROR(__xludf.DUMMYFUNCTION("""COMPUTED_VALUE"""),4152) -> 4152 | E15: =IFERROR(__xludf.DUMMYFUNCTION("""COMPUTED_VALUE"""),"UN") -> UN | F15: =IFERROR(__xludf.DUMMYFUNCTION("""COMPUTED_VALUE"""),"Abarrotes") -> Abarrotes | G15: =(C15)*D15 -> 0 | H15: =G15*19% -> 0 | I15: =G15+H15 -> 0
A16: =IFERROR(__xludf.DUMMYFUNCTION("""COMPUTED_VALUE"""),"ti-ing-b908bdf8-4d68-4e4a-bca8-67edb76d6236") -> ti-ing-b908bdf8-4d68-4e4a-bca8-67edb76d6236 | B16: =IFERROR(__xludf.DUMMYFUNCTION("""COMPUTED_VALUE"""),"Chips Chocolate Negro kg") -> Chips Chocolate Negro kg | C16: 9 | D16: =IFERROR(__xludf.DUMMYFUNCTION("""COMPUTED_VALUE"""),6977.75) -> 6977.75 | E16: =IFERROR(__xludf.DUMMYFUNCTION("""COMPUTED_VALUE"""),"KG") -> KG | F16: =IFERROR(__xludf.DUMMYFUNCTION("""COMPUTED_VALUE"""),"Abarrotes") -> Abarrotes | G16: =(C16)*D16 -> 62799.75 | H16: =G16*19% -> 11931.952 | I16: =G16+H16 -> 74731.702
A17: =IFERROR(__xludf.DUMMYFUNCTION("""COMPUTED_VALUE"""),"ti-ing-89800579-a778-4a4e-8895-e0cc7ed6a986") -> ti-ing-89800579-a778-4a4e-8895-e0cc7ed6a986 | B17: =IFERROR(__xludf.DUMMYFUNCTION("""COMPUTED_VALUE"""),"Coco Laminado") -> Coco Laminado | C17: 2 | D17: =IFERROR(__xludf.DUMMYFUNCTION("""COMPUTED_VALUE"""),8474) -> 8474 | E17: =IFERROR(__xludf.DUMMYFUNCTION("""COMPUTED_VALUE"""),"KG") -> KG | F17: =IFERROR(__xludf.DUMMYFUNCTION("""COMPUTED_VALUE"""),"Abarrotes") -> Abarrotes | G17: =(C17)*D17 -> 16948 | H17: =G17*19% -> 3220.12 | I17: =G17+H17 -> 20168.12
A18: =IFERROR(__xludf.DUMMYFUNCTION("""COMPUTED_VALUE"""),"ti-ing-a396335b-a1d5-46a1-874a-de8bd1a3a0de") -> ti-ing-a396335b-a1d5-46a1-874a-de8bd1a3a0de | B18: =IFERROR(__xludf.DUMMYFUNCTION("""COMPUTED_VALUE"""),"Coco Rallado") -> Coco Rallado | C18: 3 | D18: =IFERROR(__xludf.DUMMYFUNCTION("""COMPUTED_VALUE"""),4188) -> 4188 | E18: =IFERROR(__xludf.DUMMYFUNCTION("""COMPUTED_VALUE"""),"KG") -> KG | F18: =IFERROR(__xludf.DUMMYFUNCTION("""COMPUTED_VALUE"""),"Abarrotes") -> Abarrotes | G18: =(C18)*D18 -> 12564 | H18: =G18*19% -> 2387.16 | I18: =G18+H18 -> 14951.16
A19: =IFERROR(__xludf.DUMMYFUNCTION("""COMPUTED_VALUE"""),"ti-ing-280562df-e2c6-469c-bfaf-8f7361fb5c74") -> ti-ing-280562df-e2c6-469c-bfaf-8f7361fb5c74 | B19: =IFERROR(__xludf.DUMMYFUNCTION("""COMPUTED_VALUE"""),"COMINO") -> COMINO | C19: 0 | D19: =IFERROR(__xludf.DUMMYFUNCTION("""COMPUTED_VALUE"""),5250) -> 5250 | E19: =IFERROR(__xludf.DUMMYFUNCTION("""COMPUTED_VALUE"""),"KG") -> KG | F19: =IFERROR(__xludf.DUMMYFUNCTION("""COMPUTED_VALUE"""),"Abarrotes") -> Abarrotes | G19: =(C19)*D19 -> 0 | H19: =G19*19% -> 0 | I19: =G19+H19 -> 0
A20: =IFERROR(__xludf.DUMMYFUNCTION("""COMPUTED_VALUE"""),"ti-ing-55e22a4e-70ba-4bfe-9ef6-78d09a6c71b6") -> ti-ing-55e22a4e-70ba-4bfe-9ef6-78d09a6c71b6 | B20: =IFERROR(__xludf.DUMMYFUNCTION("""COMPUTED_VALUE"""),"Curcuma") -> Curcuma | C20: 1 | D20: =IFERROR(__xludf.DUMMYFUNCTION("""COMPUTED_VALUE"""),5437) -> 5437 | E20: =IFERROR(__xludf.DUMMYFUNCTION("""COMPUTED_VALUE"""),"KG") -> KG | F20: =IFERROR(__xludf.DUMMYFUNCTION("""COMPUTED_VALUE"""),"Abarrotes") -> Abarrotes | G20: =(C20)*D20 -> 5437 | H20: =G20*19% -> 1033.03 | I20: =G20+H20 -> 6470.03
A21: =IFERROR(__xludf.DUMMYFUNCTION("""COMPUTED_VALUE"""),"ti-ing-064cb0f3-6635-4de8-915c-d57502a19286") -> ti-ing-064cb0f3-6635-4de8-915c-d57502a19286 | B21: =IFERROR(__xludf.DUMMYFUNCTION("""COMPUTED_VALUE"""),"Esencia vainilla") -> Esencia vainilla | C21: 0 | D21: =IFERROR(__xludf.DUMMYFUNCTION("""COMPUTED_VALUE"""),1000) -> 1000 | E21: =IFERROR(__xludf.DUMMYFUNCTION("""COMPUTED_VALUE"""),"LT") -> LT | F21: =IFERROR(__xludf.DUMMYFUNCTION("""COMPUTED_VALUE"""),"Abarrotes") -> Abarrotes | G21: =(C21)*D21 -> 0 | H21: =G21*19% -> 0 | I21: =G21+H21 -> 0
A22: =IFERROR(__xludf.DUMMYFUNCTION("""COMPUTED_VALUE"""),"ti-ing-2fbc1c56-3286-4d64-8ddd-b547296361a3") -> ti-ing-2fbc1c56-3286-4d64-8ddd-b547296361a3 | B22: =IFERROR(__xludf.DUMMYFUNCTION("""COMPUTED_VALUE"""),"Espaguetti") -> Espaguetti | C22: 2 | D22: =IFERROR(__xludf.DUMMYFUNCTION("""COMPUTED_VALUE"""),407) -> 407 | E22: =IFERROR(__xludf.DUMMYFUNCTION("""COMPUTED_VALUE"""),"UN") -> UN | F22: =IFERROR(__xludf.DUMMYFUNCTION("""COMPUTED_VALUE"""),"Abarrotes") -> Abarrotes | G22: =(C22)*D22 -> 814 | H22: =G22*19% -> 154.66 | I22: =G22+H22 -> 968.66
A23: =IFERROR(__xludf.DUMMYFUNCTION("""COMPUTED_VALUE"""),"ti-ing-446530ff-42dc-41f9-9208-1b6c8dded86f") -> ti-ing-446530ff-42dc-41f9-9208-1b6c8dded86f | B23: =IFERROR(__xludf.DUMMYFUNCTION("""COMPUTED_VALUE"""),"Espirales") -> Espirales | C23: 0 | D23: =IFERROR(__xludf.DUMMYFUNCTION("""COMPUTED_VALUE"""),399) -> 399 | E23: =IFERROR(__xludf.DUMMYFUNCTION("""COMPUTED_VALUE"""),"UN") -> UN | F23: =IFERROR(__xludf.DUMMYFUNCTION("""COMPUTED_VALUE"""),"Abarrotes") -> Abarrotes | G23: =(C23)*D23 -> 0 | H23: =G23*19% -> 0 | I23: =G23+H23 -> 0
A24: =IFERROR(__xludf.DUMMYFUNCTION("""COMPUTED_VALUE"""),"ti-ing-150d078f-94cc-4527-a524-b16516d0adfa") -> ti-ing-150d078f-94cc-4527-a524-b16516d0adfa | B24: =IFERROR(__xludf.DUMMYFUNCTION("""COMPUTED_VALUE"""),"Fruta Confitada") -> Fruta Confitada | C24: 4 | D24: =IFERROR(__xludf.DUMMYFUNCTION("""COMPUTED_VALUE"""),3500) -> 3500 | E24: =IFERROR(__xludf.DUMMYFUNCTION("""COMPUTED_VALUE"""),"KG") -> KG | F24: =IFERROR(__xludf.DUMMYFUNCTION("""COMPUTED_VALUE"""),"Abarrotes") -> Abarrotes | G24: =(C24)*D24 -> 14000 | H24: =G24*19% -> 2660 | I24: =G24+H24 -> 16660
A25: =IFERROR(__xludf.DUMMYFUNCTION("""COMPUTED_VALUE"""),"ti-ing-11a33780-09cc-47f7-b11c-89e4b6139bb9") -> ti-ing-11a33780-09cc-47f7-b11c-89e4b6139bb9 | B25: =IFERROR(__xludf.DUMMYFUNCTION("""COMPUTED_VALUE"""),"Garbanzos") -> Garbanzos | C25: 1 | D25: =IFERROR(__xludf.DUMMYFUNCTION("""COMPUTED_VALUE"""),2291.25) -> 2291.25 | E25: =IFERROR(__xludf.DUMMYFUNCTION("""COMPUTED_VALUE"""),"KG") -> KG | F25: =IFERROR(__xludf.DUMMYFUNCTION("""COMPUTED_VALUE"""),"Abarrotes") -> Abarrotes | G25: =(C25)*D25 -> 2291.25 | H25: =G25*19% -> 435.3375 | I25: =G25+H25 -> 2726.5875
A26: =IFERROR(__xludf.DUMMYFUNCTION("""COMPUTED_VALUE"""),"ti-ing-af062f27-295c-456a-9ce5-77fbb725f339") -> ti-ing-af062f27-295c-456a-9ce5-77fbb725f339 | B26: =IFERROR(__xludf.DUMMYFUNCTION("""COMPUTED_VALUE"""),"Helado Chocolate") -> Helado Chocolate | C26: 0 | D26: =IFERROR(__xludf.DUMMYFUNCTION("""COMPUTED_VALUE"""),2360.6) -> 2360.6 | E26: =IFERROR(__xludf.DUMMYFUNCTION("""COMPUTED_VALUE"""),"LT") -> LT | F26: =IFERROR(__xludf.DUMMYFUNCTION("""COMPUTED_VALUE"""),"Abarrotes") -> Abarrotes | G26: =(C26)*D26 -> 0 | H26: =G26*19% -> 0 | I26: =G26+H26 -> 0
B27: =IFERROR(__xludf.DUMMYFUNCTION("""COMPUTED_VALUE"""),"Helado frutilla") -> Helado frutilla | C27: 0 | D27: =IFERROR(__xludf.DUMMYFUNCTION("""COMPUTED_VALUE"""),3469) -> 3469 | E27: =IFERROR(__xludf.DUMMYFUNCTION("""COMPUTED_VALUE"""),"LT") -> LT | F27: =IFERROR(__xludf.DUMMYFUNCTION("""COMPUTED_VALUE"""),"Abarrotes") -> Abarrotes | G27: =(C27)*D27 -> 0 | H27: =G27*19% -> 0 | I27: =G27+H27 -> 0
A28: =IFERROR(__xludf.DUMMYFUNCTION("""COMPUTED_VALUE"""),"ti-ing-12dbd538-5012-4d25-8c02-7d0b4f3fdf45") -> ti-ing-12dbd538-5012-4d25-8c02-7d0b4f3fdf45 | B28: =IFERROR(__xludf.DUMMYFUNCTION("""COMPUTED_VALUE"""),"Helado Vainilla") -> Helado Vainilla | C28: 0 | D28: =IFERROR(__xludf.DUMMYFUNCTION("""COMPUTED_VALUE"""),2979) -> 2979 | E28: =IFERROR(__xludf.DUMMYFUNCTION("""COMPUTED_VALUE"""),"LT") -> LT | F28: =IFERROR(__xludf.DUMMYFUNCTION("""COMPUTED_VALUE"""),"Abarrotes") -> Abarrotes | G28: =(C28)*D28 -> 0 | H28: =G28*19% -> 0 | I28: =G28+H28 -> 0
A29: =IFERROR(__xludf.DUMMYFUNCTION("""COMPUTED_VALUE"""),"ti-ing-e6ff2cd2-0729-44b9-b0d3-457299c1ead8") -> ti-ing-e6ff2cd2-0729-44b9-b0d3-457299c1ead8 | B29: =IFERROR(__xludf.DUMMYFUNCTION("""COMPUTED_VALUE"""),"Huevos Arizona") -> Huevos Arizona | C29: 1.08 | D29: =IFERROR(__xludf.DUMMYFUNCTION("""COMPUTED_VALUE"""),138) -> 138 | E29: =IFERROR(__xludf.DUMMYFUNCTION("""COMPUTED_VALUE"""),"UN") -> UN | F29: =IFERROR(__xludf.DUMMYFUNCTION("""COMPUTED_VALUE"""),"Abarrotes") -> Abarrotes | G29: =(C29)*D29 -> 149.04 | H29: =G29*19% -> 28.3176 | I29: =G29+H29 -> 177.3576
A30: =IFERROR(__xludf.DUMMYFUNCTION("""COMPUTED_VALUE"""),"ti-ing-06898fd0-9448-431b-9bad-3526a93cf181") -> ti-ing-06898fd0-9448-431b-9bad-3526a93cf181 | B30: =IFERROR(__xludf.DUMMYFUNCTION("""COMPUTED_VALUE"""),"Ketchup kg") -> Ketchup kg | C30: 0 | D30: =IFERROR(__xludf.DUMMYFUNCTION("""COMPUTED_VALUE"""),1550) -> 1550 | E30: =IFERROR(__xludf.DUMMYFUNCTION("""COMPUTED_VALUE"""),"KG") -> KG | F30: =IFERROR(__xludf.DUMMYFUNCTION("""COMPUTED_VALUE"""),"Abarrotes") -> Abarrotes | G30: =(C30)*D30 -> 0 | H30: =G30*19% -> 0 | I30: =G30+H30 -> 0
A31: =IFERROR(__xludf.DUMMYFUNCTION("""COMPUTED_VALUE"""),"ti-ing-f3eeca8c-b308-4136-a438-0f68fc53c279") -> ti-ing-f3eeca8c-b308-4136-a438-0f68fc53c279 | B31: =IFERROR(__xludf.DUMMYFUNCTION("""COMPUTED_VALUE"""),"Lasagne Chef") -> Lasagne Chef | C31: 6.6 | D31: =IFERROR(__xludf.DUMMYFUNCTION("""COMPUTED_VALUE"""),3831.8) -> 3831.8 | E31: =IFERROR(__xludf.DUMMYFUNCTION("""COMPUTED_VALUE"""),"kg") -> kg | F31: =IFERROR(__xludf.DUMMYFUNCTION("""COMPUTED_VALUE"""),"Abarrotes") -> Abarrotes | G31: =(C31)*D31 -> 25289.88 | H31: =G31*19% -> 4805.0772 | I31: =G31+H31 -> 30094.957
A32: =IFERROR(__xludf.DUMMYFUNCTION("""COMPUTED_VALUE"""),"ti-ing-20a9682d-4a6c-42c4-a3ed-312cab8df904") -> ti-ing-20a9682d-4a6c-42c4-a3ed-312cab8df904 | B32: =IFERROR(__xludf.DUMMYFUNCTION("""COMPUTED_VALUE"""),"Laurel") -> Laurel | C32: 0.3 | D32: =IFERROR(__xludf.DUMMYFUNCTION("""COMPUTED_VALUE"""),75280) -> 75280 | E32: =IFERROR(__xludf.DUMMYFUNCTION("""COMPUTED_VALUE"""),"KG") -> KG | F32: =IFERROR(__xludf.DUMMYFUNCTION("""COMPUTED_VALUE"""),"Abarrotes") -> Abarrotes | G32: =(C32)*D32 -> 22584 | H32: =G32*19% -> 4290.96 | I32: =G32+H32 -> 26874.96
A33: =IFERROR(__xludf.DUMMYFUNCTION("""COMPUTED_VALUE"""),"ti-ing-772eef79-e2de-41fa-b52c-f097abd8b4a8") -> ti-ing-772eef79-e2de-41fa-b52c-f097abd8b4a8 | B33: =IFERROR(__xludf.DUMMYFUNCTION("""COMPUTED_VALUE"""),"Leche Entera En Polvo") -> Leche Entera En Polvo | C33: 7.2 | D33: =IFERROR(__xludf.DUMMYFUNCTION("""COMPUTED_VALUE"""),7079.167) -> 7079.167 | E33: =IFERROR(__xludf.DUMMYFUNCTION("""COMPUTED_VALUE"""),"KG") -> KG | F33: =IFERROR(__xludf.DUMMYFUNCTION("""COMPUTED_VALUE"""),"Abarrotes") -> Abarrotes | G33: =(C33)*D33 -> 50970.002 | H33: =G33*19% -> 9684.3005 | I33: =G33+H33 -> 60654.303
A34: =IFERROR(__xludf.DUMMYFUNCTION("""COMPUTED_VALUE"""),"ti-ing-a5f32751-2fe1-4388-acd1-977dd4d921a6") -> ti-ing-a5f32751-2fe1-4388-acd1-977dd4d921a6 | B34: =IFERROR(__xludf.DUMMYFUNCTION("""COMPUTED_VALUE"""),"Lentejas (colacion personal)") -> Lentejas (colacion personal) | C34: 0 | D34: =IFERROR(__xludf.DUMMYFUNCTION("""COMPUTED_VALUE"""),2118) -> 2118 | E34: =IFERROR(__xludf.DUMMYFUNCTION("""COMPUTED_VALUE"""),"KG") -> KG | F34: =IFERROR(__xludf.DUMMYFUNCTION("""COMPUTED_VALUE"""),"Abarrotes") -> Abarrotes | G34: =(C34)*D34 -> 0 | H34: =G34*19% -> 0 | I34: =G34+H34 -> 0
A35: =IFERROR(__xludf.DUMMYFUNCTION("""COMPUTED_VALUE"""),"ti-ing-0ec3786c-eec8-4a04-af8d-bda30eac5549") -> ti-ing-0ec3786c-eec8-4a04-af8d-bda30eac5549 | B35: =IFERROR(__xludf.DUMMYFUNCTION("""COMPUTED_VALUE"""),"Levadura seca (Unidad)") -> Levadura seca (Unidad) | C35: 8 | D35: =IFERROR(__xludf.DUMMYFUNCTION("""COMPUTED_VALUE"""),1711) -> 1711 | E35: =IFERROR(__xludf.DUMMYFUNCTION("""COMPUTED_VALUE"""),"UN") -> UN | F35: =IFERROR(__xludf.DUMMYFUNCTION("""COMPUTED_VALUE"""),"Abarrotes") -> Abarrotes | G35: =(C35)*D35 -> 13688 | H35: =G35*19% -> 2600.72 | I35: =G35+H35 -> 16288.72
A36: =IFERROR(__xludf.DUMMYFUNCTION("""COMPUTED_VALUE"""),"ti-ing-b41eeb59-c8ac-4580-b11d-bbd7dc537fd3") -> ti-ing-b41eeb59-c8ac-4580-b11d-bbd7dc537fd3 | B36: =IFERROR(__xludf.DUMMYFUNCTION("""COMPUTED_VALUE"""),"Linaza kg") -> Linaza kg | C36: 1 | D36: =IFERROR(__xludf.DUMMYFUNCTION("""COMPUTED_VALUE"""),2995) -> 2995 | E36: =IFERROR(__xludf.DUMMYFUNCTION("""COMPUTED_VALUE"""),"KG") -> KG | F36: =IFERROR(__xludf.DUMMYFUNCTION("""COMPUTED_VALUE"""),"Abarrotes") -> Abarrotes | G36: =(C36)*D36 -> 2995 | H36: =G36*19% -> 569.05 | I36: =G36+H36 -> 3564.05
A37: =IFERROR(__xludf.DUMMYFUNCTION("""COMPUTED_VALUE"""),"ti-ing-69061f8d-e4d9-4fc4-b44e-0cd173ebf8f3") -> ti-ing-69061f8d-e4d9-4fc4-b44e-0cd173ebf8f3 | B37: =IFERROR(__xludf.DUMMYFUNCTION("""COMPUTED_VALUE"""),"Maicena kg") -> Maicena kg | C37: 2 | D37: =IFERROR(__xludf.DUMMYFUNCTION("""COMPUTED_VALUE"""),1582) -> 1582 | E37: =IFERROR(__xludf.DUMMYFUNCTION("""COMPUTED_VALUE"""),"KG") -> KG | F37: =IFERROR(__xludf.DUMMYFUNCTION("""COMPUTED_VALUE"""),"Abarrotes") -> Abarrotes | G37: =(C37)*D37 -> 3164 | H37: =G37*19% -> 601.16 | I37: =G37+H37 -> 3765.16
A38: =IFERROR(__xludf.DUMMYFUNCTION("""COMPUTED_VALUE"""),"ti-ing-3dba6697-1589-49e0-8e6e-951b48b7d160") -> ti-ing-3dba6697-1589-49e0-8e6e-951b48b7d160 | B38: =IFERROR(__xludf.DUMMYFUNCTION("""COMPUTED_VALUE"""),"Mayonesa Hellmans") -> Mayonesa Hellmans | C38: 5.7 | D38: =IFERROR(__xludf.DUMMYFUNCTION("""COMPUTED_VALUE"""),3989.362) -> 3989.362 | E38: =IFERROR(__xludf.DUMMYFUNCTION("""COMPUTED_VALUE"""),"Kg") -> Kg | F38: =IFERROR(__xludf.DUMMYFUNCTION("""COMPUTED_VALUE"""),"Abarrotes") -> Abarrotes | G38: =(C38)*D38 -> 22739.363 | H38: =G38*19% -> 4320.479 | I38: =G38+H38 -> 27059.842
B39: =IFERROR(__xludf.DUMMYFUNCTION("""COMPUTED_VALUE"""),"Metabisulfito de sodio") -> Metabisulfito de sodio | C39: 0 | D39: =IFERROR(__xludf.DUMMYFUNCTION("""COMPUTED_VALUE"""),14958) -> 14958 | E39: =IFERROR(__xludf.DUMMYFUNCTION("""COMPUTED_VALUE"""),"KG") -> KG | F39: =IFERROR(__xludf.DUMMYFUNCTION("""COMPUTED_VALUE"""),"Abarrotes") -> Abarrotes | G39: =(C39)*D39 -> 0 | H39: =G39*19% -> 0 | I39: =G39+H39 -> 0
A40: =IFERROR(__xludf.DUMMYFUNCTION("""COMPUTED_VALUE"""),"ti-ing-2758a41a-4b82-4e9c-b888-e1e3498bbd24") -> ti-ing-2758a41a-4b82-4e9c-b888-e1e3498bbd24 | B40: =IFERROR(__xludf.DUMMYFUNCTION("""COMPUTED_VALUE"""),"Miel") -> Miel | C40: 1 | D40: =IFERROR(__xludf.DUMMYFUNCTION("""COMPUTED_VALUE"""),4117) -> 4117 | E40: =IFERROR(__xludf.DUMMYFUNCTION("""COMPUTED_VALUE"""),"UN") -> UN | F40: =IFERROR(__xludf.DUMMYFUNCTION("""COMPUTED_VALUE"""),"Abarrotes") -> Abarrotes | G40: =(C40)*D40 -> 4117 | H40: =G40*19% -> 782.23 | I40: =G40+H40 -> 4899.23
A41: =IFERROR(__xludf.DUMMYFUNCTION("""COMPUTED_VALUE"""),"ti-ing-55acf21a-55c1-406f-a76b-b81347750e20") -> ti-ing-55acf21a-55c1-406f-a76b-b81347750e20 | B41: =IFERROR(__xludf.DUMMYFUNCTION("""COMPUTED_VALUE"""),"Mostaza") -> Mostaza | C41: 1 | D41: =IFERROR(__xludf.DUMMYFUNCTION("""COMPUTED_VALUE"""),1336) -> 1336 | E41: =IFERROR(__xludf.DUMMYFUNCTION("""COMPUTED_VALUE"""),"KG") -> KG | F41: =IFERROR(__xludf.DUMMYFUNCTION("""COMPUTED_VALUE"""),"Abarrotes") -> Abarrotes | G41: =(C41)*D41 -> 1336 | H41: =G41*19% -> 253.84 | I41: =G41+H41 -> 1589.84
A42: =IFERROR(__xludf.DUMMYFUNCTION("""COMPUTED_VALUE"""),"ti-ing-1a1ad4e7-e7d7-4d58-a706-bfd83210f90b") -> ti-ing-1a1ad4e7-e7d7-4d58-a706-bfd83210f90b | B42: =IFERROR(__xludf.DUMMYFUNCTION("""COMPUTED_VALUE"""),"Oregano kg") -> Oregano kg | C42: 1 | D42: =IFERROR(__xludf.DUMMYFUNCTION("""COMPUTED_VALUE"""),4812) -> 4812 | E42: =IFERROR(__xludf.DUMMYFUNCTION("""COMPUTED_VALUE"""),"KG") -> KG | F42: =IFERROR(__xludf.DUMMYFUNCTION("""COMPUTED_VALUE"""),"Abarrotes") -> Abarrotes | G42: =(C42)*D42 -> 4812 | H42: =G42*19% -> 914.28 | I42: =G42+H42 -> 5726.28
A43: =IFERROR(__xludf.DUMMYFUNCTION("""COMPUTED_VALUE"""),"ti-ing-dc13f521-8e90-4186-98aa-e2a49341278b") -> ti-ing-dc13f521-8e90-4186-98aa-e2a49341278b | B43: =IFERROR(__xludf.DUMMYFUNCTION("""COMPUTED_VALUE"""),"Paprika") -> Paprika | C43: 1 | D43: =IFERROR(__xludf.DUMMYFUNCTION("""COMPUTED_VALUE"""),3850) -> 3850 | E43: =IFERROR(__xludf.DUMMYFUNCTION("""COMPUTED_VALUE"""),"KG") -> KG | F43: =IFERROR(__xludf.DUMMYFUNCTION("""COMPUTED_VALUE"""),"Abarrotes") -> Abarrotes | G43: =(C43)*D43 -> 3850 | H43: =G43*19% -> 731.5 | I43: =G43+H43 -> 4581.5
A44: =IFERROR(__xludf.DUMMYFUNCTION("""COMPUTED_VALUE"""),"ti-ing-999c769d-83cf-47ce-8cb8-90e72bf3771e") -> ti-ing-999c769d-83cf-47ce-8cb8-90e72bf3771e | B44: =IFERROR(__xludf.DUMMYFUNCTION("""COMPUTED_VALUE"""),"Pasas") -> Pasas | C44: 0 | D44: =IFERROR(__xludf.DUMMYFUNCTION("""COMPUTED_VALUE"""),2719) -> 2719 | E44: =IFERROR(__xludf.DUMMYFUNCTION("""COMPUTED_VALUE"""),"KG") -> KG | F44: =IFERROR(__xludf.DUMMYFUNCTION("""COMPUTED_VALUE"""),"Abarrotes") -> Abarrotes | G44: =(C44)*D44 -> 0 | H44: =G44*19% -> 0 | I44: =G44+H44 -> 0
B45: =IFERROR(__xludf.DUMMYFUNCTION("""COMPUTED_VALUE"""),"Pasta aji panca") -> Pasta aji panca | C45: 0 | D45: =IFERROR(__xludf.DUMMYFUNCTION("""COMPUTED_VALUE"""),14335) -> 14335 | E45: =IFERROR(__xludf.DUMMYFUNCTION("""COMPUTED_VALUE"""),"KG") -> KG | F45: =IFERROR(__xludf.DUMMYFUNCTION("""COMPUTED_VALUE"""),"Abarrotes") -> Abarrotes | G45: =(C45)*D45 -> 0 | H45: =G45*19% -> 0 | I45: =G45+H45 -> 0
A46: =IFERROR(__xludf.DUMMYFUNCTION("""COMPUTED_VALUE"""),"ti-ing-dce3151a-440e-4adc-b6f6-75fb61de8ac6") -> ti-ing-dce3151a-440e-4adc-b6f6-75fb61de8ac6 | B46: =IFERROR(__xludf.DUMMYFUNCTION("""COMPUTED_VALUE"""),"Pimienta") -> Pimienta | C46: 1 | D46: =IFERROR(__xludf.DUMMYFUNCTION("""COMPUTED_VALUE"""),11258) -> 11258 | E46: =IFERROR(__xludf.DUMMYFUNCTION("""COMPUTED_VALUE"""),"UN") -> UN | F46: =IFERROR(__xludf.DUMMYFUNCTION("""COMPUTED_VALUE"""),"Abarrotes") -> Abarrotes | G46: =(C46)*D46 -> 11258 | H46: =G46*19% -> 2139.02 | I46: =G46+H46 -> 13397.02
A47: =IFERROR(__xludf.DUMMYFUNCTION("""COMPUTED_VALUE"""),"ti-ing-5406e51a-e384-417d-9b6d-dfe14303d6be") -> ti-ing-5406e51a-e384-417d-9b6d-dfe14303d6be | B47: =IFERROR(__xludf.DUMMYFUNCTION("""COMPUTED_VALUE"""),"Polvos de Hornear") -> Polvos de Hornear | C47: 12 | D47: =IFERROR(__xludf.DUMMYFUNCTION("""COMPUTED_VALUE"""),3941.140889) -> 3941.1409 | E47: =IFERROR(__xludf.DUMMYFUNCTION("""COMPUTED_VALUE"""),"KG") -> KG | F47: =IFERROR(__xludf.DUMMYFUNCTION("""COMPUTED_VALUE"""),"Abarrotes") -> Abarrotes | G47: =(C47)*D47 -> 47293.691 | H47: =G47*19% -> 8985.8012 | I47: =G47+H47 -> 56279.492
A48: =IFERROR(__xludf.DUMMYFUNCTION("""COMPUTED_VALUE"""),"ti-ing-904468d1-7aa3-4ea8-a76b-bb2fb6b316e2") -> ti-ing-904468d1-7aa3-4ea8-a76b-bb2fb6b316e2 | B48: =IFERROR(__xludf.DUMMYFUNCTION("""COMPUTED_VALUE"""),"Porotos") -> Porotos | C48: 0 | D48: =IFERROR(__xludf.DUMMYFUNCTION("""COMPUTED_VALUE"""),1778) -> 1778 | E48: =IFERROR(__xludf.DUMMYFUNCTION("""COMPUTED_VALUE"""),"KG") -> KG | F48: =IFERROR(__xludf.DUMMYFUNCTION("""COMPUTED_VALUE"""),"Abarrotes") -> Abarrotes | G48: =(C48)*D48 -> 0 | H48: =G48*19% -> 0 | I48: =G48+H48 -> 0
A49: =IFERROR(__xludf.DUMMYFUNCTION("""COMPUTED_VALUE"""),"ti-ing-2d6c0e54-94ef-4df0-a728-f28c834a70d6") -> ti-ing-2d6c0e54-94ef-4df0-a728-f28c834a70d6 | B49: =IFERROR(__xludf.DUMMYFUNCTION("""COMPUTED_VALUE"""),"Pre Mezcla Pan De Pascua (Saco 10 kg)") -> Pre Mezcla Pan De Pascua (Saco 10 kg) | C49: 0 | D49: =IFERROR(__xludf.DUMMYFUNCTION("""COMPUTED_VALUE"""),3760) -> 3760 | E49: =IFERROR(__xludf.DUMMYFUNCTION("""COMPUTED_VALUE"""),"KG") -> KG | F49: =IFERROR(__xludf.DUMMYFUNCTION("""COMPUTED_VALUE"""),"Abarrotes") -> Abarrotes | G49: =(C49)*D49 -> 0 | H49: =G49*19% -> 0 | I49: =G49+H49 -> 0
A50: =IFERROR(__xludf.DUMMYFUNCTION("""COMPUTED_VALUE"""),"ti-ing-fb27813f-4cd7-443f-8a10-e933adbefc38") -> ti-ing-fb27813f-4cd7-443f-8a10-e933adbefc38 | B50: =IFERROR(__xludf.DUMMYFUNCTION("""COMPUTED_VALUE"""),"Puratos desmoldante ""PURALIX"" (bidon 10 lt)") -> Puratos desmoldante "PURALIX" (bidon 10 lt) | C50: 0 | D50: =IFERROR(__xludf.DUMMYFUNCTION("""COMPUTED_VALUE"""),6456.959305) -> 6456.9593 | E50: =IFERROR(__xludf.DUMMYFUNCTION("""COMPUTED_VALUE"""),"KG") -> KG | F50: =IFERROR(__xludf.DUMMYFUNCTION("""COMPUTED_VALUE"""),"Abarrotes") -> Abarrotes | G50: =(C50)*D50 -> 0 | H50: =G50*19% -> 0 | I50: =G50+H50 -> 0
A51: =IFERROR(__xludf.DUMMYFUNCTION("""COMPUTED_VALUE"""),"ti-ing-adcc52a1-e0e4-4266-9ae9-20d8c55afb93") -> ti-ing-adcc52a1-e0e4-4266-9ae9-20d8c55afb93 | B51: =IFERROR(__xludf.DUMMYFUNCTION("""COMPUTED_VALUE"""),"Puratos granos molde ""SOFT GRAIN""") -> Puratos granos molde "SOFT GRAIN" | C51: 0 | D51: =IFERROR(__xludf.DUMMYFUNCTION("""COMPUTED_VALUE"""),4742) -> 4742 | E51: =IFERROR(__xludf.DUMMYFUNCTION("""COMPUTED_VALUE"""),"KG") -> KG | F51: =IFERROR(__xludf.DUMMYFUNCTION("""COMPUTED_VALUE"""),"Abarrotes") -> Abarrotes | G51: =(C51)*D51 -> 0 | H51: =G51*19% -> 0 | I51: =G51+H51 -> 0
A52: =IFERROR(__xludf.DUMMYFUNCTION("""COMPUTED_VALUE"""),"ti-ing-d7848686-6931-4ec1-ba2c-64fafb54502c") -> ti-ing-d7848686-6931-4ec1-ba2c-64fafb54502c | B52: =IFERROR(__xludf.DUMMYFUNCTION("""COMPUTED_VALUE"""),"Puratos mejorador hallulla ""JOKER""") -> Puratos mejorador hallulla "JOKER" | C52: 10 | D52: =IFERROR(__xludf.DUMMYFUNCTION("""COMPUTED_VALUE"""),1779.375) -> 1779.375 | E52: =IFERROR(__xludf.DUMMYFUNCTION("""COMPUTED_VALUE"""),"KG") -> KG | F52: =IFERROR(__xludf.DUMMYFUNCTION("""COMPUTED_VALUE"""),"Abarrotes") -> Abarrotes | G52: =(C52)*D52 -> 17793.75 | H52: =G52*19% -> 3380.8125 | I52: =G52+H52 -> 21174.562
A53: =IFERROR(__xludf.DUMMYFUNCTION("""COMPUTED_VALUE"""),"ti-ing-0788472c-969e-4253-a6aa-9419b979f617") -> ti-ing-0788472c-969e-4253-a6aa-9419b979f617 | B53: =IFERROR(__xludf.DUMMYFUNCTION("""COMPUTED_VALUE"""),"puratos mejorador marraqueta ""TOUPAN"" (caja 20 un./400 gr)") -> puratos mejorador marraqueta "TOUPAN" (caja 20 un./400 gr) | C53: 4.4 | D53: =IFERROR(__xludf.DUMMYFUNCTION("""COMPUTED_VALUE"""),1968) -> 1968 | E53: =IFERROR(__xludf.DUMMYFUNCTION("""COMPUTED_VALUE"""),"KG") -> KG | F53: =IFERROR(__xludf.DUMMYFUNCTION("""COMPUTED_VALUE"""),"Abarrotes") -> Abarrotes | G53: =(C53)*D53 -> 8659.2 | H53: =G53*19% -> 1645.248 | I53: =G53+H53 -> 10304.448
A54: =IFERROR(__xludf.DUMMYFUNCTION("""COMPUTED_VALUE"""),"ti-ing-2c5ed605-f331-4f63-bc96-caf004c9d9f1") -> ti-ing-2c5ed605-f331-4f63-bc96-caf004c9d9f1 | B54: =IFERROR(__xludf.DUMMYFUNCTION("""COMPUTED_VALUE"""),"puratos mejorador molde ""TRIM SOFTER"" (caja 12un./1kg)") -> puratos mejorador molde "TRIM SOFTER" (caja 12un./1kg) | C54: 6 | D54: =IFERROR(__xludf.DUMMYFUNCTION("""COMPUTED_VALUE"""),4816) -> 4816 | E54: =IFERROR(__xludf.DUMMYFUNCTION("""COMPUTED_VALUE"""),"KG") -> KG | F54: =IFERROR(__xludf.DUMMYFUNCTION("""COMPUTED_VALUE"""),"Abarrotes") -> Abarrotes | G54: =(C54)*D54 -> 28896 | H54: =G54*19% -> 5490.24 | I54: =G54+H54 -> 34386.24
B55: =IFERROR(__xludf.DUMMYFUNCTION("""COMPUTED_VALUE"""),"Quinua mixta") -> Quinua mixta | C55: 1 | D55: =IFERROR(__xludf.DUMMYFUNCTION("""COMPUTED_VALUE"""),4596) -> 4596 | E55: =IFERROR(__xludf.DUMMYFUNCTION("""COMPUTED_VALUE"""),"KG") -> KG | F55: =IFERROR(__xludf.DUMMYFUNCTION("""COMPUTED_VALUE"""),"Abarrotes") -> Abarrotes | G55: =(C55)*D55 -> 4596 | H55: =G55*19% -> 873.24 | I55: =G55+H55 -> 5469.24
A56: =IFERROR(__xludf.DUMMYFUNCTION("""COMPUTED_VALUE"""),"ti-ing-93b9bb76-8e33-404b-b4a2-19bddccf01ff") -> ti-ing-93b9bb76-8e33-404b-b4a2-19bddccf01ff | B56: =IFERROR(__xludf.DUMMYFUNCTION("""COMPUTED_VALUE"""),"Romero") -> Romero | C56: 0 | D56: =IFERROR(__xludf.DUMMYFUNCTION("""COMPUTED_VALUE"""),7135.19) -> 7135.19 | E56: =IFERROR(__xludf.DUMMYFUNCTION("""COMPUTED_VALUE"""),"UN") -> UN | F56: =IFERROR(__xludf.DUMMYFUNCTION("""COMPUTED_VALUE"""),"Abarrotes") -> Abarrotes | G56: =(C56)*D56 -> 0 | H56: =G56*19% -> 0 | I56: =G56+H56 -> 0
A57: =IFERROR(__xludf.DUMMYFUNCTION("""COMPUTED_VALUE"""),"ti-ing-4818468c-bc91-40f7-9fa4-eb19def3bff7") -> ti-ing-4818468c-bc91-40f7-9fa4-eb19def3bff7 | B57: =IFERROR(__xludf.DUMMYFUNCTION("""COMPUTED_VALUE"""),"Sal fina") -> Sal fina | C57: 24 | D57: =IFERROR(__xludf.DUMMYFUNCTION("""COMPUTED_VALUE"""),290) -> 290 | E57: =IFERROR(__xludf.DUMMYFUNCTION("""COMPUTED_VALUE"""),"KG") -> KG | F57: =IFERROR(__xludf.DUMMYFUNCTION("""COMPUTED_VALUE"""),"Abarrotes") -> Abarrotes | G57: =(C57)*D57 -> 6960 | H57: =G57*19% -> 1322.4 | I57: =G57+H57 -> 8282.4
A58: =IFERROR(__xludf.DUMMYFUNCTION("""COMPUTED_VALUE"""),"ti-ing-562ebc87-5bd7-439e-9451-999b88fdd759") -> ti-ing-562ebc87-5bd7-439e-9451-999b88fdd759 | B58: =IFERROR(__xludf.DUMMYFUNCTION("""COMPUTED_VALUE"""),"Salsa De Tomate") -> Salsa De Tomate | C58: 4 | D58: =IFERROR(__xludf.DUMMYFUNCTION("""COMPUTED_VALUE"""),1587) -> 1587 | E58: =IFERROR(__xludf.DUMMYFUNCTION("""COMPUTED_VALUE"""),"KG") -> KG | F58: =IFERROR(__xludf.DUMMYFUNCTION("""COMPUTED_VALUE"""),"Abarrotes") -> Abarrotes | G58: =(C58)*D58 -> 6348 | H58: =G58*19% -> 1206.12 | I58: =G58+H58 -> 7554.12
A59: =IFERROR(__xludf.DUMMYFUNCTION("""COMPUTED_VALUE"""),"ti-ing-4f8ac25a-9411-4a59-806f-62cee4c4e0f1") -> ti-ing-4f8ac25a-9411-4a59-806f-62cee4c4e0f1 | B59: =IFERROR(__xludf.DUMMYFUNCTION("""COMPUTED_VALUE"""),"Salsa inglesa") -> Salsa inglesa | C59: 1 | D59: =IFERROR(__xludf.DUMMYFUNCTION("""COMPUTED_VALUE"""),4035) -> 4035 | E59: =IFERROR(__xludf.DUMMYFUNCTION("""COMPUTED_VALUE"""),"Kg") -> Kg | F59: =IFERROR(__xludf.DUMMYFUNCTION("""COMPUTED_VALUE"""),"Abarrotes") -> Abarrotes | G59: =(C59)*D59 -> 4035 | H59: =G59*19% -> 766.65 | I59: =G59+H59 -> 4801.65
A60: =IFERROR(__xludf.DUMMYFUNCTION("""COMPUTED_VALUE"""),"ti-ing-9f3dba64-3cca-408b-ac1e-45359966da75") -> ti-ing-9f3dba64-3cca-408b-ac1e-45359966da75 | B60: =IFERROR(__xludf.DUMMYFUNCTION("""COMPUTED_VALUE"""),"Salsa Soya") -> Salsa Soya | C60: 0 | D60: =IFERROR(__xludf.DUMMYFUNCTION("""COMPUTED_VALUE"""),1625) -> 1625 | E60: =IFERROR(__xludf.DUMMYFUNCTION("""COMPUTED_VALUE"""),"KG") -> KG | F60: =IFERROR(__xludf.DUMMYFUNCTION("""COMPUTED_VALUE"""),"Abarrotes") -> Abarrotes | G60: =(C60)*D60 -> 0 | H60: =G60*19% -> 0 | I60: =G60+H60 -> 0
A61: =IFERROR(__xludf.DUMMYFUNCTION("""COMPUTED_VALUE"""),"ti-ing-7e2cee8d-1717-48ff-96be-290c5aa01461") -> ti-ing-7e2cee8d-1717-48ff-96be-290c5aa01461 | B61: =IFERROR(__xludf.DUMMYFUNCTION("""COMPUTED_VALUE"""),"Semilla cilantro") -> Semilla cilantro | C61: 0 | D61: =IFERROR(__xludf.DUMMYFUNCTION("""COMPUTED_VALUE"""),4874.396) -> 4874.396 | E61: =IFERROR(__xludf.DUMMYFUNCTION("""COMPUTED_VALUE"""),"KG") -> KG | F61: =IFERROR(__xludf.DUMMYFUNCTION("""COMPUTED_VALUE"""),"Abarrotes") -> Abarrotes | G61: =(C61)*D61 -> 0 | H61: =G61*19% -> 0 | I61: =G61+H61 -> 0
A62: =IFERROR(__xludf.DUMMYFUNCTION("""COMPUTED_VALUE"""),"ti-ing-f3669215-5eea-4b87-8743-83d65563f01d") -> ti-ing-f3669215-5eea-4b87-8743-83d65563f01d | B62: =IFERROR(__xludf.DUMMYFUNCTION("""COMPUTED_VALUE"""),"Semilla De Zapallo kg") -> Semilla De Zapallo kg | C62: 1 | D62: =IFERROR(__xludf.DUMMYFUNCTION("""COMPUTED_VALUE"""),5550) -> 5550 | E62: =IFERROR(__xludf.DUMMYFUNCTION("""COMPUTED_VALUE"""),"Kg") -> Kg | F62: =IFERROR(__xludf.DUMMYFUNCTION("""COMPUTED_VALUE"""),"Abarrotes") -> Abarrotes | G62: =(C62)*D62 -> 5550 | H62: =G62*19% -> 1054.5 | I62: =G62+H62 -> 6604.5
A63: =IFERROR(__xludf.DUMMYFUNCTION("""COMPUTED_VALUE"""),"ti-ing-ee9260f2-296c-423d-bf8d-ee978626dfa5") -> ti-ing-ee9260f2-296c-423d-bf8d-ee978626dfa5 | B63: =IFERROR(__xludf.DUMMYFUNCTION("""COMPUTED_VALUE"""),"Sesamo Blanco") -> Sesamo Blanco | C63: 1 | D63: =IFERROR(__xludf.DUMMYFUNCTION("""COMPUTED_VALUE"""),4164) -> 4164 | E63: =IFERROR(__xludf.DUMMYFUNCTION("""COMPUTED_VALUE"""),"KG") -> KG | F63: =IFERROR(__xludf.DUMMYFUNCTION("""COMPUTED_VALUE"""),"Abarrotes") -> Abarrotes | G63: =(C63)*D63 -> 4164 | H63: =G63*19% -> 791.16 | I63: =G63+H63 -> 4955.16
A64: =IFERROR(__xludf.DUMMYFUNCTION("""COMPUTED_VALUE"""),"ti-ing-eb1cdfba-1bad-4930-a6f4-b0ad48b55576") -> ti-ing-eb1cdfba-1bad-4930-a6f4-b0ad48b55576 | B64: =IFERROR(__xludf.DUMMYFUNCTION("""COMPUTED_VALUE"""),"Sesamo Negro") -> Sesamo Negro | C64: 1 | D64: =IFERROR(__xludf.DUMMYFUNCTION("""COMPUTED_VALUE"""),5441) -> 5441 | E64: =IFERROR(__xludf.DUMMYFUNCTION("""COMPUTED_VALUE"""),"KG") -> KG | F64: =IFERROR(__xludf.DUMMYFUNCTION("""COMPUTED_VALUE"""),"Abarrotes") -> Abarrotes | G64: =(C64)*D64 -> 5441 | H64: =G64*19% -> 1033.79 | I64: =G64+H64 -> 6474.79
A65: =IFERROR(__xludf.DUMMYFUNCTION("""COMPUTED_VALUE"""),"ti-ing-802599df-3955-46c2-9418-b1ef4176ed29") -> ti-ing-802599df-3955-46c2-9418-b1ef4176ed29 | B65: =IFERROR(__xludf.DUMMYFUNCTION("""COMPUTED_VALUE"""),"STEVIA LIQUIDA") -> STEVIA LIQUIDA | C65: 3 | D65: =IFERROR(__xludf.DUMMYFUNCTION("""COMPUTED_VALUE"""),3444) -> 3444 | E65: =IFERROR(__xludf.DUMMYFUNCTION("""COMPUTED_VALUE"""),"un") -> un | F65: =IFERROR(__xludf.DUMMYFUNCTION("""COMPUTED_VALUE"""),"Abarrotes") -> Abarrotes | G65: =(C65)*D65 -> 10332 | H65: =G65*19% -> 1963.08 | I65: =G65+H65 -> 12295.08
A66: =IFERROR(__xludf.DUMMYFUNCTION("""COMPUTED_VALUE"""),"ti-ing-c5dc548f-f0a9-4499-a4b3-23a34458dbfa") -> ti-ing-c5dc548f-f0a9-4499-a4b3-23a34458dbfa | B66: =IFERROR(__xludf.DUMMYFUNCTION("""COMPUTED_VALUE"""),"Te en Bolsa Caja") -> Te en Bolsa Caja | C66: 0 | D66: =IFERROR(__xludf.DUMMYFUNCTION("""COMPUTED_VALUE"""),46.5) -> 46.5 | E66: =IFERROR(__xludf.DUMMYFUNCTION("""COMPUTED_VALUE"""),"UN") -> UN | F66: =IFERROR(__xludf.DUMMYFUNCTION("""COMPUTED_VALUE"""),"Abarrotes") -> Abarrotes | G66: =(C66)*D66 -> 0 | H66: =G66*19% -> 0 | I66: =G66+H66 -> 0
A67: =IFERROR(__xludf.DUMMYFUNCTION("""COMPUTED_VALUE"""),"ti-ing-7a052395-bb4e-4c4d-a1cf-c498a5386bb1") -> ti-ing-7a052395-bb4e-4c4d-a1cf-c498a5386bb1 | B67: =IFERROR(__xludf.DUMMYFUNCTION("""COMPUTED_VALUE"""),"Tomillo") -> Tomillo | C67: 0 | D67: =IFERROR(__xludf.DUMMYFUNCTION("""COMPUTED_VALUE"""),9885) -> 9885 | E67: =IFERROR(__xludf.DUMMYFUNCTION("""COMPUTED_VALUE"""),"UN") -> UN | F67: =IFERROR(__xludf.DUMMYFUNCTION("""COMPUTED_VALUE"""),"Abarrotes") -> Abarrotes | G67: =(C67)*D67 -> 0 | H67: =G67*19% -> 0 | I67: =G67+H67 -> 0
A68: =IFERROR(__xludf.DUMMYFUNCTION("""COMPUTED_VALUE"""),"ti-ing-0e85d9bc-d4c4-4362-994b-91915a9dcf13") -> ti-ing-0e85d9bc-d4c4-4362-994b-91915a9dcf13 | B68: =IFERROR(__xludf.DUMMYFUNCTION("""COMPUTED_VALUE"""),"Velas cumpleaños") -> Velas cumpleaños | C68: 120 | D68: =IFERROR(__xludf.DUMMYFUNCTION("""COMPUTED_VALUE"""),31.25) -> 31.25 | E68: =IFERROR(__xludf.DUMMYFUNCTION("""COMPUTED_VALUE"""),"un") -> un | F68: =IFERROR(__xludf.DUMMYFUNCTION("""COMPUTED_VALUE"""),"Abarrotes") -> Abarrotes | G68: =(C68)*D68 -> 3750 | H68: =G68*19% -> 712.5 | I68: =G68+H68 -> 4462.5
A69: =IFERROR(__xludf.DUMMYFUNCTION("""COMPUTED_VALUE"""),"ti-ing-b38390e4-8c11-4339-8209-7a310643c3be") -> ti-ing-b38390e4-8c11-4339-8209-7a310643c3be | B69: =IFERROR(__xludf.DUMMYFUNCTION("""COMPUTED_VALUE"""),"Vinagre") -> Vinagre | C69: 0 | D69: =IFERROR(__xludf.DUMMYFUNCTION("""COMPUTED_VALUE"""),593) -> 593 | E69: =IFERROR(__xludf.DUMMYFUNCTION("""COMPUTED_VALUE"""),"UN") -> UN | F69: =IFERROR(__xludf.DUMMYFUNCTION("""COMPUTED_VALUE"""),"Abarrotes") -> Abarrotes | G69: =(C69)*D69 -> 0 | H69: =G69*19% -> 0 | I69: =G69+H69 -> 0
A70: =IFERROR(__xludf.DUMMYFUNCTION("""COMPUTED_VALUE"""),"ti-ing-f8ffedeb-44d6-400b-bef8-0b9c51a508a0") -> ti-ing-f8ffedeb-44d6-400b-bef8-0b9c51a508a0 | B70: =IFERROR(__xludf.DUMMYFUNCTION("""COMPUTED_VALUE"""),"ALCOHOL") -> ALCOHOL | C70: 5 | D70: =IFERROR(__xludf.DUMMYFUNCTION("""COMPUTED_VALUE"""),2348.2) -> 2348.2 | E70: =IFERROR(__xludf.DUMMYFUNCTION("""COMPUTED_VALUE"""),"UN") -> UN | F70: =IFERROR(__xludf.DUMMYFUNCTION("""COMPUTED_VALUE"""),"Aseo") -> Aseo | G70: =(C70)*D70 -> 11741 | H70: =G70*19% -> 2230.79 | I70: =G70+H70 -> 13971.79
A71: =IFERROR(__xludf.DUMMYFUNCTION("""COMPUTED_VALUE"""),"ti-ing-7607ac26-0154-48c7-a176-272daa456f7a") -> ti-ing-7607ac26-0154-48c7-a176-272daa456f7a | B71: =IFERROR(__xludf.DUMMYFUNCTION("""COMPUTED_VALUE"""),"BOLSA BASURA CHICA (un)") -> BOLSA BASURA CHICA (un) | C71: 70 | D71: =IFERROR(__xludf.DUMMYFUNCTION("""COMPUTED_VALUE"""),39) -> 39 | E71: =IFERROR(__xludf.DUMMYFUNCTION("""COMPUTED_VALUE"""),"UN") -> UN | F71: =IFERROR(__xludf.DUMMYFUNCTION("""COMPUTED_VALUE"""),"Aseo") -> Aseo | G71: =(C71)*D71 -> 2730 | H71: =G71*19% -> 518.7 | I71: =G71+H71 -> 3248.7
A72: =IFERROR(__xludf.DUMMYFUNCTION("""COMPUTED_VALUE"""),"ti-ing-32a0a1de-7d7a-48fa-8701-58015f10f3d8") -> ti-ing-32a0a1de-7d7a-48fa-8701-58015f10f3d8 | B72: =IFERROR(__xludf.DUMMYFUNCTION("""COMPUTED_VALUE"""),"BOLSA BASURA GRANDE (un)") -> BOLSA BASURA GRANDE (un) | C72: 30 | D72: =IFERROR(__xludf.DUMMYFUNCTION("""COMPUTED_VALUE"""),391.1) -> 391.1 | E72: =IFERROR(__xludf.DUMMYFUNCTION("""COMPUTED_VALUE"""),"UN") -> UN | F72: =IFERROR(__xludf.DUMMYFUNCTION("""COMPUTED_VALUE"""),"Aseo") -> Aseo | G72: =(C72)*D72 -> 11733 | H72: =G72*19% -> 2229.27 | I72: =G72+H72 -> 13962.27
A73: =IFERROR(__xludf.DUMMYFUNCTION("""COMPUTED_VALUE"""),"ti-ing-b56c8191-87a4-414c-8649-692ed6f88304") -> ti-ing-b56c8191-87a4-414c-8649-692ed6f88304 | B73: =IFERROR(__xludf.DUMMYFUNCTION("""COMPUTED_VALUE"""),"BOLSA BASURA MEDIANA (un)") -> BOLSA BASURA MEDIANA (un) | C73: 50 | D73: =IFERROR(__xludf.DUMMYFUNCTION("""COMPUTED_VALUE"""),74.8) -> 74.8 | E73: =IFERROR(__xludf.DUMMYFUNCTION("""COMPUTED_VALUE"""),"UN") -> UN | F73: =IFERROR(__xludf.DUMMYFUNCTION("""COMPUTED_VALUE"""),"Aseo") -> Aseo | G73: =(C73)*D73 -> 3740 | H73: =G73*19% -> 710.6 | I73: =G73+H73 -> 4450.6
A74: =IFERROR(__xludf.DUMMYFUNCTION("""COMPUTED_VALUE"""),"ti-ing-dbb6ae46-9301-4b24-b966-4b4c02ecbb20") -> ti-ing-dbb6ae46-9301-4b24-b966-4b4c02ecbb20 | B74: =IFERROR(__xludf.DUMMYFUNCTION("""COMPUTED_VALUE"""),"Cafiza2") -> Cafiza2 | C74: 1 | D74: =IFERROR(__xludf.DUMMYFUNCTION("""COMPUTED_VALUE"""),19328) -> 19328 | E74: =IFERROR(__xludf.DUMMYFUNCTION("""COMPUTED_VALUE"""),"KG") -> KG | F74: =IFERROR(__xludf.DUMMYFUNCTION("""COMPUTED_VALUE"""),"Aseo") -> Aseo | G74: =(C74)*D74 -> 19328 | H74: =G74*19% -> 3672.32 | I74: =G74+H74 -> 23000.32
A75: =IFERROR(__xludf.DUMMYFUNCTION("""COMPUTED_VALUE"""),"ti-ing-addf5a00-64be-48da-80f1-f963e13357c9") -> ti-ing-addf5a00-64be-48da-80f1-f963e13357c9 | B75: =IFERROR(__xludf.DUMMYFUNCTION("""COMPUTED_VALUE"""),"CLORO 5 LTS") -> CLORO 5 LTS | C75: 5 | D75: =IFERROR(__xludf.DUMMYFUNCTION("""COMPUTED_VALUE"""),247) -> 247 | E75: =IFERROR(__xludf.DUMMYFUNCTION("""COMPUTED_VALUE"""),"LT") -> LT | F75: =IFERROR(__xludf.DUMMYFUNCTION("""COMPUTED_VALUE"""),"Aseo") -> Aseo | G75: =(C75)*D75 -> 1235 | H75: =G75*19% -> 234.65 | I75: =G75+H75 -> 1469.65
A76: =IFERROR(__xludf.DUMMYFUNCTION("""COMPUTED_VALUE"""),"ti-ing-04d39eaa-25ae-4aa0-b31a-7ca9c1ec8bc0") -> ti-ing-04d39eaa-25ae-4aa0-b31a-7ca9c1ec8bc0 | B76: =IFERROR(__xludf.DUMMYFUNCTION("""COMPUTED_VALUE"""),"CLORO GEL") -> CLORO GEL | C76: 5 | D76: =IFERROR(__xludf.DUMMYFUNCTION("""COMPUTED_VALUE"""),1250) -> 1250 | E76: =IFERROR(__xludf.DUMMYFUNCTION("""COMPUTED_VALUE"""),"LT") -> LT | F76: =IFERROR(__xludf.DUMMYFUNCTION("""COMPUTED_VALUE"""),"Aseo") -> Aseo | G76: =(C76)*D76 -> 6250 | H76: =G76*19% -> 1187.5 | I76: =G76+H76 -> 7437.5
A77: =IFERROR(__xludf.DUMMYFUNCTION("""COMPUTED_VALUE"""),"ti-ing-2a9f7a04-ff9b-4634-9f27-edac618856d6") -> ti-ing-2a9f7a04-ff9b-4634-9f27-edac618856d6 | B77: =IFERROR(__xludf.DUMMYFUNCTION("""COMPUTED_VALUE"""),"DESENGRASANTE 5 lt") -> DESENGRASANTE 5 lt | C77: 10 | D77: =IFERROR(__xludf.DUMMYFUNCTION("""COMPUTED_VALUE"""),658.8) -> 658.8 | E77: =IFERROR(__xludf.DUMMYFUNCTION("""COMPUTED_VALUE"""),"LT") -> LT | F77: =IFERROR(__xludf.DUMMYFUNCTION("""COMPUTED_VALUE"""),"Aseo") -> Aseo | G77: =(C77)*D77 -> 6588 | H77: =G77*19% -> 1251.72 | I77: =G77+H77 -> 7839.72
A78: =IFERROR(__xludf.DUMMYFUNCTION("""COMPUTED_VALUE"""),"ti-ing-e0ae8367-512a-46da-9188-edb6aed9ccac") -> ti-ing-e0ae8367-512a-46da-9188-edb6aed9ccac | B78: =IFERROR(__xludf.DUMMYFUNCTION("""COMPUTED_VALUE"""),"ESCOBA") -> ESCOBA | C78: 11 | D78: =IFERROR(__xludf.DUMMYFUNCTION("""COMPUTED_VALUE"""),1250) -> 1250 | E78: =IFERROR(__xludf.DUMMYFUNCTION("""COMPUTED_VALUE"""),"UN") -> UN | F78: =IFERROR(__xludf.DUMMYFUNCTION("""COMPUTED_VALUE"""),"Aseo") -> Aseo | G78: =(C78)*D78 -> 13750 | H78: =G78*19% -> 2612.5 | I78: =G78+H78 -> 16362.5
A79: =IFERROR(__xludf.DUMMYFUNCTION("""COMPUTED_VALUE"""),"ti-ing-102eb718-4b52-41a7-9529-6a535c4ceb37") -> ti-ing-102eb718-4b52-41a7-9529-6a535c4ceb37 | B79: =IFERROR(__xludf.DUMMYFUNCTION("""COMPUTED_VALUE"""),"ESPONJAS AMARILLAS") -> ESPONJAS AMARILLAS | C79: 9 | D79: =IFERROR(__xludf.DUMMYFUNCTION("""COMPUTED_VALUE"""),149) -> 149 | E79: =IFERROR(__xludf.DUMMYFUNCTION("""COMPUTED_VALUE"""),"UN") -> UN | F79: =IFERROR(__xludf.DUMMYFUNCTION("""COMPUTED_VALUE"""),"Aseo") -> Aseo | G79: =(C79)*D79 -> 1341 | H79: =G79*19% -> 254.79 | I79: =G79+H79 -> 1595.79
A80: =IFERROR(__xludf.DUMMYFUNCTION("""COMPUTED_VALUE"""),"ti-ing-0c760711-4885-4c8f-b5d5-6615e29d0673") -> ti-ing-0c760711-4885-4c8f-b5d5-6615e29d0673 | B80: =IFERROR(__xludf.DUMMYFUNCTION("""COMPUTED_VALUE"""),"GUANTES AMARILLOS L") -> GUANTES AMARILLOS L | C80: 2 | D80: =IFERROR(__xludf.DUMMYFUNCTION("""COMPUTED_VALUE"""),495) -> 495 | E80: =IFERROR(__xludf.DUMMYFUNCTION("""COMPUTED_VALUE"""),"UN") -> UN | F80: =IFERROR(__xludf.DUMMYFUNCTION("""COMPUTED_VALUE"""),"Aseo") -> Aseo | G80: =(C80)*D80 -> 990 | H80: =G80*19% -> 188.1 | I80: =G80+H80 -> 1178.1
A81: =IFERROR(__xludf.DUMMYFUNCTION("""COMPUTED_VALUE"""),"ti-ing-7fc47597-0e5d-46f8-a43c-94faaa1daf88") -> ti-ing-7fc47597-0e5d-46f8-a43c-94faaa1daf88 | B81: =IFERROR(__xludf.DUMMYFUNCTION("""COMPUTED_VALUE"""),"GUANTES AMARILLOS M") -> GUANTES AMARILLOS M | C81: 2 | D81: =IFERROR(__xludf.DUMMYFUNCTION("""COMPUTED_VALUE"""),495) -> 495 | E81: =IFERROR(__xludf.DUMMYFUNCTION("""COMPUTED_VALUE"""),"UN") -> UN | F81: =IFERROR(__xludf.DUMMYFUNCTION("""COMPUTED_VALUE"""),"Aseo") -> Aseo | G81: =(C81)*D81 -> 990 | H81: =G81*19% -> 188.1 | I81: =G81+H81 -> 1178.1
A82: =IFERROR(__xludf.DUMMYFUNCTION("""COMPUTED_VALUE"""),"ti-ing-fefd1f5b-c7c3-4780-83fd-7e625942b766") -> ti-ing-fefd1f5b-c7c3-4780-83fd-7e625942b766 | B82: =IFERROR(__xludf.DUMMYFUNCTION("""COMPUTED_VALUE"""),"GUANTES AMARILLOS S") -> GUANTES AMARILLOS S | C82: 2 | D82: =IFERROR(__xludf.DUMMYFUNCTION("""COMPUTED_VALUE"""),450) -> 450 | E82: =IFERROR(__xludf.DUMMYFUNCTION("""COMPUTED_VALUE"""),"UN") -> UN | F82: =IFERROR(__xludf.DUMMYFUNCTION("""COMPUTED_VALUE"""),"Aseo") -> Aseo | G82: =(C82)*D82 -> 900 | H82: =G82*19% -> 171 | I82: =G82+H82 -> 1071
A83: =IFERROR(__xludf.DUMMYFUNCTION("""COMPUTED_VALUE"""),"ti-ing-04fc2068-57ca-42bc-bedb-ceda3e223def") -> ti-ing-04fc2068-57ca-42bc-bedb-ceda3e223def | B83: =IFERROR(__xludf.DUMMYFUNCTION("""COMPUTED_VALUE"""),"Guantes De Látex L") -> Guantes De Látex L | C83: 1 | D83: =IFERROR(__xludf.DUMMYFUNCTION("""COMPUTED_VALUE"""),3649.902) -> 3649.902 | E83: =IFERROR(__xludf.DUMMYFUNCTION("""COMPUTED_VALUE"""),"UN") -> UN | F83: =IFERROR(__xludf.DUMMYFUNCTION("""COMPUTED_VALUE"""),"Aseo") -> Aseo | G83: =(C83)*D83 -> 3649.902 | H83: =G83*19% -> 693.48138 | I83: =G83+H83 -> 4343.3834
A84: =IFERROR(__xludf.DUMMYFUNCTION("""COMPUTED_VALUE"""),"ti-ing-3c965e17-4bc3-453d-b74f-c682b54aeade") -> ti-ing-3c965e17-4bc3-453d-b74f-c682b54aeade | B84: =IFERROR(__xludf.DUMMYFUNCTION("""COMPUTED_VALUE"""),"Guantes De Látex M") -> Guantes De Látex M | C84: 4 | D84: =IFERROR(__xludf.DUMMYFUNCTION("""COMPUTED_VALUE"""),3650) -> 3650 | E84: =IFERROR(__xludf.DUMMYFUNCTION("""COMPUTED_VALUE"""),"UN") -> UN | F84: =IFERROR(__xludf.DUMMYFUNCTION("""COMPUTED_VALUE"""),"Aseo") -> Aseo | G84: =(C84)*D84 -> 14600 | H84: =G84*19% -> 2774 | I84: =G84+H84 -> 17374
A85: =IFERROR(__xludf.DUMMYFUNCTION("""COMPUTED_VALUE"""),"ti-ing-a5847069-c85b-4a57-a415-7cf62066dedc") -> ti-ing-a5847069-c85b-4a57-a415-7cf62066dedc | B85: =IFERROR(__xludf.DUMMYFUNCTION("""COMPUTED_VALUE"""),"Guantes De Látex S") -> Guantes De Látex S | C85: 0 | D85: =IFERROR(__xludf.DUMMYFUNCTION("""COMPUTED_VALUE"""),3650) -> 3650 | E85: =IFERROR(__xludf.DUMMYFUNCTION("""COMPUTED_VALUE"""),"un") -> un | F85: =IFERROR(__xludf.DUMMYFUNCTION("""COMPUTED_VALUE"""),"Aseo") -> Aseo | G85: =(C85)*D85 -> 0 | H85: =G85*19% -> 0 | I85: =G85+H85 -> 0
A86: =IFERROR(__xludf.DUMMYFUNCTION("""COMPUTED_VALUE"""),"ti-ing-f1845df4-9dd0-4be9-9cda-4e9939c6c9a8") -> ti-ing-f1845df4-9dd0-4be9-9cda-4e9939c6c9a8 | B86: =IFERROR(__xludf.DUMMYFUNCTION("""COMPUTED_VALUE"""),"JABON BAÑO") -> JABON BAÑO | C86: 0 | D86: =IFERROR(__xludf.DUMMYFUNCTION("""COMPUTED_VALUE"""),880) -> 880 | E86: =IFERROR(__xludf.DUMMYFUNCTION("""COMPUTED_VALUE"""),"LT") -> LT | F86: =IFERROR(__xludf.DUMMYFUNCTION("""COMPUTED_VALUE"""),"Aseo") -> Aseo | G86: =(C86)*D86 -> 0 | H86: =G86*19% -> 0 | I86: =G86+H86 -> 0
A87: =IFERROR(__xludf.DUMMYFUNCTION("""COMPUTED_VALUE"""),"ti-ing-90438c34-c1c8-455a-8b38-f56ab57f0e76") -> ti-ing-90438c34-c1c8-455a-8b38-f56ab57f0e76 | B87: =IFERROR(__xludf.DUMMYFUNCTION("""COMPUTED_VALUE"""),"LAVALOZAS") -> LAVALOZAS | C87: 15 | D87: =IFERROR(__xludf.DUMMYFUNCTION("""COMPUTED_VALUE"""),381.6) -> 381.6 | E87: =IFERROR(__xludf.DUMMYFUNCTION("""COMPUTED_VALUE"""),"LT") -> LT | F87: =IFERROR(__xludf.DUMMYFUNCTION("""COMPUTED_VALUE"""),"Aseo") -> Aseo | G87: =(C87)*D87 -> 5724 | H87: =G87*19% -> 1087.56 | I87: =G87+H87 -> 6811.56
A88: =IFERROR(__xludf.DUMMYFUNCTION("""COMPUTED_VALUE"""),"ti-ing-096ebcd5-904f-4e35-9378-181fe59b0c31") -> ti-ing-096ebcd5-904f-4e35-9378-181fe59b0c31 | B88: =IFERROR(__xludf.DUMMYFUNCTION("""COMPUTED_VALUE"""),"Limpiador Crema CIF 750g") -> Limpiador Crema CIF 750g | C88: 0 | D88: =IFERROR(__xludf.DUMMYFUNCTION("""COMPUTED_VALUE"""),1522) -> 1522 | E88: =IFERROR(__xludf.DUMMYFUNCTION("""COMPUTED_VALUE"""),"UN") -> UN | F88: =IFERROR(__xludf.DUMMYFUNCTION("""COMPUTED_VALUE"""),"Aseo") -> Aseo | G88: =(C88)*D88 -> 0 | H88: =G88*19% -> 0 | I88: =G88+H88 -> 0
A89: =IFERROR(__xludf.DUMMYFUNCTION("""COMPUTED_VALUE"""),"ti-ing-87e4c4d7-978b-4106-9ff1-dda60dd75d70") -> ti-ing-87e4c4d7-978b-4106-9ff1-dda60dd75d70 | B89: =IFERROR(__xludf.DUMMYFUNCTION("""COMPUTED_VALUE"""),"LIMPIAPISOS") -> LIMPIAPISOS | C89: 25 | D89: =IFERROR(__xludf.DUMMYFUNCTION("""COMPUTED_VALUE"""),284.1160494) -> 284.11605 | E89: =IFERROR(__xludf.DUMMYFUNCTION("""COMPUTED_VALUE"""),"LT") -> LT | F89: =IFERROR(__xludf.DUMMYFUNCTION("""COMPUTED_VALUE"""),"Aseo") -> Aseo | G89: =(C89)*D89 -> 7102.9012 | H89: =G89*19% -> 1349.5512 | I89: =G89+H89 -> 8452.4525
A90: =IFERROR(__xludf.DUMMYFUNCTION("""COMPUTED_VALUE"""),"ti-ing-197c4981-e3d5-425b-b927-86de4c38a9b1") -> ti-ing-197c4981-e3d5-425b-b927-86de4c38a9b1 | B90: =IFERROR(__xludf.DUMMYFUNCTION("""COMPUTED_VALUE"""),"LIMPIAVIDRIOS") -> LIMPIAVIDRIOS | C90: 0 | D90: =IFERROR(__xludf.DUMMYFUNCTION("""COMPUTED_VALUE"""),696.4) -> 696.4 | E90: =IFERROR(__xludf.DUMMYFUNCTION("""COMPUTED_VALUE"""),"LT") -> LT | F90: =IFERROR(__xludf.DUMMYFUNCTION("""COMPUTED_VALUE"""),"Aseo") -> Aseo | G90: =(C90)*D90 -> 0 | H90: =G90*19% -> 0 | I90: =G90+H90 -> 0
A91: =IFERROR(__xludf.DUMMYFUNCTION("""COMPUTED_VALUE"""),"ti-ing-9fcf899e-b43f-49a0-bfca-d4ca3181f761") -> ti-ing-9fcf899e-b43f-49a0-bfca-d4ca3181f761 | B91: =IFERROR(__xludf.DUMMYFUNCTION("""COMPUTED_VALUE"""),"LUSTRAMUEBLES") -> LUSTRAMUEBLES | C91: 2 | D91: =IFERROR(__xludf.DUMMYFUNCTION("""COMPUTED_VALUE"""),893) -> 893 | E91: =IFERROR(__xludf.DUMMYFUNCTION("""COMPUTED_VALUE"""),"UN") -> UN | F91: =IFERROR(__xludf.DUMMYFUNCTION("""COMPUTED_VALUE"""),"Aseo") -> Aseo | G91: =(C91)*D91 -> 1786 | H91: =G91*19% -> 339.34 | I91: =G91+H91 -> 2125.34
A92: =IFERROR(__xludf.DUMMYFUNCTION("""COMPUTED_VALUE"""),"ti-ing-af8029ba-0f08-420d-ae31-6cf6502d2e32") -> ti-ing-af8029ba-0f08-420d-ae31-6cf6502d2e32 | B92: =IFERROR(__xludf.DUMMYFUNCTION("""COMPUTED_VALUE"""),"Lysoform") -> Lysoform | C92: 1 | D92: =IFERROR(__xludf.DUMMYFUNCTION("""COMPUTED_VALUE"""),2428) -> 2428 | E92: =IFERROR(__xludf.DUMMYFUNCTION("""COMPUTED_VALUE"""),"UN") -> UN | F92: =IFERROR(__xludf.DUMMYFUNCTION("""COMPUTED_VALUE"""),"Aseo") -> Aseo | G92: =(C92)*D92 -> 2428 | H92: =G92*19% -> 461.32 | I92: =G92+H92 -> 2889.32
A93: =IFERROR(__xludf.DUMMYFUNCTION("""COMPUTED_VALUE"""),"ti-ing-64301c86-8657-4a60-9738-54b3f81ead5a") -> ti-ing-64301c86-8657-4a60-9738-54b3f81ead5a | B93: =IFERROR(__xludf.DUMMYFUNCTION("""COMPUTED_VALUE"""),"MALLAS DE PELO (100un)") -> MALLAS DE PELO (100un) | C93: 2 | D93: =IFERROR(__xludf.DUMMYFUNCTION("""COMPUTED_VALUE"""),1529) -> 1529 | E93: =IFERROR(__xludf.DUMMYFUNCTION("""COMPUTED_VALUE"""),"UN") -> UN | F93: =IFERROR(__xludf.DUMMYFUNCTION("""COMPUTED_VALUE"""),"Aseo") -> Aseo | G93: =(C93)*D93 -> 3058 | H93: =G93*19% -> 581.02 | I93: =G93+H93 -> 3639.02
A94: =IFERROR(__xludf.DUMMYFUNCTION("""COMPUTED_VALUE"""),"ti-ing-242bf6e9-d5c5-47e7-8f0a-88f3cbbcc3af") -> ti-ing-242bf6e9-d5c5-47e7-8f0a-88f3cbbcc3af | B94: =IFERROR(__xludf.DUMMYFUNCTION("""COMPUTED_VALUE"""),"Mascarillas") -> Mascarillas | C94: 0 | D94: =IFERROR(__xludf.DUMMYFUNCTION("""COMPUTED_VALUE"""),1350) -> 1350 | E94: =IFERROR(__xludf.DUMMYFUNCTION("""COMPUTED_VALUE"""),"UN") -> UN | F94: =IFERROR(__xludf.DUMMYFUNCTION("""COMPUTED_VALUE"""),"Aseo") -> Aseo | G94: =(C94)*D94 -> 0 | H94: =G94*19% -> 0 | I94: =G94+H94 -> 0
A95: =IFERROR(__xludf.DUMMYFUNCTION("""COMPUTED_VALUE"""),"ti-ing-313073f4-b1b1-442d-b077-951f3ce67b06") -> ti-ing-313073f4-b1b1-442d-b077-951f3ce67b06 | B95: =IFERROR(__xludf.DUMMYFUNCTION("""COMPUTED_VALUE"""),"NOVA Unidad") -> NOVA Unidad | C95: 6 | D95: =IFERROR(__xludf.DUMMYFUNCTION("""COMPUTED_VALUE"""),2735) -> 2735 | E95: =IFERROR(__xludf.DUMMYFUNCTION("""COMPUTED_VALUE"""),"UN") -> UN | F95: =IFERROR(__xludf.DUMMYFUNCTION("""COMPUTED_VALUE"""),"Aseo") -> Aseo | G95: =(C95)*D95 -> 16410 | H95: =G95*19% -> 3117.9 | I95: =G95+H95 -> 19527.9
A96: =IFERROR(__xludf.DUMMYFUNCTION("""COMPUTED_VALUE"""),"ti-ing-f2a85135-486f-455a-9223-1092ccd4e7cd") -> ti-ing-f2a85135-486f-455a-9223-1092ccd4e7cd | B96: =IFERROR(__xludf.DUMMYFUNCTION("""COMPUTED_VALUE"""),"PALA") -> PALA | C96: 7 | D96: =IFERROR(__xludf.DUMMYFUNCTION("""COMPUTED_VALUE"""),1165) -> 1165 | E96: =IFERROR(__xludf.DUMMYFUNCTION("""COMPUTED_VALUE"""),"UN") -> UN | F96: =IFERROR(__xludf.DUMMYFUNCTION("""COMPUTED_VALUE"""),"Aseo") -> Aseo | G96: =(C96)*D96 -> 8155 | H96: =G96*19% -> 1549.45 | I96: =G96+H96 -> 9704.45
A97: =IFERROR(__xludf.DUMMYFUNCTION("""COMPUTED_VALUE"""),"ti-ing-a496bcbe-0906-4bd7-90be-10085697981e") -> ti-ing-a496bcbe-0906-4bd7-90be-10085697981e | B97: =IFERROR(__xludf.DUMMYFUNCTION("""COMPUTED_VALUE"""),"Paño microfibra") -> Paño microfibra | C97: 4 | D97: =IFERROR(__xludf.DUMMYFUNCTION("""COMPUTED_VALUE"""),650) -> 650 | E97: =IFERROR(__xludf.DUMMYFUNCTION("""COMPUTED_VALUE"""),"UN") -> UN | F97: =IFERROR(__xludf.DUMMYFUNCTION("""COMPUTED_VALUE"""),"Aseo") -> Aseo | G97: =(C97)*D97 -> 2600 | H97: =G97*19% -> 494 | I97: =G97+H97 -> 3094
A98: =IFERROR(__xludf.DUMMYFUNCTION("""COMPUTED_VALUE"""),"ti-ing-71ad4a79-597d-4cd3-85f8-8c113261d29e") -> ti-ing-71ad4a79-597d-4cd3-85f8-8c113261d29e | B98: =IFERROR(__xludf.DUMMYFUNCTION("""COMPUTED_VALUE"""),"PAÑOS AMARILLOS") -> PAÑOS AMARILLOS | C98: 0 | D98: =IFERROR(__xludf.DUMMYFUNCTION("""COMPUTED_VALUE"""),185) -> 185 | E98: =IFERROR(__xludf.DUMMYFUNCTION("""COMPUTED_VALUE"""),"UN") -> UN | F98: =IFERROR(__xludf.DUMMYFUNCTION("""COMPUTED_VALUE"""),"Aseo") -> Aseo | G98: =(C98)*D98 -> 0 | H98: =G98*19% -> 0 | I98: =G98+H98 -> 0
A99: =IFERROR(__xludf.DUMMYFUNCTION("""COMPUTED_VALUE"""),"ti-ing-adaa762a-98c1-4bd8-8d7f-d256999a6d54") -> ti-ing-adaa762a-98c1-4bd8-8d7f-d256999a6d54 | B99: =IFERROR(__xludf.DUMMYFUNCTION("""COMPUTED_VALUE"""),"PAPEL HIGUIENICO UN") -> PAPEL HIGUIENICO UN | C99: 4 | D99: =IFERROR(__xludf.DUMMYFUNCTION("""COMPUTED_VALUE"""),1676.25) -> 1676.25 | E99: =IFERROR(__xludf.DUMMYFUNCTION("""COMPUTED_VALUE"""),"UN") -> UN | F99: =IFERROR(__xludf.DUMMYFUNCTION("""COMPUTED_VALUE"""),"Aseo") -> Aseo | G99: =(C99)*D99 -> 6705 | H99: =G99*19% -> 1273.95 | I99: =G99+H99 -> 7978.95
A100: =IFERROR(__xludf.DUMMYFUNCTION("""COMPUTED_VALUE"""),"ti-ing-f9770958-721b-4e86-963c-bb85b123a83c") -> ti-ing-f9770958-721b-4e86-963c-bb85b123a83c | B100: =IFERROR(__xludf.DUMMYFUNCTION("""COMPUTED_VALUE"""),"Pastilla para estanque") -> Pastilla para estanque | C100: 0 | D100: =IFERROR(__xludf.DUMMYFUNCTION("""COMPUTED_VALUE"""),409.8889) -> 409.8889 | E100: =IFERROR(__xludf.DUMMYFUNCTION("""COMPUTED_VALUE"""),"UN") -> UN | F100: =IFERROR(__xludf.DUMMYFUNCTION("""COMPUTED_VALUE"""),"Aseo") -> Aseo | G100: =(C100)*D100 -> 0 | H100: =G100*19% -> 0 | I100: =G100+H100 -> 0
...

Sheet cocina
A1: Stock Cocina | B1: Stock Cocina
A2: ID PRODUCTO | B2: PRODUCTO | C2: STOCK | D2: PEDIDO | E2: UN MEDIDA | F2: CATEGORIA | G2: Valorizado Neto | H2: IVA (19%) | I2: Total Bruto | J2: PEDIDO
A3: =IFERROR(__xludf.DUMMYFUNCTION("FILTER('UNIVERSO PRODUCTOS'!A1:B958, ISNUMBER(SEARCH(A1, 'UNIVERSO PRODUCTOS'!K1:K958))) "),"ti-ing-b69bd6ae-ccae-4801-af83-bece901d304f") -> ti-ing-b69bd6ae-ccae-4801-af83-bece901d304f | B3: =IFERROR(__xludf.DUMMYFUNCTION("""COMPUTED_VALUE"""),"Aceite oliva extra virgen 5 lts") -> Aceite oliva extra virgen 5 lts | C3: 1.524 | D3: =IFERROR(__xludf.DUMMYFUNCTION("FILTER('UNIVERSO PRODUCTOS'!C1:C961, ISNUMBER(SEARCH(A1, 'UNIVERSO PRODUCTOS'!K1:K961))) "),4646.2) -> 4646.2 | E3: =IFERROR(__xludf.DUMMYFUNCTION("FILTER('UNIVERSO PRODUCTOS'!D1:D958, ISNUMBER(SEARCH(A1, 'UNIVERSO PRODUCTOS'!K1:K958))) "),"LT") -> LT | F3: =IFERROR(__xludf.DUMMYFUNCTION("FILTER('UNIVERSO PRODUCTOS'!H1:H958, ISNUMBER(SEARCH(A1, 'UNIVERSO PRODUCTOS'!K1:K958))) "),"Abarrotes") -> Abarrotes | G3: =(C3)*D3 -> 7080.8088 | H3: =G3*19% -> 1345.3537 | I3: =G3+H3 -> 8426.1625
A4: =IFERROR(__xludf.DUMMYFUNCTION("""COMPUTED_VALUE"""),"ti-ing-5a1041f6-5fed-4ae0-8d00-dee7d47968a3") -> ti-ing-5a1041f6-5fed-4ae0-8d00-dee7d47968a3 | B4: =IFERROR(__xludf.DUMMYFUNCTION("""COMPUTED_VALUE"""),"Aceite vegetal 900 ml") -> Aceite vegetal 900 ml | C4: 6 | D4: =IFERROR(__xludf.DUMMYFUNCTION("""COMPUTED_VALUE"""),1540.6) -> 1540.6 | E4: =IFERROR(__xludf.DUMMYFUNCTION("""COMPUTED_VALUE"""),"UN") -> UN | F4: =IFERROR(__xludf.DUMMYFUNCTION("""COMPUTED_VALUE"""),"Abarrotes") -> Abarrotes | G4: =(C4)*D4 -> 9243.6 | H4: =G4*19% -> 1756.284 | I4: =G4+H4 -> 10999.884 | L4: Abarrotes | M4: Aseo | N4: Bebestibles | O4: Cafetería | P4: Carnes y Aves | Q4: Desechables | R4: Frutas y Verduras | S4: Harinas | T4: Ovolacteos | U4: Pastelería | V4: Pescados y Mariscos | W4: P.Terminados | X4: Té | Y4: Valor Neto
A5: =IFERROR(__xludf.DUMMYFUNCTION("""COMPUTED_VALUE"""),"ti-ing-0ab486df-7d4d-4782-82bb-c30b4209e5fb") -> ti-ing-0ab486df-7d4d-4782-82bb-c30b4209e5fb | B5: =IFERROR(__xludf.DUMMYFUNCTION("""COMPUTED_VALUE"""),"Aceituna Morada kg") -> Aceituna Morada kg | C5: 1.278 | D5: =IFERROR(__xludf.DUMMYFUNCTION("""COMPUTED_VALUE"""),7130) -> 7130 | E5: =IFERROR(__xludf.DUMMYFUNCTION("""COMPUTED_VALUE"""),"KG") -> KG | F5: =IFERROR(__xludf.DUMMYFUNCTION("""COMPUTED_VALUE"""),"Abarrotes") -> Abarrotes | G5: =(C5)*D5 -> 9112.14 | H5: =G5*19% -> 1731.3066 | I5: =G5+H5 -> 10843.447
A6: =IFERROR(__xludf.DUMMYFUNCTION("""COMPUTED_VALUE"""),"ti-ing-581e5046-d41b-44fd-981a-fa5ec2c4d4ba") -> ti-ing-581e5046-d41b-44fd-981a-fa5ec2c4d4ba | B6: =IFERROR(__xludf.DUMMYFUNCTION("""COMPUTED_VALUE"""),"Ajinomoto") -> Ajinomoto | C6: 0.476 | D6: =IFERROR(__xludf.DUMMYFUNCTION("""COMPUTED_VALUE"""),3354) -> 3354 | E6: =IFERROR(__xludf.DUMMYFUNCTION("""COMPUTED_VALUE"""),"kg") -> kg | F6: =IFERROR(__xludf.DUMMYFUNCTION("""COMPUTED_VALUE"""),"Abarrotes") -> Abarrotes | G6: =(C6)*D6 -> 1596.504 | H6: =G6*19% -> 303.33576 | I6: =G6+H6 -> 1899.8398 | L6: =SUM(G3:G45) -> 145971.49 | M6: =SUM(G46:G63) -> 64394.913 | P6: =SUM(G64:G76) -> 319553.82 | Q6: =SUM(G77:G85) -> 42169.185 | R6: =SUM(G86:G120) -> 177430.72 | S6: =SUM(G121) -> 7156.3331 | T6: =SUM(G122:G131) -> 145824.48 | V6: =SUM(G132:G133) -> 0 | W6: =SUM(G134:G175) -> 487668.19 | Y6: =SUM(L6:X6) -> 1390169.1
A7: =IFERROR(__xludf.DUMMYFUNCTION("""COMPUTED_VALUE"""),"ti-ing-bfd5d10e-d265-4e6e-b05a-79c836269380") -> ti-ing-bfd5d10e-d265-4e6e-b05a-79c836269380 | B7: =IFERROR(__xludf.DUMMYFUNCTION("""COMPUTED_VALUE"""),"Arroz (colacion)") -> Arroz (colacion) | C7: 0 | D7: =IFERROR(__xludf.DUMMYFUNCTION("""COMPUTED_VALUE"""),905) -> 905 | E7: =IFERROR(__xludf.DUMMYFUNCTION("""COMPUTED_VALUE"""),"KG") -> KG | F7: =IFERROR(__xludf.DUMMYFUNCTION("""COMPUTED_VALUE"""),"Abarrotes") -> Abarrotes | G7: =(C7)*D7 -> 0 | H7: =G7*19% -> 0 | I7: =G7+H7 -> 0
A8: =IFERROR(__xludf.DUMMYFUNCTION("""COMPUTED_VALUE"""),"ti-ing-5c316419-1759-4d90-bb2e-e9025a87d122") -> ti-ing-5c316419-1759-4d90-bb2e-e9025a87d122 | B8: =IFERROR(__xludf.DUMMYFUNCTION("""COMPUTED_VALUE"""),"Atun Coliseo Al Agua") -> Atun Coliseo Al Agua | C8: 0 | D8: =IFERROR(__xludf.DUMMYFUNCTION("""COMPUTED_VALUE"""),879) -> 879 | E8: =IFERROR(__xludf.DUMMYFUNCTION("""COMPUTED_VALUE"""),"UN") -> UN | F8: =IFERROR(__xludf.DUMMYFUNCTION("""COMPUTED_VALUE"""),"Abarrotes") -> Abarrotes | G8: =(C8)*D8 -> 0 | H8: =G8*19% -> 0 | I8: =G8+H8 -> 0 | L8: Abarrotes | M8: Aseo | N8: Bebestibles | O8: Cafetería | P8: Carnes y Aves | Q8: Desechables | R8: Frutas y Verduras | S8: Harinas | T8: Ovolacteos | U8: Pastelería | V8: Pescados y Mariscos | W8: P.Terminados | X8: Té | Y8: Valor Bruto
A9: =IFERROR(__xludf.DUMMYFUNCTION("""COMPUTED_VALUE"""),"ti-ing-363a5ec1-8d6b-4612-be6a-7a19b61ab7e2") -> ti-ing-363a5ec1-8d6b-4612-be6a-7a19b61ab7e2 | B9: =IFERROR(__xludf.DUMMYFUNCTION("""COMPUTED_VALUE"""),"Atun Dorasol Al Agua") -> Atun Dorasol Al Agua | C9: 0 | D9: =IFERROR(__xludf.DUMMYFUNCTION("""COMPUTED_VALUE"""),879) -> 879 | E9: =IFERROR(__xludf.DUMMYFUNCTION("""COMPUTED_VALUE"""),"UN") -> UN | F9: =IFERROR(__xludf.DUMMYFUNCTION("""COMPUTED_VALUE"""),"Abarrotes") -> Abarrotes | G9: =(C9)*D9 -> 0 | H9: =G9*19% -> 0 | I9: =G9+H9 -> 0
A10: =IFERROR(__xludf.DUMMYFUNCTION("""COMPUTED_VALUE"""),"ti-ing-531d1d9b-814d-49bc-9bbf-06be4ae2e6d5") -> ti-ing-531d1d9b-814d-49bc-9bbf-06be4ae2e6d5 | B10: =IFERROR(__xludf.DUMMYFUNCTION("""COMPUTED_VALUE"""),"Azucar blanca") -> Azucar blanca | C10: 1.264 | D10: =IFERROR(__xludf.DUMMYFUNCTION("""COMPUTED_VALUE"""),939.9985) -> 939.9985 | E10: =IFERROR(__xludf.DUMMYFUNCTION("""COMPUTED_VALUE"""),"KG") -> KG | F10: =IFERROR(__xludf.DUMMYFUNCTION("""COMPUTED_VALUE"""),"Abarrotes") -> Abarrotes | G10: =(C10)*D10 -> 1188.1581 | H10: =G10*19% -> 225.75004 | I10: =G10+H10 -> 1413.9081 | L10: =SUM(I3:I45) -> 173706.08 | M10: =SUM(I46:I63) -> 76629.947 | P10: =SUM(I64:I76) -> 380269.05 | Q10: =SUM(I77:I85) -> 50181.331 | R10: =SUM(I86:I120) -> 211142.56 | S10: =SUM(I121) -> 8516.0364 | T10: =SUM(I122:I131) -> 173531.13 | V10: =SUM(I132:I133) -> 0 | W10: =SUM(I134:I175) -> 580325.14 | Y10: =SUM(L10:X10) -> 1654301.3
B11: =IFERROR(__xludf.DUMMYFUNCTION("""COMPUTED_VALUE"""),"Azúcar blanca por kilo") -> Azúcar blanca por kilo | C11: 0 | D11: =IFERROR(__xludf.DUMMYFUNCTION("""COMPUTED_VALUE"""),930) -> 930 | E11: =IFERROR(__xludf.DUMMYFUNCTION("""COMPUTED_VALUE"""),"KG") -> KG | F11: =IFERROR(__xludf.DUMMYFUNCTION("""COMPUTED_VALUE"""),"Abarrotes") -> Abarrotes | G11: =(C11)*D11 -> 0 | H11: =G11*19% -> 0 | I11: =G11+H11 -> 0
A12: =IFERROR(__xludf.DUMMYFUNCTION("""COMPUTED_VALUE"""),"ti-ing-c4486ce7-85c4-49c5-ac82-4d98b0798d01") -> ti-ing-c4486ce7-85c4-49c5-ac82-4d98b0798d01 | B12: =IFERROR(__xludf.DUMMYFUNCTION("""COMPUTED_VALUE"""),"Azucar rubia") -> Azucar rubia | C12: 0.75 | D12: =IFERROR(__xludf.DUMMYFUNCTION("""COMPUTED_VALUE"""),1047) -> 1047 | E12: =IFERROR(__xludf.DUMMYFUNCTION("""COMPUTED_VALUE"""),"KG") -> KG | F12: =IFERROR(__xludf.DUMMYFUNCTION("""COMPUTED_VALUE"""),"Abarrotes") -> Abarrotes | G12: =(C12)*D12 -> 785.25 | H12: =G12*19% -> 149.1975 | I12: =G12+H12 -> 934.4475
A13: =IFERROR(__xludf.DUMMYFUNCTION("""COMPUTED_VALUE"""),"ti-ing-63a7f9f9-77ff-45f4-9e3f-3feff0b73432") -> ti-ing-63a7f9f9-77ff-45f4-9e3f-3feff0b73432 | B13: =IFERROR(__xludf.DUMMYFUNCTION("""COMPUTED_VALUE"""),"Café tarro grande (desayuno)") -> Café tarro grande (desayuno) | C13: 0.5 | D13: =IFERROR(__xludf.DUMMYFUNCTION("""COMPUTED_VALUE"""),12032) -> 12032 | E13: =IFERROR(__xludf.DUMMYFUNCTION("""COMPUTED_VALUE"""),"UN") -> UN | F13: =IFERROR(__xludf.DUMMYFUNCTION("""COMPUTED_VALUE"""),"Abarrotes") -> Abarrotes | G13: =(C13)*D13 -> 6016 | H13: =G13*19% -> 1143.04 | I13: =G13+H13 -> 7159.04
A14: =IFERROR(__xludf.DUMMYFUNCTION("""COMPUTED_VALUE"""),"ti-ing-280562df-e2c6-469c-bfaf-8f7361fb5c74") -> ti-ing-280562df-e2c6-469c-bfaf-8f7361fb5c74 | B14: =IFERROR(__xludf.DUMMYFUNCTION("""COMPUTED_VALUE"""),"COMINO") -> COMINO | C14: 0.414 | D14: =IFERROR(__xludf.DUMMYFUNCTION("""COMPUTED_VALUE"""),5250) -> 5250 | E14: =IFERROR(__xludf.DUMMYFUNCTION("""COMPUTED_VALUE"""),"KG") -> KG | F14: =IFERROR(__xludf.DUMMYFUNCTION("""COMPUTED_VALUE"""),"Abarrotes") -> Abarrotes | G14: =(C14)*D14 -> 2173.5 | H14: =G14*19% -> 412.965 | I14: =G14+H14 -> 2586.465
A15: =IFERROR(__xludf.DUMMYFUNCTION("""COMPUTED_VALUE"""),"ti-ing-55e22a4e-70ba-4bfe-9ef6-78d09a6c71b6") -> ti-ing-55e22a4e-70ba-4bfe-9ef6-78d09a6c71b6 | B15: =IFERROR(__xludf.DUMMYFUNCTION("""COMPUTED_VALUE"""),"Curcuma") -> Curcuma | C15: 0.284 | D15: =IFERROR(__xludf.DUMMYFUNCTION("""COMPUTED_VALUE"""),5437) -> 5437 | E15: =IFERROR(__xludf.DUMMYFUNCTION("""COMPUTED_VALUE"""),"KG") -> KG | F15: =IFERROR(__xludf.DUMMYFUNCTION("""COMPUTED_VALUE"""),"Abarrotes") -> Abarrotes | G15: =(C15)*D15 -> 1544.108 | H15: =G15*19% -> 293.38052 | I15: =G15+H15 -> 1837.4885
A16: =IFERROR(__xludf.DUMMYFUNCTION("""COMPUTED_VALUE"""),"ti-ing-2fbc1c56-3286-4d64-8ddd-b547296361a3") -> ti-ing-2fbc1c56-3286-4d64-8ddd-b547296361a3 | B16: =IFERROR(__xludf.DUMMYFUNCTION("""COMPUTED_VALUE"""),"Espaguetti") -> Espaguetti | C16: 0 | D16: =IFERROR(__xludf.DUMMYFUNCTION("""COMPUTED_VALUE"""),407) -> 407 | E16: =IFERROR(__xludf.DUMMYFUNCTION("""COMPUTED_VALUE"""),"UN") -> UN | F16: =IFERROR(__xludf.DUMMYFUNCTION("""COMPUTED_VALUE"""),"Abarrotes") -> Abarrotes | G16: =(C16)*D16 -> 0 | H16: =G16*19% -> 0 | I16: =G16+H16 -> 0
A17: =IFERROR(__xludf.DUMMYFUNCTION("""COMPUTED_VALUE"""),"ti-ing-446530ff-42dc-41f9-9208-1b6c8dded86f") -> ti-ing-446530ff-42dc-41f9-9208-1b6c8dded86f | B17: =IFERROR(__xludf.DUMMYFUNCTION("""COMPUTED_VALUE"""),"Espirales") -> Espirales | C17: 0 | D17: =IFERROR(__xludf.DUMMYFUNCTION("""COMPUTED_VALUE"""),399) -> 399 | E17: =IFERROR(__xludf.DUMMYFUNCTION("""COMPUTED_VALUE"""),"UN") -> UN | F17: =IFERROR(__xludf.DUMMYFUNCTION("""COMPUTED_VALUE"""),"Abarrotes") -> Abarrotes | G17: =(C17)*D17 -> 0 | H17: =G17*19% -> 0 | I17: =G17+H17 -> 0
A18: =IFERROR(__xludf.DUMMYFUNCTION("""COMPUTED_VALUE"""),"ti-ing-11a33780-09cc-47f7-b11c-89e4b6139bb9") -> ti-ing-11a33780-09cc-47f7-b11c-89e4b6139bb9 | B18: =IFERROR(__xludf.DUMMYFUNCTION("""COMPUTED_VALUE"""),"Garbanzos") -> Garbanzos | C18: 0 | D18: =IFERROR(__xludf.DUMMYFUNCTION("""COMPUTED_VALUE"""),2291.25) -> 2291.25 | E18: =IFERROR(__xludf.DUMMYFUNCTION("""COMPUTED_VALUE"""),"KG") -> KG | F18: =IFERROR(__xludf.DUMMYFUNCTION("""COMPUTED_VALUE"""),"Abarrotes") -> Abarrotes | G18: =(C18)*D18 -> 0 | H18: =G18*19% -> 0 | I18: =G18+H18 -> 0
A19: =IFERROR(__xludf.DUMMYFUNCTION("""COMPUTED_VALUE"""),"ti-ing-16366b6f-c022-48bc-9b77-61765f107986") -> ti-ing-16366b6f-c022-48bc-9b77-61765f107986 | B19: =IFERROR(__xludf.DUMMYFUNCTION("""COMPUTED_VALUE"""),"Harina pan") -> Harina pan | C19: 0 | D19: =IFERROR(__xludf.DUMMYFUNCTION("""COMPUTED_VALUE"""),1638.667) -> 1638.667 | E19: =IFERROR(__xludf.DUMMYFUNCTION("""COMPUTED_VALUE"""),"KG") -> KG | F19: =IFERROR(__xludf.DUMMYFUNCTION("""COMPUTED_VALUE"""),"Abarrotes") -> Abarrotes | G19: =(C19)*D19 -> 0 | H19: =G19*19% -> 0 | I19: =G19+H19 -> 0
A20: =IFERROR(__xludf.DUMMYFUNCTION("""COMPUTED_VALUE"""),"ti-ing-e6ff2cd2-0729-44b9-b0d3-457299c1ead8") -> ti-ing-e6ff2cd2-0729-44b9-b0d3-457299c1ead8 | B20: =IFERROR(__xludf.DUMMYFUNCTION("""COMPUTED_VALUE"""),"Huevos Arizona") -> Huevos Arizona | C20: 177 | D20: =IFERROR(__xludf.DUMMYFUNCTION("""COMPUTED_VALUE"""),138) -> 138 | E20: =IFERROR(__xludf.DUMMYFUNCTION("""COMPUTED_VALUE"""),"UN") -> UN | F20: =IFERROR(__xludf.DUMMYFUNCTION("""COMPUTED_VALUE"""),"Abarrotes") -> Abarrotes | G20: =(C20)*D20 -> 24426 | H20: =G20*19% -> 4640.94 | I20: =G20+H20 -> 29066.94
A21: =IFERROR(__xludf.DUMMYFUNCTION("""COMPUTED_VALUE"""),"ti-ing-06898fd0-9448-431b-9bad-3526a93cf181") -> ti-ing-06898fd0-9448-431b-9bad-3526a93cf181 | B21: =IFERROR(__xludf.DUMMYFUNCTION("""COMPUTED_VALUE"""),"Ketchup kg") -> Ketchup kg | C21: 0 | D21: =IFERROR(__xludf.DUMMYFUNCTION("""COMPUTED_VALUE"""),1550) -> 1550 | E21: =IFERROR(__xludf.DUMMYFUNCTION("""COMPUTED_VALUE"""),"KG") -> KG | F21: =IFERROR(__xludf.DUMMYFUNCTION("""COMPUTED_VALUE"""),"Abarrotes") -> Abarrotes | G21: =(C21)*D21 -> 0 | H21: =G21*19% -> 0 | I21: =G21+H21 -> 0
A22: =IFERROR(__xludf.DUMMYFUNCTION("""COMPUTED_VALUE"""),"ti-ing-f3eeca8c-b308-4136-a438-0f68fc53c279") -> ti-ing-f3eeca8c-b308-4136-a438-0f68fc53c279 | B22: =IFERROR(__xludf.DUMMYFUNCTION("""COMPUTED_VALUE"""),"Lasagne Chef") -> Lasagne Chef | C22: 2.44 | D22: =IFERROR(__xludf.DUMMYFUNCTION("""COMPUTED_VALUE"""),3831.8) -> 3831.8 | E22: =IFERROR(__xludf.DUMMYFUNCTION("""COMPUTED_VALUE"""),"kg") -> kg | F22: =IFERROR(__xludf.DUMMYFUNCTION("""COMPUTED_VALUE"""),"Abarrotes") -> Abarrotes | G22: =(C22)*D22 -> 9349.592 | H22: =G22*19% -> 1776.4225 | I22: =G22+H22 -> 11126.014
A23: =IFERROR(__xludf.DUMMYFUNCTION("""COMPUTED_VALUE"""),"ti-ing-20a9682d-4a6c-42c4-a3ed-312cab8df904") -> ti-ing-20a9682d-4a6c-42c4-a3ed-312cab8df904 | B23: =IFERROR(__xludf.DUMMYFUNCTION("""COMPUTED_VALUE"""),"Laurel") -> Laurel | C23: 0.118 | D23: =IFERROR(__xludf.DUMMYFUNCTION("""COMPUTED_VALUE"""),75280) -> 75280 | E23: =IFERROR(__xludf.DUMMYFUNCTION("""COMPUTED_VALUE"""),"KG") -> KG | F23: =IFERROR(__xludf.DUMMYFUNCTION("""COMPUTED_VALUE"""),"Abarrotes") -> Abarrotes | G23: =(C23)*D23 -> 8883.04 | H23: =G23*19% -> 1687.7776 | I23: =G23+H23 -> 10570.818
A24: =IFERROR(__xludf.DUMMYFUNCTION("""COMPUTED_VALUE"""),"ti-ing-a5f32751-2fe1-4388-acd1-977dd4d921a6") -> ti-ing-a5f32751-2fe1-4388-acd1-977dd4d921a6 | B24: =IFERROR(__xludf.DUMMYFUNCTION("""COMPUTED_VALUE"""),"Lentejas (colacion personal)") -> Lentejas (colacion personal) | C24: 0 | D24: =IFERROR(__xludf.DUMMYFUNCTION("""COMPUTED_VALUE"""),2118) -> 2118 | E24: =IFERROR(__xludf.DUMMYFUNCTION("""COMPUTED_VALUE"""),"KG") -> KG | F24: =IFERROR(__xludf.DUMMYFUNCTION("""COMPUTED_VALUE"""),"Abarrotes") -> Abarrotes | G24: =(C24)*D24 -> 0 | H24: =G24*19% -> 0 | I24: =G24+H24 -> 0
A25: =IFERROR(__xludf.DUMMYFUNCTION("""COMPUTED_VALUE"""),"ti-ing-69061f8d-e4d9-4fc4-b44e-0cd173ebf8f3") -> ti-ing-69061f8d-e4d9-4fc4-b44e-0cd173ebf8f3 | B25: =IFERROR(__xludf.DUMMYFUNCTION("""COMPUTED_VALUE"""),"Maicena kg") -> Maicena kg | C25: 0.648 | D25: =IFERROR(__xludf.DUMMYFUNCTION("""COMPUTED_VALUE"""),1582) -> 1582 | E25: =IFERROR(__xludf.DUMMYFUNCTION("""COMPUTED_VALUE"""),"KG") -> KG | F25: =IFERROR(__xludf.DUMMYFUNCTION("""COMPUTED_VALUE"""),"Abarrotes") -> Abarrotes | G25: =(C25)*D25 -> 1025.136 | H25: =G25*19% -> 194.77584 | I25: =G25+H25 -> 1219.9118
A26: =IFERROR(__xludf.DUMMYFUNCTION("""COMPUTED_VALUE"""),"ti-ing-3dba6697-1589-49e0-8e6e-951b48b7d160") -> ti-ing-3dba6697-1589-49e0-8e6e-951b48b7d160 | B26: =IFERROR(__xludf.DUMMYFUNCTION("""COMPUTED_VALUE"""),"Mayonesa Hellmans") -> Mayonesa Hellmans | C26: 5.918 | D26: =IFERROR(__xludf.DUMMYFUNCTION("""COMPUTED_VALUE"""),3989.362) -> 3989.362 | E26: =IFERROR(__xludf.DUMMYFUNCTION("""COMPUTED_VALUE"""),"Kg") -> Kg | F26: =IFERROR(__xludf.DUMMYFUNCTION("""COMPUTED_VALUE"""),"Abarrotes") -> Abarrotes | G26: =(C26)*D26 -> 23609.044 | H26: =G26*19% -> 4485.7184 | I26: =G26+H26 -> 28094.763
B27: =IFERROR(__xludf.DUMMYFUNCTION("""COMPUTED_VALUE"""),"Metabisulfito de sodio") -> Metabisulfito de sodio | C27: 0.114 | D27: =IFERROR(__xludf.DUMMYFUNCTION("""COMPUTED_VALUE"""),14958) -> 14958 | E27: =IFERROR(__xludf.DUMMYFUNCTION("""COMPUTED_VALUE"""),"KG") -> KG | F27: =IFERROR(__xludf.DUMMYFUNCTION("""COMPUTED_VALUE"""),"Abarrotes") -> Abarrotes | G27: =(C27)*D27 -> 1705.212 | H27: =G27*19% -> 323.99028 | I27: =G27+H27 -> 2029.2023
A28: =IFERROR(__xludf.DUMMYFUNCTION("""COMPUTED_VALUE"""),"ti-ing-55acf21a-55c1-406f-a76b-b81347750e20") -> ti-ing-55acf21a-55c1-406f-a76b-b81347750e20 | B28: =IFERROR(__xludf.DUMMYFUNCTION("""COMPUTED_VALUE"""),"Mostaza") -> Mostaza | C28: 1.246 | D28: =IFERROR(__xludf.DUMMYFUNCTION("""COMPUTED_VALUE"""),1336) -> 1336 | E28: =IFERROR(__xludf.DUMMYFUNCTION("""COMPUTED_VALUE"""),"KG") -> KG | F28: =IFERROR(__xludf.DUMMYFUNCTION("""COMPUTED_VALUE"""),"Abarrotes") -> Abarrotes | G28: =(C28)*D28 -> 1664.656 | H28: =G28*19% -> 316.28464 | I28: =G28+H28 -> 1980.9406
A29: =IFERROR(__xludf.DUMMYFUNCTION("""COMPUTED_VALUE"""),"ti-ing-1a1ad4e7-e7d7-4d58-a706-bfd83210f90b") -> ti-ing-1a1ad4e7-e7d7-4d58-a706-bfd83210f90b | B29: =IFERROR(__xludf.DUMMYFUNCTION("""COMPUTED_VALUE"""),"Oregano kg") -> Oregano kg | C29: 0.902 | D29: =IFERROR(__xludf.DUMMYFUNCTION("""COMPUTED_VALUE"""),4812) -> 4812 | E29: =IFERROR(__xludf.DUMMYFUNCTION("""COMPUTED_VALUE"""),"KG") -> KG | F29: =IFERROR(__xludf.DUMMYFUNCTION("""COMPUTED_VALUE"""),"Abarrotes") -> Abarrotes | G29: =(C29)*D29 -> 4340.424 | H29: =G29*19% -> 824.68056 | I29: =G29+H29 -> 5165.1046
A30: =IFERROR(__xludf.DUMMYFUNCTION("""COMPUTED_VALUE"""),"ti-ing-dc13f521-8e90-4186-98aa-e2a49341278b") -> ti-ing-dc13f521-8e90-4186-98aa-e2a49341278b | B30: =IFERROR(__xludf.DUMMYFUNCTION("""COMPUTED_VALUE"""),"Paprika") -> Paprika | C30: 0.822 | D30: =IFERROR(__xludf.DUMMYFUNCTION("""COMPUTED_VALUE"""),3850) -> 3850 | E30: =IFERROR(__xludf.DUMMYFUNCTION("""COMPUTED_VALUE"""),"KG") -> KG | F30: =IFERROR(__xludf.DUMMYFUNCTION("""COMPUTED_VALUE"""),"Abarrotes") -> Abarrotes | G30: =(C30)*D30 -> 3164.7 | H30: =G30*19% -> 601.293 | I30: =G30+H30 -> 3765.993
B31: =IFERROR(__xludf.DUMMYFUNCTION("""COMPUTED_VALUE"""),"Pasta aji panca") -> Pasta aji panca | C31: 0 | D31: =IFERROR(__xludf.DUMMYFUNCTION("""COMPUTED_VALUE"""),14335) -> 14335 | E31: =IFERROR(__xludf.DUMMYFUNCTION("""COMPUTED_VALUE"""),"KG") -> KG | F31: =IFERROR(__xludf.DUMMYFUNCTION("""COMPUTED_VALUE"""),"Abarrotes") -> Abarrotes | G31: =(C31)*D31 -> 0 | H31: =G31*19% -> 0 | I31: =G31+H31 -> 0
A32: =IFERROR(__xludf.DUMMYFUNCTION("""COMPUTED_VALUE"""),"ti-ing-dce3151a-440e-4adc-b6f6-75fb61de8ac6") -> ti-ing-dce3151a-440e-4adc-b6f6-75fb61de8ac6 | B32: =IFERROR(__xludf.DUMMYFUNCTION("""COMPUTED_VALUE"""),"Pimienta") -> Pimienta | C32: 0.224 | D32: =IFERROR(__xludf.DUMMYFUNCTION("""COMPUTED_VALUE"""),11258) -> 11258 | E32: =IFERROR(__xludf.DUMMYFUNCTION("""COMPUTED_VALUE"""),"UN") -> UN | F32: =IFERROR(__xludf.DUMMYFUNCTION("""COMPUTED_VALUE"""),"Abarrotes") -> Abarrotes | G32: =(C32)*D32 -> 2521.792 | H32: =G32*19% -> 479.14048 | I32: =G32+H32 -> 3000.9325
A33: =IFERROR(__xludf.DUMMYFUNCTION("""COMPUTED_VALUE"""),"ti-ing-904468d1-7aa3-4ea8-a76b-bb2fb6b316e2") -> ti-ing-904468d1-7aa3-4ea8-a76b-bb2fb6b316e2 | B33: =IFERROR(__xludf.DUMMYFUNCTION("""COMPUTED_VALUE"""),"Porotos") -> Porotos | C33: 0 | D33: =IFERROR(__xludf.DUMMYFUNCTION("""COMPUTED_VALUE"""),1778) -> 1778 | E33: =IFERROR(__xludf.DUMMYFUNCTION("""COMPUTED_VALUE"""),"KG") -> KG | F33: =IFERROR(__xludf.DUMMYFUNCTION("""COMPUTED_VALUE"""),"Abarrotes") -> Abarrotes | G33: =(C33)*D33 -> 0 | H33: =G33*19% -> 0 | I33: =G33+H33 -> 0
A34: =IFERROR(__xludf.DUMMYFUNCTION("""COMPUTED_VALUE"""),"ti-ing-67451d2d-c408-4de8-b583-b73d147b0c3c") -> ti-ing-67451d2d-c408-4de8-b583-b73d147b0c3c | B34: =IFERROR(__xludf.DUMMYFUNCTION("""COMPUTED_VALUE"""),"Porotos verde") -> Porotos verde | C34: 0 | D34: =IFERROR(__xludf.DUMMYFUNCTION("""COMPUTED_VALUE"""),680) -> 680 | E34: =IFERROR(__xludf.DUMMYFUNCTION("""COMPUTED_VALUE"""),"KG") -> KG | F34: =IFERROR(__xludf.DUMMYFUNCTION("""COMPUTED_VALUE"""),"Abarrotes") -> Abarrotes | G34: =(C34)*D34 -> 0 | H34: =G34*19% -> 0 | I34: =G34+H34 -> 0
B35: =IFERROR(__xludf.DUMMYFUNCTION("""COMPUTED_VALUE"""),"Quinua mixta") -> Quinua mixta | C35: 0.616 | D35: =IFERROR(__xludf.DUMMYFUNCTION("""COMPUTED_VALUE"""),4596) -> 4596 | E35: =IFERROR(__xludf.DUMMYFUNCTION("""COMPUTED_VALUE"""),"KG") -> KG | F35: =IFERROR(__xludf.DUMMYFUNCTION("""COMPUTED_VALUE"""),"Abarrotes") -> Abarrotes | G35: =(C35)*D35 -> 2831.136 | H35: =G35*19% -> 537.91584 | I35: =G35+H35 -> 3369.0518
A36: =IFERROR(__xludf.DUMMYFUNCTION("""COMPUTED_VALUE"""),"ti-ing-93b9bb76-8e33-404b-b4a2-19bddccf01ff") -> ti-ing-93b9bb76-8e33-404b-b4a2-19bddccf01ff | B36: =IFERROR(__xludf.DUMMYFUNCTION("""COMPUTED_VALUE"""),"Romero") -> Romero | C36: 0.278 | D36: =IFERROR(__xludf.DUMMYFUNCTION("""COMPUTED_VALUE"""),7135.19) -> 7135.19 | E36: =IFERROR(__xludf.DUMMYFUNCTION("""COMPUTED_VALUE"""),"UN") -> UN | F36: =IFERROR(__xludf.DUMMYFUNCTION("""COMPUTED_VALUE"""),"Abarrotes") -> Abarrotes | G36: =(C36)*D36 -> 1983.5828 | H36: =G36*19% -> 376.88074 | I36: =G36+H36 -> 2360.4636
A37: =IFERROR(__xludf.DUMMYFUNCTION("""COMPUTED_VALUE"""),"ti-ing-4818468c-bc91-40f7-9fa4-eb19def3bff7") -> ti-ing-4818468c-bc91-40f7-9fa4-eb19def3bff7 | B37: =IFERROR(__xludf.DUMMYFUNCTION("""COMPUTED_VALUE"""),"Sal fina") -> Sal fina | C37: 0.502 | D37: =IFERROR(__xludf.DUMMYFUNCTION("""COMPUTED_VALUE"""),290) -> 290 | E37: =IFERROR(__xludf.DUMMYFUNCTION("""COMPUTED_VALUE"""),"KG") -> KG | F37: =IFERROR(__xludf.DUMMYFUNCTION("""COMPUTED_VALUE"""),"Abarrotes") -> Abarrotes | G37: =(C37)*D37 -> 145.58 | H37: =G37*19% -> 27.6602 | I37: =G37+H37 -> 173.2402
A38: =IFERROR(__xludf.DUMMYFUNCTION("""COMPUTED_VALUE"""),"ti-ing-562ebc87-5bd7-439e-9451-999b88fdd759") -> ti-ing-562ebc87-5bd7-439e-9451-999b88fdd759 | B38: =IFERROR(__xludf.DUMMYFUNCTION("""COMPUTED_VALUE"""),"Salsa De Tomate") -> Salsa De Tomate | C38: 1.326 | D38: =IFERROR(__xludf.DUMMYFUNCTION("""COMPUTED_VALUE"""),1587) -> 1587 | E38: =IFERROR(__xludf.DUMMYFUNCTION("""COMPUTED_VALUE"""),"KG") -> KG | F38: =IFERROR(__xludf.DUMMYFUNCTION("""COMPUTED_VALUE"""),"Abarrotes") -> Abarrotes | G38: =(C38)*D38 -> 2104.362 | H38: =G38*19% -> 399.82878 | I38: =G38+H38 -> 2504.1908
A39: =IFERROR(__xludf.DUMMYFUNCTION("""COMPUTED_VALUE"""),"ti-ing-4f8ac25a-9411-4a59-806f-62cee4c4e0f1") -> ti-ing-4f8ac25a-9411-4a59-806f-62cee4c4e0f1 | B39: =IFERROR(__xludf.DUMMYFUNCTION("""COMPUTED_VALUE"""),"Salsa inglesa") -> Salsa inglesa | C39: 0.282 | D39: =IFERROR(__xludf.DUMMYFUNCTION("""COMPUTED_VALUE"""),4035) -> 4035 | E39: =IFERROR(__xludf.DUMMYFUNCTION("""COMPUTED_VALUE"""),"Kg") -> Kg | F39: =IFERROR(__xludf.DUMMYFUNCTION("""COMPUTED_VALUE"""),"Abarrotes") -> Abarrotes | G39: =(C39)*D39 -> 1137.87 | H39: =G39*19% -> 216.1953 | I39: =G39+H39 -> 1354.0653
A40: =IFERROR(__xludf.DUMMYFUNCTION("""COMPUTED_VALUE"""),"ti-ing-9f3dba64-3cca-408b-ac1e-45359966da75") -> ti-ing-9f3dba64-3cca-408b-ac1e-45359966da75 | B40: =IFERROR(__xludf.DUMMYFUNCTION("""COMPUTED_VALUE"""),"Salsa Soya") -> Salsa Soya | C40: 0.9 | D40: =IFERROR(__xludf.DUMMYFUNCTION("""COMPUTED_VALUE"""),1625) -> 1625 | E40: =IFERROR(__xludf.DUMMYFUNCTION("""COMPUTED_VALUE"""),"KG") -> KG | F40: =IFERROR(__xludf.DUMMYFUNCTION("""COMPUTED_VALUE"""),"Abarrotes") -> Abarrotes | G40: =(C40)*D40 -> 1462.5 | H40: =G40*19% -> 277.875 | I40: =G40+H40 -> 1740.375
A41: =IFERROR(__xludf.DUMMYFUNCTION("""COMPUTED_VALUE"""),"ti-ing-7e2cee8d-1717-48ff-96be-290c5aa01461") -> ti-ing-7e2cee8d-1717-48ff-96be-290c5aa01461 | B41: =IFERROR(__xludf.DUMMYFUNCTION("""COMPUTED_VALUE"""),"Semilla cilantro") -> Semilla cilantro | C41: 0.698 | D41: =IFERROR(__xludf.DUMMYFUNCTION("""COMPUTED_VALUE"""),4874.396) -> 4874.396 | E41: =IFERROR(__xludf.DUMMYFUNCTION("""COMPUTED_VALUE"""),"KG") -> KG | F41: =IFERROR(__xludf.DUMMYFUNCTION("""COMPUTED_VALUE"""),"Abarrotes") -> Abarrotes | G41: =(C41)*D41 -> 3402.3284 | H41: =G41*19% -> 646.4424 | I41: =G41+H41 -> 4048.7708
A42: =IFERROR(__xludf.DUMMYFUNCTION("""COMPUTED_VALUE"""),"ti-ing-7a052395-bb4e-4c4d-a1cf-c498a5386bb1") -> ti-ing-7a052395-bb4e-4c4d-a1cf-c498a5386bb1 | B42: =IFERROR(__xludf.DUMMYFUNCTION("""COMPUTED_VALUE"""),"Tomillo") -> Tomillo | C42: 0.938 | D42: =IFERROR(__xludf.DUMMYFUNCTION("""COMPUTED_VALUE"""),9885) -> 9885 | E42: =IFERROR(__xludf.DUMMYFUNCTION("""COMPUTED_VALUE"""),"UN") -> UN | F42: =IFERROR(__xludf.DUMMYFUNCTION("""COMPUTED_VALUE"""),"Abarrotes") -> Abarrotes | G42: =(C42)*D42 -> 9272.13 | H42: =G42*19% -> 1761.7047 | I42: =G42+H42 -> 11033.835
A43: =IFERROR(__xludf.DUMMYFUNCTION("""COMPUTED_VALUE"""),"ti-ing-b38390e4-8c11-4339-8209-7a310643c3be") -> ti-ing-b38390e4-8c11-4339-8209-7a310643c3be | B43: =IFERROR(__xludf.DUMMYFUNCTION("""COMPUTED_VALUE"""),"Vinagre") -> Vinagre | C43: 2.112 | D43: =IFERROR(__xludf.DUMMYFUNCTION("""COMPUTED_VALUE"""),593) -> 593 | E43: =IFERROR(__xludf.DUMMYFUNCTION("""COMPUTED_VALUE"""),"UN") -> UN | F43: =IFERROR(__xludf.DUMMYFUNCTION("""COMPUTED_VALUE"""),"Abarrotes") -> Abarrotes | G43: =(C43)*D43 -> 1252.416 | H43: =G43*19% -> 237.95904 | I43: =G43+H43 -> 1490.375
A44: =IFERROR(__xludf.DUMMYFUNCTION("""COMPUTED_VALUE"""),"ti-ing-32a0a1de-7d7a-48fa-8701-58015f10f3d8") -> ti-ing-32a0a1de-7d7a-48fa-8701-58015f10f3d8 | B44: =IFERROR(__xludf.DUMMYFUNCTION("""COMPUTED_VALUE"""),"BOLSA BASURA GRANDE (un)") -> BOLSA BASURA GRANDE (un) | C44: 5 | D44: =IFERROR(__xludf.DUMMYFUNCTION("""COMPUTED_VALUE"""),391.1) -> 391.1 | E44: =IFERROR(__xludf.DUMMYFUNCTION("""COMPUTED_VALUE"""),"UN") -> UN | F44: =IFERROR(__xludf.DUMMYFUNCTION("""COMPUTED_VALUE"""),"Aseo") -> Aseo | G44: =(C44)*D44 -> 1955.5 | H44: =G44*19% -> 371.545 | I44: =G44+H44 -> 2327.045
A45: =IFERROR(__xludf.DUMMYFUNCTION("""COMPUTED_VALUE"""),"ti-ing-addf5a00-64be-48da-80f1-f963e13357c9") -> ti-ing-addf5a00-64be-48da-80f1-f963e13357c9 | B45: =IFERROR(__xludf.DUMMYFUNCTION("""COMPUTED_VALUE"""),"CLORO 5 LTS") -> CLORO 5 LTS | C45: 4.026 | D45: =IFERROR(__xludf.DUMMYFUNCTION("""COMPUTED_VALUE"""),247) -> 247 | E45: =IFERROR(__xludf.DUMMYFUNCTION("""COMPUTED_VALUE"""),"LT") -> LT | F45: =IFERROR(__xludf.DUMMYFUNCTION("""COMPUTED_VALUE"""),"Aseo") -> Aseo | G45: =(C45)*D45 -> 994.422 | H45: =G45*19% -> 188.94018 | I45: =G45+H45 -> 1183.3622
A46: =IFERROR(__xludf.DUMMYFUNCTION("""COMPUTED_VALUE"""),"ti-ing-2a9f7a04-ff9b-4634-9f27-edac618856d6") -> ti-ing-2a9f7a04-ff9b-4634-9f27-edac618856d6 | B46: =IFERROR(__xludf.DUMMYFUNCTION("""COMPUTED_VALUE"""),"DESENGRASANTE 5 lt") -> DESENGRASANTE 5 lt | C46: 3.38 | D46: =IFERROR(__xludf.DUMMYFUNCTION("""COMPUTED_VALUE"""),658.8) -> 658.8 | E46: =IFERROR(__xludf.DUMMYFUNCTION("""COMPUTED_VALUE"""),"LT") -> LT | F46: =IFERROR(__xludf.DUMMYFUNCTION("""COMPUTED_VALUE"""),"Aseo") -> Aseo | G46: =(C46)*D46 -> 2226.744 | H46: =G46*19% -> 423.08136 | I46: =G46+H46 -> 2649.8254
A47: =IFERROR(__xludf.DUMMYFUNCTION("""COMPUTED_VALUE"""),"ti-ing-e0ae8367-512a-46da-9188-edb6aed9ccac") -> ti-ing-e0ae8367-512a-46da-9188-edb6aed9ccac | B47: =IFERROR(__xludf.DUMMYFUNCTION("""COMPUTED_VALUE"""),"ESCOBA") -> ESCOBA | C47: 1 | D47: =IFERROR(__xludf.DUMMYFUNCTION("""COMPUTED_VALUE"""),1250) -> 1250 | E47: =IFERROR(__xludf.DUMMYFUNCTION("""COMPUTED_VALUE"""),"UN") -> UN | F47: =IFERROR(__xludf.DUMMYFUNCTION("""COMPUTED_VALUE"""),"Aseo") -> Aseo | G47: =(C47)*D47 -> 1250 | H47: =G47*19% -> 237.5 | I47: =G47+H47 -> 1487.5
A48: =IFERROR(__xludf.DUMMYFUNCTION("""COMPUTED_VALUE"""),"ti-ing-102eb718-4b52-41a7-9529-6a535c4ceb37") -> ti-ing-102eb718-4b52-41a7-9529-6a535c4ceb37 | B48: =IFERROR(__xludf.DUMMYFUNCTION("""COMPUTED_VALUE"""),"ESPONJAS AMARILLAS") -> ESPONJAS AMARILLAS | C48: 4 | D48: =IFERROR(__xludf.DUMMYFUNCTION("""COMPUTED_VALUE"""),149) -> 149 | E48: =IFERROR(__xludf.DUMMYFUNCTION("""COMPUTED_VALUE"""),"UN") -> UN | F48: =IFERROR(__xludf.DUMMYFUNCTION("""COMPUTED_VALUE"""),"Aseo") -> Aseo | G48: =(C48)*D48 -> 596 | H48: =G48*19% -> 113.24 | I48: =G48+H48 -> 709.24
A49: =IFERROR(__xludf.DUMMYFUNCTION("""COMPUTED_VALUE"""),"ti-ing-04fc2068-57ca-42bc-bedb-ceda3e223def") -> ti-ing-04fc2068-57ca-42bc-bedb-ceda3e223def | B49: =IFERROR(__xludf.DUMMYFUNCTION("""COMPUTED_VALUE"""),"Guantes De Látex L") -> Guantes De Látex L | C49: 1.3 | D49: =IFERROR(__xludf.DUMMYFUNCTION("""COMPUTED_VALUE"""),3649.902) -> 3649.902 | E49: =IFERROR(__xludf.DUMMYFUNCTION("""COMPUTED_VALUE"""),"UN") -> UN | F49: =IFERROR(__xludf.DUMMYFUNCTION("""COMPUTED_VALUE"""),"Aseo") -> Aseo | G49: =(C49)*D49 -> 4744.8726 | H49: =G49*19% -> 901.52579 | I49: =G49+H49 -> 5646.3984
A50: =IFERROR(__xludf.DUMMYFUNCTION("""COMPUTED_VALUE"""),"ti-ing-3c965e17-4bc3-453d-b74f-c682b54aeade") -> ti-ing-3c965e17-4bc3-453d-b74f-c682b54aeade | B50: =IFERROR(__xludf.DUMMYFUNCTION("""COMPUTED_VALUE"""),"Guantes De Látex M") -> Guantes De Látex M | C50: 0 | D50: =IFERROR(__xludf.DUMMYFUNCTION("""COMPUTED_VALUE"""),3650) -> 3650 | E50: =IFERROR(__xludf.DUMMYFUNCTION("""COMPUTED_VALUE"""),"UN") -> UN | F50: =IFERROR(__xludf.DUMMYFUNCTION("""COMPUTED_VALUE"""),"Aseo") -> Aseo | G50: =(C50)*D50 -> 0 | H50: =G50*19% -> 0 | I50: =G50+H50 -> 0
A51: =IFERROR(__xludf.DUMMYFUNCTION("""COMPUTED_VALUE"""),"ti-ing-90438c34-c1c8-455a-8b38-f56ab57f0e76") -> ti-ing-90438c34-c1c8-455a-8b38-f56ab57f0e76 | B51: =IFERROR(__xludf.DUMMYFUNCTION("""COMPUTED_VALUE"""),"LAVALOZAS") -> LAVALOZAS | C51: 4.884 | D51: =IFERROR(__xludf.DUMMYFUNCTION("""COMPUTED_VALUE"""),381.6) -> 381.6 | E51: =IFERROR(__xludf.DUMMYFUNCTION("""COMPUTED_VALUE"""),"LT") -> LT | F51: =IFERROR(__xludf.DUMMYFUNCTION("""COMPUTED_VALUE"""),"Aseo") -> Aseo | G51: =(C51)*D51 -> 1863.7344 | H51: =G51*19% -> 354.10954 | I51: =G51+H51 -> 2217.8439
A52: =IFERROR(__xludf.DUMMYFUNCTION("""COMPUTED_VALUE"""),"ti-ing-87e4c4d7-978b-4106-9ff1-dda60dd75d70") -> ti-ing-87e4c4d7-978b-4106-9ff1-dda60dd75d70 | B52: =IFERROR(__xludf.DUMMYFUNCTION("""COMPUTED_VALUE"""),"LIMPIAPISOS") -> LIMPIAPISOS | C52: 2.562 | D52: =IFERROR(__xludf.DUMMYFUNCTION("""COMPUTED_VALUE"""),284.1160494) -> 284.11605 | E52: =IFERROR(__xludf.DUMMYFUNCTION("""COMPUTED_VALUE"""),"LT") -> LT | F52: =IFERROR(__xludf.DUMMYFUNCTION("""COMPUTED_VALUE"""),"Aseo") -> Aseo | G52: =(C52)*D52 -> 727.90532 | H52: =G52*19% -> 138.30201 | I52: =G52+H52 -> 866.20733
A53: =IFERROR(__xludf.DUMMYFUNCTION("""COMPUTED_VALUE"""),"ti-ing-64301c86-8657-4a60-9738-54b3f81ead5a") -> ti-ing-64301c86-8657-4a60-9738-54b3f81ead5a | B53: =IFERROR(__xludf.DUMMYFUNCTION("""COMPUTED_VALUE"""),"MALLAS DE PELO (100un)") -> MALLAS DE PELO (100un) | C53: 0.81 | D53: =IFERROR(__xludf.DUMMYFUNCTION("""COMPUTED_VALUE"""),1529) -> 1529 | E53: =IFERROR(__xludf.DUMMYFUNCTION("""COMPUTED_VALUE"""),"UN") -> UN | F53: =IFERROR(__xludf.DUMMYFUNCTION("""COMPUTED_VALUE"""),"Aseo") -> Aseo | G53: =(C53)*D53 -> 1238.49 | H53: =G53*19% -> 235.3131 | I53: =G53+H53 -> 1473.8031
A54: =IFERROR(__xludf.DUMMYFUNCTION("""COMPUTED_VALUE"""),"ti-ing-242bf6e9-d5c5-47e7-8f0a-88f3cbbcc3af") -> ti-ing-242bf6e9-d5c5-47e7-8f0a-88f3cbbcc3af | B54: =IFERROR(__xludf.DUMMYFUNCTION("""COMPUTED_VALUE"""),"Mascarillas") -> Mascarillas | C54: 22 | D54: =IFERROR(__xludf.DUMMYFUNCTION("""COMPUTED_VALUE"""),1350) -> 1350 | E54: =IFERROR(__xludf.DUMMYFUNCTION("""COMPUTED_VALUE"""),"UN") -> UN | F54: =IFERROR(__xludf.DUMMYFUNCTION("""COMPUTED_VALUE"""),"Aseo") -> Aseo | G54: =(C54)*D54 -> 29700 | H54: =G54*19% -> 5643 | I54: =G54+H54 -> 35343
A55: =IFERROR(__xludf.DUMMYFUNCTION("""COMPUTED_VALUE"""),"ti-ing-313073f4-b1b1-442d-b077-951f3ce67b06") -> ti-ing-313073f4-b1b1-442d-b077-951f3ce67b06 | B55: =IFERROR(__xludf.DUMMYFUNCTION("""COMPUTED_VALUE"""),"NOVA Unidad") -> NOVA Unidad | C55: 1.5 | D55: =IFERROR(__xludf.DUMMYFUNCTION("""COMPUTED_VALUE"""),2735) -> 2735 | E55: =IFERROR(__xludf.DUMMYFUNCTION("""COMPUTED_VALUE"""),"UN") -> UN | F55: =IFERROR(__xludf.DUMMYFUNCTION("""COMPUTED_VALUE"""),"Aseo") -> Aseo | G55: =(C55)*D55 -> 4102.5 | H55: =G55*19% -> 779.475 | I55: =G55+H55 -> 4881.975
A56: =IFERROR(__xludf.DUMMYFUNCTION("""COMPUTED_VALUE"""),"ti-ing-f2a85135-486f-455a-9223-1092ccd4e7cd") -> ti-ing-f2a85135-486f-455a-9223-1092ccd4e7cd | B56: =IFERROR(__xludf.DUMMYFUNCTION("""COMPUTED_VALUE"""),"PALA") -> PALA | C56: 1 | D56: =IFERROR(__xludf.DUMMYFUNCTION("""COMPUTED_VALUE"""),1165) -> 1165 | E56: =IFERROR(__xludf.DUMMYFUNCTION("""COMPUTED_VALUE"""),"UN") -> UN | F56: =IFERROR(__xludf.DUMMYFUNCTION("""COMPUTED_VALUE"""),"Aseo") -> Aseo | G56: =(C56)*D56 -> 1165 | H56: =G56*19% -> 221.35 | I56: =G56+H56 -> 1386.35
A57: =IFERROR(__xludf.DUMMYFUNCTION("""COMPUTED_VALUE"""),"ti-ing-a496bcbe-0906-4bd7-90be-10085697981e") -> ti-ing-a496bcbe-0906-4bd7-90be-10085697981e | B57: =IFERROR(__xludf.DUMMYFUNCTION("""COMPUTED_VALUE"""),"Paño microfibra") -> Paño microfibra | C57: 0 | D57: =IFERROR(__xludf.DUMMYFUNCTION("""COMPUTED_VALUE"""),650) -> 650 | E57: =IFERROR(__xludf.DUMMYFUNCTION("""COMPUTED_VALUE"""),"UN") -> UN | F57: =IFERROR(__xludf.DUMMYFUNCTION("""COMPUTED_VALUE"""),"Aseo") -> Aseo | G57: =(C57)*D57 -> 0 | H57: =G57*19% -> 0 | I57: =G57+H57 -> 0
A58: =IFERROR(__xludf.DUMMYFUNCTION("""COMPUTED_VALUE"""),"ti-ing-71ad4a79-597d-4cd3-85f8-8c113261d29e") -> ti-ing-71ad4a79-597d-4cd3-85f8-8c113261d29e | B58: =IFERROR(__xludf.DUMMYFUNCTION("""COMPUTED_VALUE"""),"PAÑOS AMARILLOS") -> PAÑOS AMARILLOS | C58: 0 | D58: =IFERROR(__xludf.DUMMYFUNCTION("""COMPUTED_VALUE"""),185) -> 185 | E58: =IFERROR(__xludf.DUMMYFUNCTION("""COMPUTED_VALUE"""),"UN") -> UN | F58: =IFERROR(__xludf.DUMMYFUNCTION("""COMPUTED_VALUE"""),"Aseo") -> Aseo | G58: =(C58)*D58 -> 0 | H58: =G58*19% -> 0 | I58: =G58+H58 -> 0
A59: =IFERROR(__xludf.DUMMYFUNCTION("""COMPUTED_VALUE"""),"ti-ing-dcad707d-6012-450f-8e1d-b50e4ae44b10") -> ti-ing-dcad707d-6012-450f-8e1d-b50e4ae44b10 | B59: =IFERROR(__xludf.DUMMYFUNCTION("""COMPUTED_VALUE"""),"TRAPOS BLANCOS") -> TRAPOS BLANCOS | C59: 1 | D59: =IFERROR(__xludf.DUMMYFUNCTION("""COMPUTED_VALUE"""),789) -> 789 | E59: =IFERROR(__xludf.DUMMYFUNCTION("""COMPUTED_VALUE"""),"UN") -> UN | F59: =IFERROR(__xludf.DUMMYFUNCTION("""COMPUTED_VALUE"""),"Aseo") -> Aseo | G59: =(C59)*D59 -> 789 | H59: =G59*19% -> 149.91 | I59: =G59+H59 -> 938.91
A60: =IFERROR(__xludf.DUMMYFUNCTION("""COMPUTED_VALUE"""),"ti-ing-46619eaa-21aa-41d5-931f-97aa9149b051") -> ti-ing-46619eaa-21aa-41d5-931f-97aa9149b051 | B60: =IFERROR(__xludf.DUMMYFUNCTION("""COMPUTED_VALUE"""),"VIRUTILLA VERDE") -> VIRUTILLA VERDE | C60: 2 | D60: =IFERROR(__xludf.DUMMYFUNCTION("""COMPUTED_VALUE"""),890) -> 890 | E60: =IFERROR(__xludf.DUMMYFUNCTION("""COMPUTED_VALUE"""),"UN") -> UN | F60: =IFERROR(__xludf.DUMMYFUNCTION("""COMPUTED_VALUE"""),"Aseo") -> Aseo | G60: =(C60)*D60 -> 1780 | H60: =G60*19% -> 338.2 | I60: =G60+H60 -> 2118.2
B61: =IFERROR(__xludf.DUMMYFUNCTION("""COMPUTED_VALUE"""),"Asado carnicero") -> Asado carnicero | C61: 0 | D61: =IFERROR(__xludf.DUMMYFUNCTION("""COMPUTED_VALUE"""),6656.013) -> 6656.013 | E61: =IFERROR(__xludf.DUMMYFUNCTION("""COMPUTED_VALUE"""),"KG") -> KG | F61: =IFERROR(__xludf.DUMMYFUNCTION("""COMPUTED_VALUE"""),"Carnes y Aves") -> Carnes y Aves | G61: =(C61)*D61 -> 0 | H61: =G61*19% -> 0 | I61: =G61+H61 -> 0
A62: =IFERROR(__xludf.DUMMYFUNCTION("""COMPUTED_VALUE"""),"ti-ing-d1d9b75c-fbe2-43ab-ae2b-b16de0e4d23a") -> ti-ing-d1d9b75c-fbe2-43ab-ae2b-b16de0e4d23a | B62: =IFERROR(__xludf.DUMMYFUNCTION("""COMPUTED_VALUE"""),"Carne Molida kg") -> Carne Molida kg | C62: 4 | D62: =IFERROR(__xludf.DUMMYFUNCTION("""COMPUTED_VALUE"""),3552.6667) -> 3552.6667 | E62: =IFERROR(__xludf.DUMMYFUNCTION("""COMPUTED_VALUE"""),"KG") -> KG | F62: =IFERROR(__xludf.DUMMYFUNCTION("""COMPUTED_VALUE"""),"Carnes y Aves") -> Carnes y Aves | G62: =(C62)*D62 -> 14210.667 | H62: =G62*19% -> 2700.0267 | I62: =G62+H62 -> 16910.693
B63: =IFERROR(__xludf.DUMMYFUNCTION("""COMPUTED_VALUE"""),"Chuleta Centro ") -> Chuleta Centro | C63: 0 | D63: =IFERROR(__xludf.DUMMYFUNCTION("""COMPUTED_VALUE"""),3623) -> 3623 | E63: =IFERROR(__xludf.DUMMYFUNCTION("""COMPUTED_VALUE"""),"KG") -> KG | F63: =IFERROR(__xludf.DUMMYFUNCTION("""COMPUTED_VALUE"""),"Carnes y Aves") -> Carnes y Aves | G63: =(C63)*D63 -> 0 | H63: =G63*19% -> 0 | I63: =G63+H63 -> 0
A64: =IFERROR(__xludf.DUMMYFUNCTION("""COMPUTED_VALUE"""),"ti-ing-f9071122-333f-445e-9d6e-66ae8844a033") -> ti-ing-f9071122-333f-445e-9d6e-66ae8844a033 | B64: =IFERROR(__xludf.DUMMYFUNCTION("""COMPUTED_VALUE"""),"Jamon Ahumado kg") -> Jamon Ahumado kg | C64: 2.716 | D64: =IFERROR(__xludf.DUMMYFUNCTION("""COMPUTED_VALUE"""),5034.167) -> 5034.167 | E64: =IFERROR(__xludf.DUMMYFUNCTION("""COMPUTED_VALUE"""),"UN") -> UN | F64: =IFERROR(__xludf.DUMMYFUNCTION("""COMPUTED_VALUE"""),"Carnes y Aves") -> Carnes y Aves | G64: =(C64)*D64 -> 13672.798 | H64: =G64*19% -> 2597.8315 | I64: =G64+H64 -> 16270.629
A65: =IFERROR(__xludf.DUMMYFUNCTION("""COMPUTED_VALUE"""),"ti-ing-f12b69a3-01b2-4d5d-927c-4e59d4a08da4") -> ti-ing-f12b69a3-01b2-4d5d-927c-4e59d4a08da4 | B65: =IFERROR(__xludf.DUMMYFUNCTION("""COMPUTED_VALUE"""),"Jamon Serrano kg") -> Jamon Serrano kg | C65: 4.76 | D65: =IFERROR(__xludf.DUMMYFUNCTION("""COMPUTED_VALUE"""),18875) -> 18875 | E65: =IFERROR(__xludf.DUMMYFUNCTION("""COMPUTED_VALUE"""),"KG") -> KG | F65: =IFERROR(__xludf.DUMMYFUNCTION("""COMPUTED_VALUE"""),"Carnes y Aves") -> Carnes y Aves | G65: =(C65)*D65 -> 89845 | H65: =G65*19% -> 17070.55 | I65: =G65+H65 -> 106915.55
A66: =IFERROR(__xludf.DUMMYFUNCTION("""COMPUTED_VALUE"""),"ti-ing-af8e0711-251d-46dc-a4b4-52572c7d1a82") -> ti-ing-af8e0711-251d-46dc-a4b4-52572c7d1a82 | B66: =IFERROR(__xludf.DUMMYFUNCTION("""COMPUTED_VALUE"""),"Mortadela Artesanal") -> Mortadela Artesanal | C66: 0 | D66: =IFERROR(__xludf.DUMMYFUNCTION("""COMPUTED_VALUE"""),9042.945) -> 9042.945 | E66: =IFERROR(__xludf.DUMMYFUNCTION("""COMPUTED_VALUE"""),"KG") -> KG | F66: =IFERROR(__xludf.DUMMYFUNCTION("""COMPUTED_VALUE"""),"Carnes y Aves") -> Carnes y Aves | G66: =(C66)*D66 -> 0 | H66: =G66*19% -> 0 | I66: =G66+H66 -> 0
A67: =IFERROR(__xludf.DUMMYFUNCTION("""COMPUTED_VALUE"""),"ti-ing-870258ef-47ee-433f-97eb-0d71c0a61a73") -> ti-ing-870258ef-47ee-433f-97eb-0d71c0a61a73 | B67: =IFERROR(__xludf.DUMMYFUNCTION("""COMPUTED_VALUE"""),"Pollo Ganso (caja 20 kg)") -> Pollo Ganso (caja 20 kg) | C67: 0 | D67: =IFERROR(__xludf.DUMMYFUNCTION("""COMPUTED_VALUE"""),7650) -> 7650 | E67: =IFERROR(__xludf.DUMMYFUNCTION("""COMPUTED_VALUE"""),"KG") -> KG | F67: =IFERROR(__xludf.DUMMYFUNCTION("""COMPUTED_VALUE"""),"Carnes y Aves") -> Carnes y Aves | G67: =(C67)*D67 -> 0 | H67: =G67*19% -> 0 | I67: =G67+H67 -> 0
A68: =IFERROR(__xludf.DUMMYFUNCTION("""COMPUTED_VALUE"""),"ti-ing-1e2c5389-4e8e-48cb-b2d1-086e93d588b5") -> ti-ing-1e2c5389-4e8e-48cb-b2d1-086e93d588b5 | B68: =IFERROR(__xludf.DUMMYFUNCTION("""COMPUTED_VALUE"""),"Pollo pechuga deshuesada (caja 20 kg)") -> Pollo pechuga deshuesada (caja 20 kg) | C68: 32 | D68: =IFERROR(__xludf.DUMMYFUNCTION("""COMPUTED_VALUE"""),3376.417) -> 3376.417 | E68: =IFERROR(__xludf.DUMMYFUNCTION("""COMPUTED_VALUE"""),"KG") -> KG | F68: =IFERROR(__xludf.DUMMYFUNCTION("""COMPUTED_VALUE"""),"Carnes y Aves") -> Carnes y Aves | G68: =(C68)*D68 -> 108045.34 | H68: =G68*19% -> 20528.615 | I68: =G68+H68 -> 128573.96
A69: =IFERROR(__xludf.DUMMYFUNCTION("""COMPUTED_VALUE"""),"ti-ing-9295c12c-83e9-4b4d-8fdf-d0e254d5f19c") -> ti-ing-9295c12c-83e9-4b4d-8fdf-d0e254d5f19c | B69: =IFERROR(__xludf.DUMMYFUNCTION("""COMPUTED_VALUE"""),"Pulpa Cerdo") -> Pulpa Cerdo | C69: 10.754 | D69: =IFERROR(__xludf.DUMMYFUNCTION("""COMPUTED_VALUE"""),2941.004) -> 2941.004 | E69: =IFERROR(__xludf.DUMMYFUNCTION("""COMPUTED_VALUE"""),"KG") -> KG | F69: =IFERROR(__xludf.DUMMYFUNCTION("""COMPUTED_VALUE"""),"Carnes y Aves") -> Carnes y Aves | G69: =(C69)*D69 -> 31627.557 | H69: =G69*19% -> 6009.2358 | I69: =G69+H69 -> 37636.793
A70: =IFERROR(__xludf.DUMMYFUNCTION("""COMPUTED_VALUE"""),"ti-ing-1ac2f275-c7c0-4e86-969d-20c2546692b7") -> ti-ing-1ac2f275-c7c0-4e86-969d-20c2546692b7 | B70: =IFERROR(__xludf.DUMMYFUNCTION("""COMPUTED_VALUE"""),"Salame kg") -> Salame kg | C70: 2.58 | D70: =IFERROR(__xludf.DUMMYFUNCTION("""COMPUTED_VALUE"""),8993.75) -> 8993.75 | E70: =IFERROR(__xludf.DUMMYFUNCTION("""COMPUTED_VALUE"""),"KG") -> KG | F70: =IFERROR(__xludf.DUMMYFUNCTION("""COMPUTED_VALUE"""),"Carnes y Aves") -> Carnes y Aves | G70: =(C70)*D70 -> 23203.875 | H70: =G70*19% -> 4408.7362 | I70: =G70+H70 -> 27612.611
A71: =IFERROR(__xludf.DUMMYFUNCTION("""COMPUTED_VALUE"""),"ti-ing-4307c859-5883-4ead-8fa8-72399922dd2d") -> ti-ing-4307c859-5883-4ead-8fa8-72399922dd2d | B71: =IFERROR(__xludf.DUMMYFUNCTION("""COMPUTED_VALUE"""),"Salchicha kg") -> Salchicha kg | C71: 0 | D71: =IFERROR(__xludf.DUMMYFUNCTION("""COMPUTED_VALUE"""),3187.5) -> 3187.5 | E71: =IFERROR(__xludf.DUMMYFUNCTION("""COMPUTED_VALUE"""),"KG") -> KG | F71: =IFERROR(__xludf.DUMMYFUNCTION("""COMPUTED_VALUE"""),"Carnes y Aves") -> Carnes y Aves | G71: =(C71)*D71 -> 0 | H71: =G71*19% -> 0 | I71: =G71+H71 -> 0
A72: =IFERROR(__xludf.DUMMYFUNCTION("""COMPUTED_VALUE"""),"ti-ing-2ed3ba0f-4530-4e48-8b65-f0e572390377") -> ti-ing-2ed3ba0f-4530-4e48-8b65-f0e572390377 | B72: =IFERROR(__xludf.DUMMYFUNCTION("""COMPUTED_VALUE"""),"TAPAPECHO") -> TAPAPECHO | C72: 0 | D72: =IFERROR(__xludf.DUMMYFUNCTION("""COMPUTED_VALUE"""),7970) -> 7970 | E72: =IFERROR(__xludf.DUMMYFUNCTION("""COMPUTED_VALUE"""),"KG") -> KG | F72: =IFERROR(__xludf.DUMMYFUNCTION("""COMPUTED_VALUE"""),"Carnes y Aves") -> Carnes y Aves | G72: =(C72)*D72 -> 0 | H72: =G72*19% -> 0 | I72: =G72+H72 -> 0
A73: =IFERROR(__xludf.DUMMYFUNCTION("""COMPUTED_VALUE"""),"ti-ing-655db34a-bc6b-4602-ad22-18ea2ca5b14b") -> ti-ing-655db34a-bc6b-4602-ad22-18ea2ca5b14b | B73: =IFERROR(__xludf.DUMMYFUNCTION("""COMPUTED_VALUE"""),"Tocino kg") -> Tocino kg | C73: 0.577 | D73: =IFERROR(__xludf.DUMMYFUNCTION("""COMPUTED_VALUE"""),8366.177) -> 8366.177 | E73: =IFERROR(__xludf.DUMMYFUNCTION("""COMPUTED_VALUE"""),"KG") -> KG | F73: =IFERROR(__xludf.DUMMYFUNCTION("""COMPUTED_VALUE"""),"Carnes y Aves") -> Carnes y Aves | G73: =(C73)*D73 -> 4827.2841 | H73: =G73*19% -> 917.18398 | I73: =G73+H73 -> 5744.4681
A74: =IFERROR(__xludf.DUMMYFUNCTION("""COMPUTED_VALUE"""),"ti-ing-834ee9ca-3693-495d-80c7-1cfacd41d82f") -> ti-ing-834ee9ca-3693-495d-80c7-1cfacd41d82f | B74: =IFERROR(__xludf.DUMMYFUNCTION("""COMPUTED_VALUE"""),"Trutro pollo") -> Trutro pollo | C74: =15.228+2.986 -> 18.214 | D74: =IFERROR(__xludf.DUMMYFUNCTION("""COMPUTED_VALUE"""),1826.667) -> 1826.667 | E74: =IFERROR(__xludf.DUMMYFUNCTION("""COMPUTED_VALUE"""),"KG") -> KG | F74: =IFERROR(__xludf.DUMMYFUNCTION("""COMPUTED_VALUE"""),"Carnes y Aves") -> Carnes y Aves | G74: =(C74)*D74 -> 33270.913 | H74: =G74*19% -> 6321.4734 | I74: =G74+H74 -> 39592.386
A75: =IFERROR(__xludf.DUMMYFUNCTION("""COMPUTED_VALUE"""),"ti-ing-b9b61920-3597-4e41-bbb7-aad976c547a5") -> ti-ing-b9b61920-3597-4e41-bbb7-aad976c547a5 | B75: =IFERROR(__xludf.DUMMYFUNCTION("""COMPUTED_VALUE"""),"BOWL KRAFT 1300") -> BOWL KRAFT 1300 | C75: 65 | D75: =IFERROR(__xludf.DUMMYFUNCTION("""COMPUTED_VALUE"""),117.6467001) -> 117.6467 | E75: =IFERROR(__xludf.DUMMYFUNCTION("""COMPUTED_VALUE"""),"UN") -> UN | F75: =IFERROR(__xludf.DUMMYFUNCTION("""COMPUTED_VALUE"""),"Desechables") -> Desechables | G75: =(C75)*D75 -> 7647.0355 | H75: =G75*19% -> 1452.9367 | I75: =G75+H75 -> 9099.9723
A76: =IFERROR(__xludf.DUMMYFUNCTION("""COMPUTED_VALUE"""),"ti-ing-68e6ad9d-c495-4a8e-9a14-9e4341f7e996") -> ti-ing-68e6ad9d-c495-4a8e-9a14-9e4341f7e996 | B76: =IFERROR(__xludf.DUMMYFUNCTION("""COMPUTED_VALUE"""),"Contenedor de aluminio c-18") -> Contenedor de aluminio c-18 | C76: 87 | D76: =IFERROR(__xludf.DUMMYFUNCTION("""COMPUTED_VALUE"""),85.21855556) -> 85.218556 | E76: =IFERROR(__xludf.DUMMYFUNCTION("""COMPUTED_VALUE"""),"UN") -> UN | F76: =IFERROR(__xludf.DUMMYFUNCTION("""COMPUTED_VALUE"""),"Desechables") -> Desechables | G76: =(C76)*D76 -> 7414.0143 | H76: =G76*19% -> 1408.6627 | I76: =G76+H76 -> 8822.6771
B77: =IFERROR(__xludf.DUMMYFUNCTION("""COMPUTED_VALUE"""),"cubre barba") -> cubre barba | C77: 0 | D77: =IFERROR(__xludf.DUMMYFUNCTION("""COMPUTED_VALUE"""),46.5) -> 46.5 | E77: =IFERROR(__xludf.DUMMYFUNCTION("""COMPUTED_VALUE"""),"UN") -> UN | F77: =IFERROR(__xludf.DUMMYFUNCTION("""COMPUTED_VALUE"""),"Desechables") -> Desechables | G77: =(C77)*D77 -> 0 | H77: =G77*19% -> 0 | I77: =G77+H77 -> 0
A78: =IFERROR(__xludf.DUMMYFUNCTION("""COMPUTED_VALUE"""),"ti-ing-6de3399c-b35b-4eb5-ae73-cad819723851") -> ti-ing-6de3399c-b35b-4eb5-ae73-cad819723851 | B78: =IFERROR(__xludf.DUMMYFUNCTION("""COMPUTED_VALUE"""),"Cubre calzado (100un)") -> Cubre calzado (100un) | C78: 0 | D78: =IFERROR(__xludf.DUMMYFUNCTION("""COMPUTED_VALUE"""),2680) -> 2680 | E78: =IFERROR(__xludf.DUMMYFUNCTION("""COMPUTED_VALUE"""),"UN") -> UN | F78: =IFERROR(__xludf.DUMMYFUNCTION("""COMPUTED_VALUE"""),"Desechables") -> Desechables | G78: =(C78)*D78 -> 0 | H78: =G78*19% -> 0 | I78: =G78+H78 -> 0
A79: =IFERROR(__xludf.DUMMYFUNCTION("""COMPUTED_VALUE"""),"ti-ing-e90893a4-34b0-4961-9f16-e5dc5dc142a3") -> ti-ing-e90893a4-34b0-4961-9f16-e5dc5dc142a3 | B79: =IFERROR(__xludf.DUMMYFUNCTION("""COMPUTED_VALUE"""),"POCILLO ADEREZO CON TAPA") -> POCILLO ADEREZO CON TAPA | C79: 178 | D79: =IFERROR(__xludf.DUMMYFUNCTION("""COMPUTED_VALUE"""),9.7284) -> 9.7284 | E79: =IFERROR(__xludf.DUMMYFUNCTION("""COMPUTED_VALUE"""),"UN") -> UN | F79: =IFERROR(__xludf.DUMMYFUNCTION("""COMPUTED_VALUE"""),"Desechables") -> Desechables | G79: =(C79)*D79 -> 1731.6552 | H79: =G79*19% -> 329.01449 | I79: =G79+H79 -> 2060.6697
A80: =IFERROR(__xludf.DUMMYFUNCTION("""COMPUTED_VALUE"""),"ti-ing-37f85cc6-1f52-4599-9741-852d98246e09") -> ti-ing-37f85cc6-1f52-4599-9741-852d98246e09 | B80: =IFERROR(__xludf.DUMMYFUNCTION("""COMPUTED_VALUE"""),"Rollo etiquetas fechera") -> Rollo etiquetas fechera | C80: 1.5 | D80: =IFERROR(__xludf.DUMMYFUNCTION("""COMPUTED_VALUE"""),2800) -> 2800 | E80: =IFERROR(__xludf.DUMMYFUNCTION("""COMPUTED_VALUE"""),"UN") -> UN | F80: =IFERROR(__xludf.DUMMYFUNCTION("""COMPUTED_VALUE"""),"Desechables") -> Desechables | G80: =(C80)*D80 -> 4200 | H80: =G80*19% -> 798 | I80: =G80+H80 -> 4998
A81: =IFERROR(__xludf.DUMMYFUNCTION("""COMPUTED_VALUE"""),"ti-ing-a2ff1857-13be-46c5-8a38-b1004f73f14b") -> ti-ing-a2ff1857-13be-46c5-8a38-b1004f73f14b | B81: =IFERROR(__xludf.DUMMYFUNCTION("""COMPUTED_VALUE"""),"Rollo film pvc 45cm 1400m") -> Rollo film pvc 45cm 1400m | C81: 1 | D81: =IFERROR(__xludf.DUMMYFUNCTION("""COMPUTED_VALUE"""),26360) -> 26360 | E81: =IFERROR(__xludf.DUMMYFUNCTION("""COMPUTED_VALUE"""),"un") -> un | F81: =IFERROR(__xludf.DUMMYFUNCTION("""COMPUTED_VALUE"""),"Desechables") -> Desechables | G81: =(C81)*D81 -> 26360 | H81: =G81*19% -> 5008.4 | I81: =G81+H81 -> 31368.4
A82: =IFERROR(__xludf.DUMMYFUNCTION("""COMPUTED_VALUE"""),"ti-ing-eb406216-ee42-4fa1-82a6-91d3d62b5e79") -> ti-ing-eb406216-ee42-4fa1-82a6-91d3d62b5e79 | B82: =IFERROR(__xludf.DUMMYFUNCTION("""COMPUTED_VALUE"""),"TAPA BOWL 1300 (1X300)") -> TAPA BOWL 1300 (1X300) | C82: 40 | D82: =IFERROR(__xludf.DUMMYFUNCTION("""COMPUTED_VALUE"""),61.6667) -> 61.6667 | E82: =IFERROR(__xludf.DUMMYFUNCTION("""COMPUTED_VALUE"""),"UN") -> UN | F82: =IFERROR(__xludf.DUMMYFUNCTION("""COMPUTED_VALUE"""),"Desechables") -> Desechables | G82: =(C82)*D82 -> 2466.668 | H82: =G82*19% -> 468.66692 | I82: =G82+H82 -> 2935.3349
A83: =IFERROR(__xludf.DUMMYFUNCTION("""COMPUTED_VALUE"""),"ti-ing-5f615c7e-0ecf-4925-aeb1-a3e1d6b038f0") -> ti-ing-5f615c7e-0ecf-4925-aeb1-a3e1d6b038f0 | B83: =IFERROR(__xludf.DUMMYFUNCTION("""COMPUTED_VALUE"""),"Tapa C-18 Transparente") -> Tapa C-18 Transparente | C83: 74 | D83: =IFERROR(__xludf.DUMMYFUNCTION("""COMPUTED_VALUE"""),75.04157) -> 75.04157 | E83: =IFERROR(__xludf.DUMMYFUNCTION("""COMPUTED_VALUE"""),"UN") -> UN | F83: =IFERROR(__xludf.DUMMYFUNCTION("""COMPUTED_VALUE"""),"Desechables") -> Desechables | G83: =(C83)*D83 -> 5553.0762 | H83: =G83*19% -> 1055.0845 | I83: =G83+H83 -> 6608.1607
A84: =IFERROR(__xludf.DUMMYFUNCTION("""COMPUTED_VALUE"""),"ti-ing-233278b8-9ec1-48e3-8a3d-db6dba717065") -> ti-ing-233278b8-9ec1-48e3-8a3d-db6dba717065 | B84: =IFERROR(__xludf.DUMMYFUNCTION("""COMPUTED_VALUE"""),"AJI AMARILLO") -> AJI AMARILLO | C84: 0 | D84: =IFERROR(__xludf.DUMMYFUNCTION("""COMPUTED_VALUE"""),2950) -> 2950 | E84: =IFERROR(__xludf.DUMMYFUNCTION("""COMPUTED_VALUE"""),"KG") -> KG | F84: =IFERROR(__xludf.DUMMYFUNCTION("""COMPUTED_VALUE"""),"Frutas y Verduras") -> Frutas y Verduras | G84: =(C84)*D84 -> 0 | H84: =G84*19% -> 0 | I84: =G84+H84 -> 0
A85: =IFERROR(__xludf.DUMMYFUNCTION("""COMPUTED_VALUE"""),"ti-ing-1d7a4c6f-2a94-4486-83b4-9301b1485aef") -> ti-ing-1d7a4c6f-2a94-4486-83b4-9301b1485aef | B85: =IFERROR(__xludf.DUMMYFUNCTION("""COMPUTED_VALUE"""),"Ajo kg") -> Ajo kg | C85: 0.534 | D85: =IFERROR(__xludf.DUMMYFUNCTION("""COMPUTED_VALUE"""),3479) -> 3479 | E85: =IFERROR(__xludf.DUMMYFUNCTION("""COMPUTED_VALUE"""),"KG") -> KG | F85: =IFERROR(__xludf.DUMMYFUNCTION("""COMPUTED_VALUE"""),"Frutas y Verduras") -> Frutas y Verduras | G85: =(C85)*D85 -> 1857.786 | H85: =G85*19% -> 352.97934 | I85: =G85+H85 -> 2210.7653
A86: =IFERROR(__xludf.DUMMYFUNCTION("""COMPUTED_VALUE"""),"ti-ing-75919a0c-e656-46fd-8004-3b3ce3e6a162") -> ti-ing-75919a0c-e656-46fd-8004-3b3ce3e6a162 | B86: =IFERROR(__xludf.DUMMYFUNCTION("""COMPUTED_VALUE"""),"Albahaca unidad") -> Albahaca unidad | C86: 11 | D86: =IFERROR(__xludf.DUMMYFUNCTION("""COMPUTED_VALUE"""),600) -> 600 | E86: =IFERROR(__xludf.DUMMYFUNCTION("""COMPUTED_VALUE"""),"KG") -> KG | F86: =IFERROR(__xludf.DUMMYFUNCTION("""COMPUTED_VALUE"""),"Frutas y Verduras") -> Frutas y Verduras | G86: =(C86)*D86 -> 6600 | H86: =G86*19% -> 1254 | I86: =G86+H86 -> 7854
A87: =IFERROR(__xludf.DUMMYFUNCTION("""COMPUTED_VALUE"""),"ti-ing-99fb5592-f8d7-417f-8119-da2a8d2ceb5e") -> ti-ing-99fb5592-f8d7-417f-8119-da2a8d2ceb5e | B87: =IFERROR(__xludf.DUMMYFUNCTION("""COMPUTED_VALUE"""),"Apio (Unidad)") -> Apio (Unidad) | C87: 0.5 | D87: =IFERROR(__xludf.DUMMYFUNCTION("""COMPUTED_VALUE"""),1900) -> 1900 | E87: =IFERROR(__xludf.DUMMYFUNCTION("""COMPUTED_VALUE"""),"UN") -> UN | F87: =IFERROR(__xludf.DUMMYFUNCTION("""COMPUTED_VALUE"""),"Frutas y Verduras") -> Frutas y Verduras | G87: =(C87)*D87 -> 950 | H87: =G87*19% -> 180.5 | I87: =G87+H87 -> 1130.5
A88: =IFERROR(__xludf.DUMMYFUNCTION("""COMPUTED_VALUE"""),"ti-ing-af032640-2aa9-4ce8-b812-3a7a785ecda4") -> ti-ing-af032640-2aa9-4ce8-b812-3a7a785ecda4 | B88: =IFERROR(__xludf.DUMMYFUNCTION("""COMPUTED_VALUE"""),"Arverja") -> Arverja | C88: 1 | D88: =IFERROR(__xludf.DUMMYFUNCTION("""COMPUTED_VALUE"""),1529) -> 1529 | E88: =IFERROR(__xludf.DUMMYFUNCTION("""COMPUTED_VALUE"""),"KG") -> KG | F88: =IFERROR(__xludf.DUMMYFUNCTION("""COMPUTED_VALUE"""),"Frutas y Verduras") -> Frutas y Verduras | G88: =(C88)*D88 -> 1529 | H88: =G88*19% -> 290.51 | I88: =G88+H88 -> 1819.51
A89: =IFERROR(__xludf.DUMMYFUNCTION("""COMPUTED_VALUE"""),"ti-ing-ac84c264-48fe-4167-8c4d-d08a41b6535c") -> ti-ing-ac84c264-48fe-4167-8c4d-d08a41b6535c | B89: =IFERROR(__xludf.DUMMYFUNCTION("""COMPUTED_VALUE"""),"BETERRAGA") -> BETERRAGA | C89: 0 | D89: =IFERROR(__xludf.DUMMYFUNCTION("""COMPUTED_VALUE"""),1400) -> 1400 | E89: =IFERROR(__xludf.DUMMYFUNCTION("""COMPUTED_VALUE"""),"KG") -> KG | F89: =IFERROR(__xludf.DUMMYFUNCTION("""COMPUTED_VALUE"""),"Frutas y Verduras") -> Frutas y Verduras | G89: =(C89)*D89 -> 0 | H89: =G89*19% -> 0 | I89: =G89+H89 -> 0
A90: =IFERROR(__xludf.DUMMYFUNCTION("""COMPUTED_VALUE"""),"ti-ing-ad6024d2-c043-487e-b6e3-9c6cd30c1357") -> ti-ing-ad6024d2-c043-487e-b6e3-9c6cd30c1357 | B90: =IFERROR(__xludf.DUMMYFUNCTION("""COMPUTED_VALUE"""),"Brocoli kg") -> Brocoli kg | C90: 2 | D90: =IFERROR(__xludf.DUMMYFUNCTION("""COMPUTED_VALUE"""),1400) -> 1400 | E90: =IFERROR(__xludf.DUMMYFUNCTION("""COMPUTED_VALUE"""),"UN") -> UN | F90: =IFERROR(__xludf.DUMMYFUNCTION("""COMPUTED_VALUE"""),"Frutas y Verduras") -> Frutas y Verduras | G90: =(C90)*D90 -> 2800 | H90: =G90*19% -> 532 | I90: =G90+H90 -> 3332
A91: =IFERROR(__xludf.DUMMYFUNCTION("""COMPUTED_VALUE"""),"ti-ing-71dbf12a-c470-4029-b17a-b98f5f165e0c") -> ti-ing-71dbf12a-c470-4029-b17a-b98f5f165e0c | B91: =IFERROR(__xludf.DUMMYFUNCTION("""COMPUTED_VALUE"""),"Cebolla blanca (malla)20K") -> Cebolla blanca (malla)20K | C91: 6.874 | D91: =IFERROR(__xludf.DUMMYFUNCTION("""COMPUTED_VALUE"""),1000) -> 1000 | E91: =IFERROR(__xludf.DUMMYFUNCTION("""COMPUTED_VALUE"""),"kg") -> kg | F91: =IFERROR(__xludf.DUMMYFUNCTION("""COMPUTED_VALUE"""),"Frutas y Verduras") -> Frutas y Verduras | G91: =(C91)*D91 -> 6874 | H91: =G91*19% -> 1306.06 | I91: =G91+H91 -> 8180.06
A92: =IFERROR(__xludf.DUMMYFUNCTION("""COMPUTED_VALUE"""),"ti-ing-b5b09e3f-e0c7-4af4-a2ce-a8d91e01cee7") -> ti-ing-b5b09e3f-e0c7-4af4-a2ce-a8d91e01cee7 | B92: =IFERROR(__xludf.DUMMYFUNCTION("""COMPUTED_VALUE"""),"Cebolla morada kg") -> Cebolla morada kg | C92: 0 | D92: =IFERROR(__xludf.DUMMYFUNCTION("""COMPUTED_VALUE"""),1000) -> 1000 | E92: =IFERROR(__xludf.DUMMYFUNCTION("""COMPUTED_VALUE"""),"KG") -> KG | F92: =IFERROR(__xludf.DUMMYFUNCTION("""COMPUTED_VALUE"""),"Frutas y Verduras") -> Frutas y Verduras | G92: =(C92)*D92 -> 0 | H92: =G92*19% -> 0 | I92: =G92+H92 -> 0
A93: =IFERROR(__xludf.DUMMYFUNCTION("""COMPUTED_VALUE"""),"ti-ing-017224a3-3b18-44f7-ae5d-3a1b32df6352") -> ti-ing-017224a3-3b18-44f7-ae5d-3a1b32df6352 | B93: =IFERROR(__xludf.DUMMYFUNCTION("""COMPUTED_VALUE"""),"CEBOLLIN") -> CEBOLLIN | C93: 1.5 | D93: =IFERROR(__xludf.DUMMYFUNCTION("""COMPUTED_VALUE"""),650) -> 650 | E93: =IFERROR(__xludf.DUMMYFUNCTION("""COMPUTED_VALUE"""),"kg") -> kg | F93: =IFERROR(__xludf.DUMMYFUNCTION("""COMPUTED_VALUE"""),"Frutas y Verduras") -> Frutas y Verduras | G93: =(C93)*D93 -> 975 | H93: =G93*19% -> 185.25 | I93: =G93+H93 -> 1160.25
A94: =IFERROR(__xludf.DUMMYFUNCTION("""COMPUTED_VALUE"""),"ti-ing-1ecc2f42-d216-410a-a377-c5d2582697ee") -> ti-ing-1ecc2f42-d216-410a-a377-c5d2582697ee | B94: =IFERROR(__xludf.DUMMYFUNCTION("""COMPUTED_VALUE"""),"Champiñones kg") -> Champiñones kg | C94: 3.712 | D94: =IFERROR(__xludf.DUMMYFUNCTION("""COMPUTED_VALUE"""),6470) -> 6470 | E94: =IFERROR(__xludf.DUMMYFUNCTION("""COMPUTED_VALUE"""),"KG") -> KG | F94: =IFERROR(__xludf.DUMMYFUNCTION("""COMPUTED_VALUE"""),"Frutas y Verduras") -> Frutas y Verduras | G94: =(C94)*D94 -> 24016.64 | H94: =G94*19% -> 4563.1616 | I94: =G94+H94 -> 28579.802
A95: =IFERROR(__xludf.DUMMYFUNCTION("""COMPUTED_VALUE"""),"ti-ing-bed7973b-9532-4b5a-a24b-c76cd3ec36aa") -> ti-ing-bed7973b-9532-4b5a-a24b-c76cd3ec36aa | B95: =IFERROR(__xludf.DUMMYFUNCTION("""COMPUTED_VALUE"""),"Choclo pasta ") -> Choclo pasta | C95: 0 | D95: =IFERROR(__xludf.DUMMYFUNCTION("""COMPUTED_VALUE"""),2424) -> 2424 | E95: =IFERROR(__xludf.DUMMYFUNCTION("""COMPUTED_VALUE"""),"KG") -> KG | F95: =IFERROR(__xludf.DUMMYFUNCTION("""COMPUTED_VALUE"""),"Frutas y Verduras") -> Frutas y Verduras | G95: =(C95)*D95 -> 0 | H95: =G95*19% -> 0 | I95: =G95+H95 -> 0
A96: =IFERROR(__xludf.DUMMYFUNCTION("""COMPUTED_VALUE"""),"ti-ing-a021b4e5-e9a7-453b-a0de-e4adc29277b0") -> ti-ing-a021b4e5-e9a7-453b-a0de-e4adc29277b0 | B96: =IFERROR(__xludf.DUMMYFUNCTION("""COMPUTED_VALUE"""),"Choclo Picado ") -> Choclo Picado | C96: 1 | D96: =IFERROR(__xludf.DUMMYFUNCTION("""COMPUTED_VALUE"""),1541) -> 1541 | E96: =IFERROR(__xludf.DUMMYFUNCTION("""COMPUTED_VALUE"""),"KG") -> KG | F96: =IFERROR(__xludf.DUMMYFUNCTION("""COMPUTED_VALUE"""),"Frutas y Verduras") -> Frutas y Verduras | G96: =(C96)*D96 -> 1541 | H96: =G96*19% -> 292.79 | I96: =G96+H96 -> 1833.79
A97: =IFERROR(__xludf.DUMMYFUNCTION("""COMPUTED_VALUE"""),"ti-ing-8c29d18e-9e5c-4200-a46a-8c0a739ac694") -> ti-ing-8c29d18e-9e5c-4200-a46a-8c0a739ac694 | B97: =IFERROR(__xludf.DUMMYFUNCTION("""COMPUTED_VALUE"""),"Choclo un") -> Choclo un | C97: 0 | D97: =IFERROR(__xludf.DUMMYFUNCTION("""COMPUTED_VALUE"""),500) -> 500 | E97: =IFERROR(__xludf.DUMMYFUNCTION("""COMPUTED_VALUE"""),"UN") -> UN | F97: =IFERROR(__xludf.DUMMYFUNCTION("""COMPUTED_VALUE"""),"Frutas y Verduras") -> Frutas y Verduras | G97: =(C97)*D97 -> 0 | H97: =G97*19% -> 0 | I97: =G97+H97 -> 0
A98: =IFERROR(__xludf.DUMMYFUNCTION("""COMPUTED_VALUE"""),"ti-ing-1c153d40-1847-4176-98eb-158c12c1b4ce") -> ti-ing-1c153d40-1847-4176-98eb-158c12c1b4ce | B98: =IFERROR(__xludf.DUMMYFUNCTION("""COMPUTED_VALUE"""),"Cilantro") -> Cilantro | C98: 1 | D98: =IFERROR(__xludf.DUMMYFUNCTION("""COMPUTED_VALUE"""),900) -> 900 | E98: =IFERROR(__xludf.DUMMYFUNCTION("""COMPUTED_VALUE"""),"UN") -> UN | F98: =IFERROR(__xludf.DUMMYFUNCTION("""COMPUTED_VALUE"""),"Frutas y Verduras") -> Frutas y Verduras | G98: =(C98)*D98 -> 900 | H98: =G98*19% -> 171 | I98: =G98+H98 -> 1071
A99: =IFERROR(__xludf.DUMMYFUNCTION("""COMPUTED_VALUE"""),"ti-ing-223edded-4746-4eeb-adba-6396efcf98a1") -> ti-ing-223edded-4746-4eeb-adba-6396efcf98a1 | B99: =IFERROR(__xludf.DUMMYFUNCTION("""COMPUTED_VALUE"""),"Espinaca") -> Espinaca | C99: 0 | D99: =IFERROR(__xludf.DUMMYFUNCTION("""COMPUTED_VALUE"""),800) -> 800 | E99: =IFERROR(__xludf.DUMMYFUNCTION("""COMPUTED_VALUE"""),"UN") -> UN | F99: =IFERROR(__xludf.DUMMYFUNCTION("""COMPUTED_VALUE"""),"Frutas y Verduras") -> Frutas y Verduras | G99: =(C99)*D99 -> 0 | H99: =G99*19% -> 0 | I99: =G99+H99 -> 0
A100: =IFERROR(__xludf.DUMMYFUNCTION("""COMPUTED_VALUE"""),"ti-ing-95855f99-76a5-4b8f-9010-41fdb238c9f0") -> ti-ing-95855f99-76a5-4b8f-9010-41fdb238c9f0 | B100: =IFERROR(__xludf.DUMMYFUNCTION("""COMPUTED_VALUE"""),"jengibre") -> jengibre | C100: 0 | D100: =IFERROR(__xludf.DUMMYFUNCTION("""COMPUTED_VALUE"""),3900) -> 3900 | E100: =IFERROR(__xludf.DUMMYFUNCTION("""COMPUTED_VALUE"""),"KG") -> KG | F100: =IFERROR(__xludf.DUMMYFUNCTION("""COMPUTED_VALUE"""),"Frutas y Verduras") -> Frutas y Verduras | G100: =(C100)*D100 -> 0 | H100: =G100*19% -> 0 | I100: =G100+H100 -> 0
...

Sheet servicio
A1: Stock Servicio | B1: Stock Servicio
A2: ID PRODUCTO | B2: PRODUCTO | C2: STOCK | D2: PEDIDO | E2: UN MEDIDA | F2: CATEGORIA | G2: Valorizado Neto | H2: IVA (19%) | I2: Total Bruto | J2: PEDIDO
A3: =IFERROR(__xludf.DUMMYFUNCTION("FILTER('UNIVERSO PRODUCTOS'!A1:B958, ISNUMBER(SEARCH(A1, 'UNIVERSO PRODUCTOS'!K1:K958))) "),"ti-ing-531d1d9b-814d-49bc-9bbf-06be4ae2e6d5") -> ti-ing-531d1d9b-814d-49bc-9bbf-06be4ae2e6d5 | B3: =IFERROR(__xludf.DUMMYFUNCTION("""COMPUTED_VALUE"""),"Azucar blanca") -> Azucar blanca | C3: 1.3 | D3: =IFERROR(__xludf.DUMMYFUNCTION("FILTER('UNIVERSO PRODUCTOS'!C1:C961, ISNUMBER(SEARCH(A1, 'UNIVERSO PRODUCTOS'!K1:K961))) "),939.9985) -> 939.9985 | E3: =IFERROR(__xludf.DUMMYFUNCTION("FILTER('UNIVERSO PRODUCTOS'!D1:D958, ISNUMBER(SEARCH(A1, 'UNIVERSO PRODUCTOS'!K1:K958))) "),"KG") -> KG | F3: =IFERROR(__xludf.DUMMYFUNCTION("FILTER('UNIVERSO PRODUCTOS'!H1:H958, ISNUMBER(SEARCH(A1, 'UNIVERSO PRODUCTOS'!K1:K958))) "),"Abarrotes") -> Abarrotes | G3: =(C3)*D3 -> 1221.9981 | H3: =G3*19% -> 232.17963 | I3: =G3+H3 -> 1454.1777
A4: =IFERROR(__xludf.DUMMYFUNCTION("""COMPUTED_VALUE"""),"ti-ing-c4486ce7-85c4-49c5-ac82-4d98b0798d01") -> ti-ing-c4486ce7-85c4-49c5-ac82-4d98b0798d01 | B4: =IFERROR(__xludf.DUMMYFUNCTION("""COMPUTED_VALUE"""),"Azucar rubia") -> Azucar rubia | C4: 0 | D4: =IFERROR(__xludf.DUMMYFUNCTION("""COMPUTED_VALUE"""),1047) -> 1047 | E4: =IFERROR(__xludf.DUMMYFUNCTION("""COMPUTED_VALUE"""),"KG") -> KG | F4: =IFERROR(__xludf.DUMMYFUNCTION("""COMPUTED_VALUE"""),"Abarrotes") -> Abarrotes | G4: =(C4)*D4 -> 0 | H4: =G4*19% -> 0 | I4: =G4+H4 -> 0 | L4: Abarrotes | M4: Aseo | N4: Bebestibles | O4: Cafetería | P4: Carnes y Aves | Q4: Desechables | R4: Frutas y Verduras | S4: Harinas | T4: Ovolacteos | U4: Pastelería | V4: Pescados y Mariscos | W4: P.Terminados | X4: Té | Y4: Valor Neto
A5: =IFERROR(__xludf.DUMMYFUNCTION("""COMPUTED_VALUE"""),"ti-ing-63a7f9f9-77ff-45f4-9e3f-3feff0b73432") -> ti-ing-63a7f9f9-77ff-45f4-9e3f-3feff0b73432 | B5: =IFERROR(__xludf.DUMMYFUNCTION("""COMPUTED_VALUE"""),"Café tarro grande (desayuno)") -> Café tarro grande (desayuno) | C5: 1 | D5: =IFERROR(__xludf.DUMMYFUNCTION("""COMPUTED_VALUE"""),12032) -> 12032 | E5: =IFERROR(__xludf.DUMMYFUNCTION("""COMPUTED_VALUE"""),"UN") -> UN | F5: =IFERROR(__xludf.DUMMYFUNCTION("""COMPUTED_VALUE"""),"Abarrotes") -> Abarrotes | G5: =(C5)*D5 -> 12032 | H5: =G5*19% -> 2286.08 | I5: =G5+H5 -> 14318.08
A6: =IFERROR(__xludf.DUMMYFUNCTION("""COMPUTED_VALUE"""),"ti-ing-af062f27-295c-456a-9ce5-77fbb725f339") -> ti-ing-af062f27-295c-456a-9ce5-77fbb725f339 | B6: =IFERROR(__xludf.DUMMYFUNCTION("""COMPUTED_VALUE"""),"Helado Chocolate") -> Helado Chocolate | C6: 12 | D6: =IFERROR(__xludf.DUMMYFUNCTION("""COMPUTED_VALUE"""),2360.6) -> 2360.6 | E6: =IFERROR(__xludf.DUMMYFUNCTION("""COMPUTED_VALUE"""),"LT") -> LT | F6: =IFERROR(__xludf.DUMMYFUNCTION("""COMPUTED_VALUE"""),"Abarrotes") -> Abarrotes | G6: =(C6)*D6 -> 28327.2 | H6: =G6*19% -> 5382.168 | I6: =G6+H6 -> 33709.368 | L6: =SUM(G3:G11) -> 59470.198 | M6: =SUM(G12:G44) -> 90482.2 | N6: =SUM(G45:G72) -> 522238.6 | O6: =SUM(G73:G88) -> 281460.28 | Q6: =SUM(G89:G136) -> 242346.49 | R6: =SUM(G137:G144) -> 117956.22 | T6: =SUM(G145:G152) -> 51778.63 | U6: =SUM(G155:G162) -> 0 | W6: =SUM(G153:G286) -> 64539 | X6: =SUM(G287:G297) -> 91240.474 | Y6: =SUM(L6:X6) -> 1521512.1
B7: =IFERROR(__xludf.DUMMYFUNCTION("""COMPUTED_VALUE"""),"Helado frutilla") -> Helado frutilla | C7: 4.5 | D7: =IFERROR(__xludf.DUMMYFUNCTION("""COMPUTED_VALUE"""),3469) -> 3469 | E7: =IFERROR(__xludf.DUMMYFUNCTION("""COMPUTED_VALUE"""),"LT") -> LT | F7: =IFERROR(__xludf.DUMMYFUNCTION("""COMPUTED_VALUE"""),"Abarrotes") -> Abarrotes | G7: =(C7)*D7 -> 15610.5 | H7: =G7*19% -> 2965.995 | I7: =G7+H7 -> 18576.495
A8: =IFERROR(__xludf.DUMMYFUNCTION("""COMPUTED_VALUE"""),"ti-ing-12dbd538-5012-4d25-8c02-7d0b4f3fdf45") -> ti-ing-12dbd538-5012-4d25-8c02-7d0b4f3fdf45 | B8: =IFERROR(__xludf.DUMMYFUNCTION("""COMPUTED_VALUE"""),"Helado Vainilla") -> Helado Vainilla | C8: 0 | D8: =IFERROR(__xludf.DUMMYFUNCTION("""COMPUTED_VALUE"""),2979) -> 2979 | E8: =IFERROR(__xludf.DUMMYFUNCTION("""COMPUTED_VALUE"""),"LT") -> LT | F8: =IFERROR(__xludf.DUMMYFUNCTION("""COMPUTED_VALUE"""),"Abarrotes") -> Abarrotes | G8: =(C8)*D8 -> 0 | H8: =G8*19% -> 0 | I8: =G8+H8 -> 0 | L8: Abarrotes | M8: Aseo | N8: Bebestibles | O8: Cafetería | P8: Carnes y Aves | Q8: Desechables | R8: Frutas y Verduras | S8: Harinas | T8: Ovolacteos | U8: Pastelería | V8: Pescados y Mariscos | W8: P.Terminados | X8: Té | Y8: Valor Bruto
A9: =IFERROR(__xludf.DUMMYFUNCTION("""COMPUTED_VALUE"""),"ti-ing-2758a41a-4b82-4e9c-b888-e1e3498bbd24") -> ti-ing-2758a41a-4b82-4e9c-b888-e1e3498bbd24 | B9: =IFERROR(__xludf.DUMMYFUNCTION("""COMPUTED_VALUE"""),"Miel") -> Miel | C9: 0 | D9: =IFERROR(__xludf.DUMMYFUNCTION("""COMPUTED_VALUE"""),4117) -> 4117 | E9: =IFERROR(__xludf.DUMMYFUNCTION("""COMPUTED_VALUE"""),"UN") -> UN | F9: =IFERROR(__xludf.DUMMYFUNCTION("""COMPUTED_VALUE"""),"Abarrotes") -> Abarrotes | G9: =(C9)*D9 -> 0 | H9: =G9*19% -> 0 | I9: =G9+H9 -> 0
A10: =IFERROR(__xludf.DUMMYFUNCTION("""COMPUTED_VALUE"""),"ti-ing-c5dc548f-f0a9-4499-a4b3-23a34458dbfa") -> ti-ing-c5dc548f-f0a9-4499-a4b3-23a34458dbfa | B10: =IFERROR(__xludf.DUMMYFUNCTION("""COMPUTED_VALUE"""),"Te en Bolsa Caja") -> Te en Bolsa Caja | C10: 49 | D10: =IFERROR(__xludf.DUMMYFUNCTION("""COMPUTED_VALUE"""),46.5) -> 46.5 | E10: =IFERROR(__xludf.DUMMYFUNCTION("""COMPUTED_VALUE"""),"UN") -> UN | F10: =IFERROR(__xludf.DUMMYFUNCTION("""COMPUTED_VALUE"""),"Abarrotes") -> Abarrotes | G10: =(C10)*D10 -> 2278.5 | H10: =G10*19% -> 432.915 | I10: =G10+H10 -> 2711.415 | L10: =SUM(I3:I11) -> 70769.536 | M10: =SUM(I12:I44) -> 107673.82 | N10: =SUM(I45:I72) -> 621463.94 | O10: =SUM(I73:I88) -> 334937.74 | Q10: =SUM(I89:I136) -> 288392.33 | R10: =SUM(I137:I144) -> 140367.91 | T10: =SUM(I145:I152) -> 61616.57 | U10: =SUM(I155:I162) -> 0 | W10: =SUM(I153:I286) -> 76801.41 | X10: =SUM(I287:I297) -> 108576.16 | Y10: =SUM(L10:X10) -> 1810599.4
A11: =IFERROR(__xludf.DUMMYFUNCTION("""COMPUTED_VALUE"""),"ti-ing-b38390e4-8c11-4339-8209-7a310643c3be") -> ti-ing-b38390e4-8c11-4339-8209-7a310643c3be | B11: =IFERROR(__xludf.DUMMYFUNCTION("""COMPUTED_VALUE"""),"Vinagre") -> Vinagre | C11: 0 | D11: =IFERROR(__xludf.DUMMYFUNCTION("""COMPUTED_VALUE"""),593) -> 593 | E11: =IFERROR(__xludf.DUMMYFUNCTION("""COMPUTED_VALUE"""),"UN") -> UN | F11: =IFERROR(__xludf.DUMMYFUNCTION("""COMPUTED_VALUE"""),"Abarrotes") -> Abarrotes | G11: =(C11)*D11 -> 0 | H11: =G11*19% -> 0 | I11: =G11+H11 -> 0
A12: =IFERROR(__xludf.DUMMYFUNCTION("""COMPUTED_VALUE"""),"ti-ing-f8ffedeb-44d6-400b-bef8-0b9c51a508a0") -> ti-ing-f8ffedeb-44d6-400b-bef8-0b9c51a508a0 | B12: =IFERROR(__xludf.DUMMYFUNCTION("""COMPUTED_VALUE"""),"ALCOHOL") -> ALCOHOL | C12: 0 | D12: =IFERROR(__xludf.DUMMYFUNCTION("""COMPUTED_VALUE"""),2348.2) -> 2348.2 | E12: =IFERROR(__xludf.DUMMYFUNCTION("""COMPUTED_VALUE"""),"UN") -> UN | F12: =IFERROR(__xludf.DUMMYFUNCTION("""COMPUTED_VALUE"""),"Aseo") -> Aseo | G12: =(C12)*D12 -> 0 | H12: =G12*19% -> 0 | I12: =G12+H12 -> 0
A13: =IFERROR(__xludf.DUMMYFUNCTION("""COMPUTED_VALUE"""),"ti-ing-7607ac26-0154-48c7-a176-272daa456f7a") -> ti-ing-7607ac26-0154-48c7-a176-272daa456f7a | B13: =IFERROR(__xludf.DUMMYFUNCTION("""COMPUTED_VALUE"""),"BOLSA BASURA CHICA (un)") -> BOLSA BASURA CHICA (un) | C13: 19 | D13: =IFERROR(__xludf.DUMMYFUNCTION("""COMPUTED_VALUE"""),39) -> 39 | E13: =IFERROR(__xludf.DUMMYFUNCTION("""COMPUTED_VALUE"""),"UN") -> UN | F13: =IFERROR(__xludf.DUMMYFUNCTION("""COMPUTED_VALUE"""),"Aseo") -> Aseo | G13: =(C13)*D13 -> 741 | H13: =G13*19% -> 140.79 | I13: =G13+H13 -> 881.79
A14: =IFERROR(__xludf.DUMMYFUNCTION("""COMPUTED_VALUE"""),"ti-ing-32a0a1de-7d7a-48fa-8701-58015f10f3d8") -> ti-ing-32a0a1de-7d7a-48fa-8701-58015f10f3d8 | B14: =IFERROR(__xludf.DUMMYFUNCTION("""COMPUTED_VALUE"""),"BOLSA BASURA GRANDE (un)") -> BOLSA BASURA GRANDE (un) | C14: 22 | D14: =IFERROR(__xludf.DUMMYFUNCTION("""COMPUTED_VALUE"""),391.1) -> 391.1 | E14: =IFERROR(__xludf.DUMMYFUNCTION("""COMPUTED_VALUE"""),"UN") -> UN | F14: =IFERROR(__xludf.DUMMYFUNCTION("""COMPUTED_VALUE"""),"Aseo") -> Aseo | G14: =(C14)*D14 -> 8604.2 | H14: =G14*19% -> 1634.798 | I14: =G14+H14 -> 10238.998
A15: =IFERROR(__xludf.DUMMYFUNCTION("""COMPUTED_VALUE"""),"ti-ing-b56c8191-87a4-414c-8649-692ed6f88304") -> ti-ing-b56c8191-87a4-414c-8649-692ed6f88304 | B15: =IFERROR(__xludf.DUMMYFUNCTION("""COMPUTED_VALUE"""),"BOLSA BASURA MEDIANA (un)") -> BOLSA BASURA MEDIANA (un) | C15: 20 | D15: =IFERROR(__xludf.DUMMYFUNCTION("""COMPUTED_VALUE"""),74.8) -> 74.8 | E15: =IFERROR(__xludf.DUMMYFUNCTION("""COMPUTED_VALUE"""),"UN") -> UN | F15: =IFERROR(__xludf.DUMMYFUNCTION("""COMPUTED_VALUE"""),"Aseo") -> Aseo | G15: =(C15)*D15 -> 1496 | H15: =G15*19% -> 284.24 | I15: =G15+H15 -> 1780.24
A16: =IFERROR(__xludf.DUMMYFUNCTION("""COMPUTED_VALUE"""),"ti-ing-dbb6ae46-9301-4b24-b966-4b4c02ecbb20") -> ti-ing-dbb6ae46-9301-4b24-b966-4b4c02ecbb20 | B16: =IFERROR(__xludf.DUMMYFUNCTION("""COMPUTED_VALUE"""),"Cafiza2") -> Cafiza2 | C16: 0.09 | D16: =IFERROR(__xludf.DUMMYFUNCTION("""COMPUTED_VALUE"""),19328) -> 19328 | E16: =IFERROR(__xludf.DUMMYFUNCTION("""COMPUTED_VALUE"""),"KG") -> KG | F16: =IFERROR(__xludf.DUMMYFUNCTION("""COMPUTED_VALUE"""),"Aseo") -> Aseo | G16: =(C16)*D16 -> 1739.52 | H16: =G16*19% -> 330.5088 | I16: =G16+H16 -> 2070.0288
A17: =IFERROR(__xludf.DUMMYFUNCTION("""COMPUTED_VALUE"""),"ti-ing-addf5a00-64be-48da-80f1-f963e13357c9") -> ti-ing-addf5a00-64be-48da-80f1-f963e13357c9 | B17: =IFERROR(__xludf.DUMMYFUNCTION("""COMPUTED_VALUE"""),"CLORO 5 LTS") -> CLORO 5 LTS | C17: 12 | D17: =IFERROR(__xludf.DUMMYFUNCTION("""COMPUTED_VALUE"""),247) -> 247 | E17: =IFERROR(__xludf.DUMMYFUNCTION("""COMPUTED_VALUE"""),"LT") -> LT | F17: =IFERROR(__xludf.DUMMYFUNCTION("""COMPUTED_VALUE"""),"Aseo") -> Aseo | G17: =(C17)*D17 -> 2964 | H17: =G17*19% -> 563.16 | I17: =G17+H17 -> 3527.16
A18: =IFERROR(__xludf.DUMMYFUNCTION("""COMPUTED_VALUE"""),"ti-ing-04d39eaa-25ae-4aa0-b31a-7ca9c1ec8bc0") -> ti-ing-04d39eaa-25ae-4aa0-b31a-7ca9c1ec8bc0 | B18: =IFERROR(__xludf.DUMMYFUNCTION("""COMPUTED_VALUE"""),"CLORO GEL") -> CLORO GEL | C18: 0 | D18: =IFERROR(__xludf.DUMMYFUNCTION("""COMPUTED_VALUE"""),1250) -> 1250 | E18: =IFERROR(__xludf.DUMMYFUNCTION("""COMPUTED_VALUE"""),"LT") -> LT | F18: =IFERROR(__xludf.DUMMYFUNCTION("""COMPUTED_VALUE"""),"Aseo") -> Aseo | G18: =(C18)*D18 -> 0 | H18: =G18*19% -> 0 | I18: =G18+H18 -> 0
A19: =IFERROR(__xludf.DUMMYFUNCTION("""COMPUTED_VALUE"""),"ti-ing-2a9f7a04-ff9b-4634-9f27-edac618856d6") -> ti-ing-2a9f7a04-ff9b-4634-9f27-edac618856d6 | B19: =IFERROR(__xludf.DUMMYFUNCTION("""COMPUTED_VALUE"""),"DESENGRASANTE 5 lt") -> DESENGRASANTE 5 lt | C19: 1 | D19: =IFERROR(__xludf.DUMMYFUNCTION("""COMPUTED_VALUE"""),658.8) -> 658.8 | E19: =IFERROR(__xludf.DUMMYFUNCTION("""COMPUTED_VALUE"""),"LT") -> LT | F19: =IFERROR(__xludf.DUMMYFUNCTION("""COMPUTED_VALUE"""),"Aseo") -> Aseo | G19: =(C19)*D19 -> 658.8 | H19: =G19*19% -> 125.172 | I19: =G19+H19 -> 783.972
A20: =IFERROR(__xludf.DUMMYFUNCTION("""COMPUTED_VALUE"""),"ti-ing-e0ae8367-512a-46da-9188-edb6aed9ccac") -> ti-ing-e0ae8367-512a-46da-9188-edb6aed9ccac | B20: =IFERROR(__xludf.DUMMYFUNCTION("""COMPUTED_VALUE"""),"ESCOBA") -> ESCOBA | C20: 7 | D20: =IFERROR(__xludf.DUMMYFUNCTION("""COMPUTED_VALUE"""),1250) -> 1250 | E20: =IFERROR(__xludf.DUMMYFUNCTION("""COMPUTED_VALUE"""),"UN") -> UN | F20: =IFERROR(__xludf.DUMMYFUNCTION("""COMPUTED_VALUE"""),"Aseo") -> Aseo | G20: =(C20)*D20 -> 8750 | H20: =G20*19% -> 1662.5 | I20: =G20+H20 -> 10412.5
A21: =IFERROR(__xludf.DUMMYFUNCTION("""COMPUTED_VALUE"""),"ti-ing-102eb718-4b52-41a7-9529-6a535c4ceb37") -> ti-ing-102eb718-4b52-41a7-9529-6a535c4ceb37 | B21: =IFERROR(__xludf.DUMMYFUNCTION("""COMPUTED_VALUE"""),"ESPONJAS AMARILLAS") -> ESPONJAS AMARILLAS | C21: 4 | D21: =IFERROR(__xludf.DUMMYFUNCTION("""COMPUTED_VALUE"""),149) -> 149 | E21: =IFERROR(__xludf.DUMMYFUNCTION("""COMPUTED_VALUE"""),"UN") -> UN | F21: =IFERROR(__xludf.DUMMYFUNCTION("""COMPUTED_VALUE"""),"Aseo") -> Aseo | G21: =(C21)*D21 -> 596 | H21: =G21*19% -> 113.24 | I21: =G21+H21 -> 709.24
A22: =IFERROR(__xludf.DUMMYFUNCTION("""COMPUTED_VALUE"""),"ti-ing-0c760711-4885-4c8f-b5d5-6615e29d0673") -> ti-ing-0c760711-4885-4c8f-b5d5-6615e29d0673 | B22: =IFERROR(__xludf.DUMMYFUNCTION("""COMPUTED_VALUE"""),"GUANTES AMARILLOS L") -> GUANTES AMARILLOS L | C22: 1 | D22: =IFERROR(__xludf.DUMMYFUNCTION("""COMPUTED_VALUE"""),495) -> 495 | E22: =IFERROR(__xludf.DUMMYFUNCTION("""COMPUTED_VALUE"""),"UN") -> UN | F22: =IFERROR(__xludf.DUMMYFUNCTION("""COMPUTED_VALUE"""),"Aseo") -> Aseo | G22: =(C22)*D22 -> 495 | H22: =G22*19% -> 94.05 | I22: =G22+H22 -> 589.05
A23: =IFERROR(__xludf.DUMMYFUNCTION("""COMPUTED_VALUE"""),"ti-ing-7fc47597-0e5d-46f8-a43c-94faaa1daf88") -> ti-ing-7fc47597-0e5d-46f8-a43c-94faaa1daf88 | B23: =IFERROR(__xludf.DUMMYFUNCTION("""COMPUTED_VALUE"""),"GUANTES AMARILLOS M") -> GUANTES AMARILLOS M | C23: 0 | D23: =IFERROR(__xludf.DUMMYFUNCTION("""COMPUTED_VALUE"""),495) -> 495 | E23: =IFERROR(__xludf.DUMMYFUNCTION("""COMPUTED_VALUE"""),"UN") -> UN | F23: =IFERROR(__xludf.DUMMYFUNCTION("""COMPUTED_VALUE"""),"Aseo") -> Aseo | G23: =(C23)*D23 -> 0 | H23: =G23*19% -> 0 | I23: =G23+H23 -> 0
A24: =IFERROR(__xludf.DUMMYFUNCTION("""COMPUTED_VALUE"""),"ti-ing-fefd1f5b-c7c3-4780-83fd-7e625942b766") -> ti-ing-fefd1f5b-c7c3-4780-83fd-7e625942b766 | B24: =IFERROR(__xludf.DUMMYFUNCTION("""COMPUTED_VALUE"""),"GUANTES AMARILLOS S") -> GUANTES AMARILLOS S | C24: 0 | D24: =IFERROR(__xludf.DUMMYFUNCTION("""COMPUTED_VALUE"""),450) -> 450 | E24: =IFERROR(__xludf.DUMMYFUNCTION("""COMPUTED_VALUE"""),"UN") -> UN | F24: =IFERROR(__xludf.DUMMYFUNCTION("""COMPUTED_VALUE"""),"Aseo") -> Aseo | G24: =(C24)*D24 -> 0 | H24: =G24*19% -> 0 | I24: =G24+H24 -> 0
A25: =IFERROR(__xludf.DUMMYFUNCTION("""COMPUTED_VALUE"""),"ti-ing-04fc2068-57ca-42bc-bedb-ceda3e223def") -> ti-ing-04fc2068-57ca-42bc-bedb-ceda3e223def | B25: =IFERROR(__xludf.DUMMYFUNCTION("""COMPUTED_VALUE"""),"Guantes De Látex L") -> Guantes De Látex L | C25: 0 | D25: =IFERROR(__xludf.DUMMYFUNCTION("""COMPUTED_VALUE"""),3649.902) -> 3649.902 | E25: =IFERROR(__xludf.DUMMYFUNCTION("""COMPUTED_VALUE"""),"UN") -> UN | F25: =IFERROR(__xludf.DUMMYFUNCTION("""COMPUTED_VALUE"""),"Aseo") -> Aseo | G25: =(C25)*D25 -> 0 | H25: =G25*19% -> 0 | I25: =G25+H25 -> 0
A26: =IFERROR(__xludf.DUMMYFUNCTION("""COMPUTED_VALUE"""),"ti-ing-3c965e17-4bc3-453d-b74f-c682b54aeade") -> ti-ing-3c965e17-4bc3-453d-b74f-c682b54aeade | B26: =IFERROR(__xludf.DUMMYFUNCTION("""COMPUTED_VALUE"""),"Guantes De Látex M") -> Guantes De Látex M | C26: 0.6 | D26: =IFERROR(__xludf.DUMMYFUNCTION("""COMPUTED_VALUE"""),3650) -> 3650 | E26: =IFERROR(__xludf.DUMMYFUNCTION("""COMPUTED_VALUE"""),"UN") -> UN | F26: =IFERROR(__xludf.DUMMYFUNCTION("""COMPUTED_VALUE"""),"Aseo") -> Aseo | G26: =(C26)*D26 -> 2190 | H26: =G26*19% -> 416.1 | I26: =G26+H26 -> 2606.1
A27: =IFERROR(__xludf.DUMMYFUNCTION("""COMPUTED_VALUE"""),"ti-ing-a5847069-c85b-4a57-a415-7cf62066dedc") -> ti-ing-a5847069-c85b-4a57-a415-7cf62066dedc | B27: =IFERROR(__xludf.DUMMYFUNCTION("""COMPUTED_VALUE"""),"Guantes De Látex S") -> Guantes De Látex S | C27: 0 | D27: =IFERROR(__xludf.DUMMYFUNCTION("""COMPUTED_VALUE"""),3650) -> 3650 | E27: =IFERROR(__xludf.DUMMYFUNCTION("""COMPUTED_VALUE"""),"un") -> un | F27: =IFERROR(__xludf.DUMMYFUNCTION("""COMPUTED_VALUE"""),"Aseo") -> Aseo | G27: =(C27)*D27 -> 0 | H27: =G27*19% -> 0 | I27: =G27+H27 -> 0
A28: =IFERROR(__xludf.DUMMYFUNCTION("""COMPUTED_VALUE"""),"ti-ing-f1845df4-9dd0-4be9-9cda-4e9939c6c9a8") -> ti-ing-f1845df4-9dd0-4be9-9cda-4e9939c6c9a8 | B28: =IFERROR(__xludf.DUMMYFUNCTION("""COMPUTED_VALUE"""),"JABON BAÑO") -> JABON BAÑO | C28: 0 | D28: =IFERROR(__xludf.DUMMYFUNCTION("""COMPUTED_VALUE"""),880) -> 880 | E28: =IFERROR(__xludf.DUMMYFUNCTION("""COMPUTED_VALUE"""),"LT") -> LT | F28: =IFERROR(__xludf.DUMMYFUNCTION("""COMPUTED_VALUE"""),"Aseo") -> Aseo | G28: =(C28)*D28 -> 0 | H28: =G28*19% -> 0 | I28: =G28+H28 -> 0
A29: =IFERROR(__xludf.DUMMYFUNCTION("""COMPUTED_VALUE"""),"ti-ing-90438c34-c1c8-455a-8b38-f56ab57f0e76") -> ti-ing-90438c34-c1c8-455a-8b38-f56ab57f0e76 | B29: =IFERROR(__xludf.DUMMYFUNCTION("""COMPUTED_VALUE"""),"LAVALOZAS") -> LAVALOZAS | C29: 1 | D29: =IFERROR(__xludf.DUMMYFUNCTION("""COMPUTED_VALUE"""),381.6) -> 381.6 | E29: =IFERROR(__xludf.DUMMYFUNCTION("""COMPUTED_VALUE"""),"LT") -> LT | F29: =IFERROR(__xludf.DUMMYFUNCTION("""COMPUTED_VALUE"""),"Aseo") -> Aseo | G29: =(C29)*D29 -> 381.6 | H29: =G29*19% -> 72.504 | I29: =G29+H29 -> 454.104
A30: =IFERROR(__xludf.DUMMYFUNCTION("""COMPUTED_VALUE"""),"ti-ing-096ebcd5-904f-4e35-9378-181fe59b0c31") -> ti-ing-096ebcd5-904f-4e35-9378-181fe59b0c31 | B30: =IFERROR(__xludf.DUMMYFUNCTION("""COMPUTED_VALUE"""),"Limpiador Crema CIF 750g") -> Limpiador Crema CIF 750g | C30: 0 | D30: =IFERROR(__xludf.DUMMYFUNCTION("""COMPUTED_VALUE"""),1522) -> 1522 | E30: =IFERROR(__xludf.DUMMYFUNCTION("""COMPUTED_VALUE"""),"UN") -> UN | F30: =IFERROR(__xludf.DUMMYFUNCTION("""COMPUTED_VALUE"""),"Aseo") -> Aseo | G30: =(C30)*D30 -> 0 | H30: =G30*19% -> 0 | I30: =G30+H30 -> 0
A31: =IFERROR(__xludf.DUMMYFUNCTION("""COMPUTED_VALUE"""),"ti-ing-87e4c4d7-978b-4106-9ff1-dda60dd75d70") -> ti-ing-87e4c4d7-978b-4106-9ff1-dda60dd75d70 | B31: =IFERROR(__xludf.DUMMYFUNCTION("""COMPUTED_VALUE"""),"LIMPIAPISOS") -> LIMPIAPISOS | C31: 5 | D31: =IFERROR(__xludf.DUMMYFUNCTION("""COMPUTED_VALUE"""),284.1160494) -> 284.11605 | E31: =IFERROR(__xludf.DUMMYFUNCTION("""COMPUTED_VALUE"""),"LT") -> LT | F31: =IFERROR(__xludf.DUMMYFUNCTION("""COMPUTED_VALUE"""),"Aseo") -> Aseo | G31: =(C31)*D31 -> 1420.5802 | H31: =G31*19% -> 269.91025 | I31: =G31+H31 -> 1690.4905
A32: =IFERROR(__xludf.DUMMYFUNCTION("""COMPUTED_VALUE"""),"ti-ing-197c4981-e3d5-425b-b927-86de4c38a9b1") -> ti-ing-197c4981-e3d5-425b-b927-86de4c38a9b1 | B32: =IFERROR(__xludf.DUMMYFUNCTION("""COMPUTED_VALUE"""),"LIMPIAVIDRIOS") -> LIMPIAVIDRIOS | C32: 5 | D32: =IFERROR(__xludf.DUMMYFUNCTION("""COMPUTED_VALUE"""),696.4) -> 696.4 | E32: =IFERROR(__xludf.DUMMYFUNCTION("""COMPUTED_VALUE"""),"LT") -> LT | F32: =IFERROR(__xludf.DUMMYFUNCTION("""COMPUTED_VALUE"""),"Aseo") -> Aseo | G32: =(C32)*D32 -> 3482 | H32: =G32*19% -> 661.58 | I32: =G32+H32 -> 4143.58
A33: =IFERROR(__xludf.DUMMYFUNCTION("""COMPUTED_VALUE"""),"ti-ing-9fcf899e-b43f-49a0-bfca-d4ca3181f761") -> ti-ing-9fcf899e-b43f-49a0-bfca-d4ca3181f761 | B33: =IFERROR(__xludf.DUMMYFUNCTION("""COMPUTED_VALUE"""),"LUSTRAMUEBLES") -> LUSTRAMUEBLES | C33: 1 | D33: =IFERROR(__xludf.DUMMYFUNCTION("""COMPUTED_VALUE"""),893) -> 893 | E33: =IFERROR(__xludf.DUMMYFUNCTION("""COMPUTED_VALUE"""),"UN") -> UN | F33: =IFERROR(__xludf.DUMMYFUNCTION("""COMPUTED_VALUE"""),"Aseo") -> Aseo | G33: =(C33)*D33 -> 893 | H33: =G33*19% -> 169.67 | I33: =G33+H33 -> 1062.67
A34: =IFERROR(__xludf.DUMMYFUNCTION("""COMPUTED_VALUE"""),"ti-ing-af8029ba-0f08-420d-ae31-6cf6502d2e32") -> ti-ing-af8029ba-0f08-420d-ae31-6cf6502d2e32 | B34: =IFERROR(__xludf.DUMMYFUNCTION("""COMPUTED_VALUE"""),"Lysoform") -> Lysoform | C34: 0 | D34: =IFERROR(__xludf.DUMMYFUNCTION("""COMPUTED_VALUE"""),2428) -> 2428 | E34: =IFERROR(__xludf.DUMMYFUNCTION("""COMPUTED_VALUE"""),"UN") -> UN | F34: =IFERROR(__xludf.DUMMYFUNCTION("""COMPUTED_VALUE"""),"Aseo") -> Aseo | G34: =(C34)*D34 -> 0 | H34: =G34*19% -> 0 | I34: =G34+H34 -> 0
A35: =IFERROR(__xludf.DUMMYFUNCTION("""COMPUTED_VALUE"""),"ti-ing-64301c86-8657-4a60-9738-54b3f81ead5a") -> ti-ing-64301c86-8657-4a60-9738-54b3f81ead5a | B35: =IFERROR(__xludf.DUMMYFUNCTION("""COMPUTED_VALUE"""),"MALLAS DE PELO (100un)") -> MALLAS DE PELO (100un) | C35: 1 | D35: =IFERROR(__xludf.DUMMYFUNCTION("""COMPUTED_VALUE"""),1529) -> 1529 | E35: =IFERROR(__xludf.DUMMYFUNCTION("""COMPUTED_VALUE"""),"UN") -> UN | F35: =IFERROR(__xludf.DUMMYFUNCTION("""COMPUTED_VALUE"""),"Aseo") -> Aseo | G35: =(C35)*D35 -> 1529 | H35: =G35*19% -> 290.51 | I35: =G35+H35 -> 1819.51
A36: =IFERROR(__xludf.DUMMYFUNCTION("""COMPUTED_VALUE"""),"ti-ing-242bf6e9-d5c5-47e7-8f0a-88f3cbbcc3af") -> ti-ing-242bf6e9-d5c5-47e7-8f0a-88f3cbbcc3af | B36: =IFERROR(__xludf.DUMMYFUNCTION("""COMPUTED_VALUE"""),"Mascarillas") -> Mascarillas | C36: 4 | D36: =IFERROR(__xludf.DUMMYFUNCTION("""COMPUTED_VALUE"""),1350) -> 1350 | E36: =IFERROR(__xludf.DUMMYFUNCTION("""COMPUTED_VALUE"""),"UN") -> UN | F36: =IFERROR(__xludf.DUMMYFUNCTION("""COMPUTED_VALUE"""),"Aseo") -> Aseo | G36: =(C36)*D36 -> 5400 | H36: =G36*19% -> 1026 | I36: =G36+H36 -> 6426
A37: =IFERROR(__xludf.DUMMYFUNCTION("""COMPUTED_VALUE"""),"ti-ing-313073f4-b1b1-442d-b077-951f3ce67b06") -> ti-ing-313073f4-b1b1-442d-b077-951f3ce67b06 | B37: =IFERROR(__xludf.DUMMYFUNCTION("""COMPUTED_VALUE"""),"NOVA Unidad") -> NOVA Unidad | C37: 5 | D37: =IFERROR(__xludf.DUMMYFUNCTION("""COMPUTED_VALUE"""),2735) -> 2735 | E37: =IFERROR(__xludf.DUMMYFUNCTION("""COMPUTED_VALUE"""),"UN") -> UN | F37: =IFERROR(__xludf.DUMMYFUNCTION("""COMPUTED_VALUE"""),"Aseo") -> Aseo | G37: =(C37)*D37 -> 13675 | H37: =G37*19% -> 2598.25 | I37: =G37+H37 -> 16273.25
A38: =IFERROR(__xludf.DUMMYFUNCTION("""COMPUTED_VALUE"""),"ti-ing-f2a85135-486f-455a-9223-1092ccd4e7cd") -> ti-ing-f2a85135-486f-455a-9223-1092ccd4e7cd | B38: =IFERROR(__xludf.DUMMYFUNCTION("""COMPUTED_VALUE"""),"PALA") -> PALA | C38: 5 | D38: =IFERROR(__xludf.DUMMYFUNCTION("""COMPUTED_VALUE"""),1165) -> 1165 | E38: =IFERROR(__xludf.DUMMYFUNCTION("""COMPUTED_VALUE"""),"UN") -> UN | F38: =IFERROR(__xludf.DUMMYFUNCTION("""COMPUTED_VALUE"""),"Aseo") -> Aseo | G38: =(C38)*D38 -> 5825 | H38: =G38*19% -> 1106.75 | I38: =G38+H38 -> 6931.75
A39: =IFERROR(__xludf.DUMMYFUNCTION("""COMPUTED_VALUE"""),"ti-ing-a496bcbe-0906-4bd7-90be-10085697981e") -> ti-ing-a496bcbe-0906-4bd7-90be-10085697981e | B39: =IFERROR(__xludf.DUMMYFUNCTION("""COMPUTED_VALUE"""),"Paño microfibra") -> Paño microfibra | C39: 16 | D39: =IFERROR(__xludf.DUMMYFUNCTION("""COMPUTED_VALUE"""),650) -> 650 | E39: =IFERROR(__xludf.DUMMYFUNCTION("""COMPUTED_VALUE"""),"UN") -> UN | F39: =IFERROR(__xludf.DUMMYFUNCTION("""COMPUTED_VALUE"""),"Aseo") -> Aseo | G39: =(C39)*D39 -> 10400 | H39: =G39*19% -> 1976 | I39: =G39+H39 -> 12376
A40: =IFERROR(__xludf.DUMMYFUNCTION("""COMPUTED_VALUE"""),"ti-ing-71ad4a79-597d-4cd3-85f8-8c113261d29e") -> ti-ing-71ad4a79-597d-4cd3-85f8-8c113261d29e | B40: =IFERROR(__xludf.DUMMYFUNCTION("""COMPUTED_VALUE"""),"PAÑOS AMARILLOS") -> PAÑOS AMARILLOS | C40: 0 | D40: =IFERROR(__xludf.DUMMYFUNCTION("""COMPUTED_VALUE"""),185) -> 185 | E40: =IFERROR(__xludf.DUMMYFUNCTION("""COMPUTED_VALUE"""),"UN") -> UN | F40: =IFERROR(__xludf.DUMMYFUNCTION("""COMPUTED_VALUE"""),"Aseo") -> Aseo | G40: =(C40)*D40 -> 0 | H40: =G40*19% -> 0 | I40: =G40+H40 -> 0
A41: =IFERROR(__xludf.DUMMYFUNCTION("""COMPUTED_VALUE"""),"ti-ing-adaa762a-98c1-4bd8-8d7f-d256999a6d54") -> ti-ing-adaa762a-98c1-4bd8-8d7f-d256999a6d54 | B41: =IFERROR(__xludf.DUMMYFUNCTION("""COMPUTED_VALUE"""),"PAPEL HIGUIENICO UN") -> PAPEL HIGUIENICO UN | C41: 6 | D41: =IFERROR(__xludf.DUMMYFUNCTION("""COMPUTED_VALUE"""),1676.25) -> 1676.25 | E41: =IFERROR(__xludf.DUMMYFUNCTION("""COMPUTED_VALUE"""),"UN") -> UN | F41: =IFERROR(__xludf.DUMMYFUNCTION("""COMPUTED_VALUE"""),"Aseo") -> Aseo | G41: =(C41)*D41 -> 10057.5 | H41: =G41*19% -> 1910.925 | I41: =G41+H41 -> 11968.425
A42: =IFERROR(__xludf.DUMMYFUNCTION("""COMPUTED_VALUE"""),"ti-ing-02407d3a-e36e-410d-8c91-3e98a395ccac") -> ti-ing-02407d3a-e36e-410d-8c91-3e98a395ccac | B42: =IFERROR(__xludf.DUMMYFUNCTION("""COMPUTED_VALUE"""),"Rinza") -> Rinza | C42: 0 | D42: =IFERROR(__xludf.DUMMYFUNCTION("""COMPUTED_VALUE"""),27731) -> 27731 | E42: =IFERROR(__xludf.DUMMYFUNCTION("""COMPUTED_VALUE"""),"UN") -> UN | F42: =IFERROR(__xludf.DUMMYFUNCTION("""COMPUTED_VALUE"""),"Aseo") -> Aseo | G42: =(C42)*D42 -> 0 | H42: =G42*19% -> 0 | I42: =G42+H42 -> 0
A43: =IFERROR(__xludf.DUMMYFUNCTION("""COMPUTED_VALUE"""),"ti-ing-dcad707d-6012-450f-8e1d-b50e4ae44b10") -> ti-ing-dcad707d-6012-450f-8e1d-b50e4ae44b10 | B43: =IFERROR(__xludf.DUMMYFUNCTION("""COMPUTED_VALUE"""),"TRAPOS BLANCOS") -> TRAPOS BLANCOS | C43: 6 | D43: =IFERROR(__xludf.DUMMYFUNCTION("""COMPUTED_VALUE"""),789) -> 789 | E43: =IFERROR(__xludf.DUMMYFUNCTION("""COMPUTED_VALUE"""),"UN") -> UN | F43: =IFERROR(__xludf.DUMMYFUNCTION("""COMPUTED_VALUE"""),"Aseo") -> Aseo | G43: =(C43)*D43 -> 4734 | H43: =G43*19% -> 899.46 | I43: =G43+H43 -> 5633.46
A44: =IFERROR(__xludf.DUMMYFUNCTION("""COMPUTED_VALUE"""),"ti-ing-46619eaa-21aa-41d5-931f-97aa9149b051") -> ti-ing-46619eaa-21aa-41d5-931f-97aa9149b051 | B44: =IFERROR(__xludf.DUMMYFUNCTION("""COMPUTED_VALUE"""),"VIRUTILLA VERDE") -> VIRUTILLA VERDE | C44: 5 | D44: =IFERROR(__xludf.DUMMYFUNCTION("""COMPUTED_VALUE"""),890) -> 890 | E44: =IFERROR(__xludf.DUMMYFUNCTION("""COMPUTED_VALUE"""),"UN") -> UN | F44: =IFERROR(__xludf.DUMMYFUNCTION("""COMPUTED_VALUE"""),"Aseo") -> Aseo | G44: =(C44)*D44 -> 4450 | H44: =G44*19% -> 845.5 | I44: =G44+H44 -> 5295.5
A45: =IFERROR(__xludf.DUMMYFUNCTION("""COMPUTED_VALUE"""),"ti-ing-753e3546-8e8c-4c1c-b8c0-f410cb9fac7d") -> ti-ing-753e3546-8e8c-4c1c-b8c0-f410cb9fac7d | B45: =IFERROR(__xludf.DUMMYFUNCTION("""COMPUTED_VALUE"""),"Agua con Gas 600 ml") -> Agua con Gas 600 ml | C45: 16 | D45: =IFERROR(__xludf.DUMMYFUNCTION("""COMPUTED_VALUE"""),351.4583) -> 351.4583 | E45: =IFERROR(__xludf.DUMMYFUNCTION("""COMPUTED_VALUE"""),"UN") -> UN | F45: =IFERROR(__xludf.DUMMYFUNCTION("""COMPUTED_VALUE"""),"Bebestibles") -> Bebestibles | G45: =(C45)*D45 -> 5623.3328 | H45: =G45*19% -> 1068.4332 | I45: =G45+H45 -> 6691.766
A46: =IFERROR(__xludf.DUMMYFUNCTION("""COMPUTED_VALUE"""),"ti-ing-2d554590-6987-4ebd-8f36-2eaade59201c") -> ti-ing-2d554590-6987-4ebd-8f36-2eaade59201c | B46: =IFERROR(__xludf.DUMMYFUNCTION("""COMPUTED_VALUE"""),"Agua sin Gas 600 ml") -> Agua sin Gas 600 ml | C46: 24 | D46: =IFERROR(__xludf.DUMMYFUNCTION("""COMPUTED_VALUE"""),351.4583) -> 351.4583 | E46: =IFERROR(__xludf.DUMMYFUNCTION("""COMPUTED_VALUE"""),"UN") -> UN | F46: =IFERROR(__xludf.DUMMYFUNCTION("""COMPUTED_VALUE"""),"Bebestibles") -> Bebestibles | G46: =(C46)*D46 -> 8434.9992 | H46: =G46*19% -> 1602.6498 | I46: =G46+H46 -> 10037.649
A47: =IFERROR(__xludf.DUMMYFUNCTION("""COMPUTED_VALUE"""),"ti-ing-e732c346-01d8-4dfd-8ca6-ff14510c0bd5") -> ti-ing-e732c346-01d8-4dfd-8ca6-ff14510c0bd5 | B47: =IFERROR(__xludf.DUMMYFUNCTION("""COMPUTED_VALUE"""),"Coca cola 350 cc") -> Coca cola 350 cc | C47: 13 | D47: =IFERROR(__xludf.DUMMYFUNCTION("""COMPUTED_VALUE"""),612.7396) -> 612.7396 | E47: =IFERROR(__xludf.DUMMYFUNCTION("""COMPUTED_VALUE"""),"UN") -> UN | F47: =IFERROR(__xludf.DUMMYFUNCTION("""COMPUTED_VALUE"""),"Bebestibles") -> Bebestibles | G47: =(C47)*D47 -> 7965.6148 | H47: =G47*19% -> 1513.4668 | I47: =G47+H47 -> 9479.0816
A48: =IFERROR(__xludf.DUMMYFUNCTION("""COMPUTED_VALUE"""),"ti-ing-a56c141e-abc8-443a-8266-32d58d78d40c") -> ti-ing-a56c141e-abc8-443a-8266-32d58d78d40c | B48: =IFERROR(__xludf.DUMMYFUNCTION("""COMPUTED_VALUE"""),"Coca cola zero 350 cc") -> Coca cola zero 350 cc | C48: 2 | D48: =IFERROR(__xludf.DUMMYFUNCTION("""COMPUTED_VALUE"""),606.5813) -> 606.5813 | E48: =IFERROR(__xludf.DUMMYFUNCTION("""COMPUTED_VALUE"""),"UN") -> UN | F48: =IFERROR(__xludf.DUMMYFUNCTION("""COMPUTED_VALUE"""),"Bebestibles") -> Bebestibles | G48: =(C48)*D48 -> 1213.1626 | H48: =G48*19% -> 230.50089 | I48: =G48+H48 -> 1443.6635
A49: =IFERROR(__xludf.DUMMYFUNCTION("""COMPUTED_VALUE"""),"ti-ing-5b9f998a-671c-474e-88c0-d5e3e2078b8c") -> ti-ing-5b9f998a-671c-474e-88c0-d5e3e2078b8c | B49: =IFERROR(__xludf.DUMMYFUNCTION("""COMPUTED_VALUE"""),"Fanta 350 cc") -> Fanta 350 cc | C49: 4 | D49: =IFERROR(__xludf.DUMMYFUNCTION("""COMPUTED_VALUE"""),612.715) -> 612.715 | E49: =IFERROR(__xludf.DUMMYFUNCTION("""COMPUTED_VALUE"""),"UN") -> UN | F49: =IFERROR(__xludf.DUMMYFUNCTION("""COMPUTED_VALUE"""),"Bebestibles") -> Bebestibles | G49: =(C49)*D49 -> 2450.86 | H49: =G49*19% -> 465.6634 | I49: =G49+H49 -> 2916.5234
A50: =IFERROR(__xludf.DUMMYFUNCTION("""COMPUTED_VALUE"""),"ti-ing-42b01feb-e855-4f88-acf1-66c2f819bf59") -> ti-ing-42b01feb-e855-4f88-acf1-66c2f819bf59 | B50: =IFERROR(__xludf.DUMMYFUNCTION("""COMPUTED_VALUE"""),"Hielo cubos") -> Hielo cubos | C50: 0 | D50: =IFERROR(__xludf.DUMMYFUNCTION("""COMPUTED_VALUE"""),546.2273) -> 546.2273 | E50: =IFERROR(__xludf.DUMMYFUNCTION("""COMPUTED_VALUE"""),"kg") -> kg | F50: =IFERROR(__xludf.DUMMYFUNCTION("""COMPUTED_VALUE"""),"Bebestibles") -> Bebestibles | G50: =(C50)*D50 -> 0 | H50: =G50*19% -> 0 | I50: =G50+H50 -> 0
A51: =IFERROR(__xludf.DUMMYFUNCTION("""COMPUTED_VALUE"""),"ti-ing-131bfafa-178d-452c-9100-f87e34267a2f") -> ti-ing-131bfafa-178d-452c-9100-f87e34267a2f | B51: =IFERROR(__xludf.DUMMYFUNCTION("""COMPUTED_VALUE"""),"Hielo frappe") -> Hielo frappe | C51: 6 | D51: =IFERROR(__xludf.DUMMYFUNCTION("""COMPUTED_VALUE"""),420) -> 420 | E51: =IFERROR(__xludf.DUMMYFUNCTION("""COMPUTED_VALUE"""),"KG") -> KG | F51: =IFERROR(__xludf.DUMMYFUNCTION("""COMPUTED_VALUE"""),"Bebestibles") -> Bebestibles | G51: =(C51)*D51 -> 2520 | H51: =G51*19% -> 478.8 | I51: =G51+H51 -> 2998.8
A52: =IFERROR(__xludf.DUMMYFUNCTION("""COMPUTED_VALUE"""),"ti-ing-08c36c8f-3d68-4d44-9e13-1657c4d9b90b") -> ti-ing-08c36c8f-3d68-4d44-9e13-1657c4d9b90b | B52: =IFERROR(__xludf.DUMMYFUNCTION("""COMPUTED_VALUE"""),"PE PORCION JUGO CHIRIMOYA (EXTRA)") -> PE PORCION JUGO CHIRIMOYA (EXTRA) | C52: 20 | D52: =IFERROR(__xludf.DUMMYFUNCTION("""COMPUTED_VALUE"""),889) -> 889 | E52: =IFERROR(__xludf.DUMMYFUNCTION("""COMPUTED_VALUE"""),"UN") -> UN | F52: =IFERROR(__xludf.DUMMYFUNCTION("""COMPUTED_VALUE"""),"Bebestibles") -> Bebestibles | G52: =(C52)*D52 -> 17780 | H52: =G52*19% -> 3378.2 | I52: =G52+H52 -> 21158.2
A53: =IFERROR(__xludf.DUMMYFUNCTION("""COMPUTED_VALUE"""),"ti-ing-4583d79a-dadd-4a88-bb28-d3a8be5b5250") -> ti-ing-4583d79a-dadd-4a88-bb28-d3a8be5b5250 | B53: =IFERROR(__xludf.DUMMYFUNCTION("""COMPUTED_VALUE"""),"PE PORCION JUGO FRAMBUESA (EXTRA)") -> PE PORCION JUGO FRAMBUESA (EXTRA) | C53: 29 | D53: =IFERROR(__xludf.DUMMYFUNCTION("""COMPUTED_VALUE"""),518) -> 518 | E53: =IFERROR(__xludf.DUMMYFUNCTION("""COMPUTED_VALUE"""),"UN") -> UN | F53: =IFERROR(__xludf.DUMMYFUNCTION("""COMPUTED_VALUE"""),"Bebestibles") -> Bebestibles | G53: =(C53)*D53 -> 15022 | H53: =G53*19% -> 2854.18 | I53: =G53+H53 -> 17876.18
A54: =IFERROR(__xludf.DUMMYFUNCTION("""COMPUTED_VALUE"""),"ti-ing-5c9566ac-4078-4562-a0a9-7e7d97607df1") -> ti-ing-5c9566ac-4078-4562-a0a9-7e7d97607df1 | B54: =IFERROR(__xludf.DUMMYFUNCTION("""COMPUTED_VALUE"""),"PE PORCION JUGO FRUTILLA (EXTRA)") -> PE PORCION JUGO FRUTILLA (EXTRA) | C54: 39 | D54: =IFERROR(__xludf.DUMMYFUNCTION("""COMPUTED_VALUE"""),493) -> 493 | E54: =IFERROR(__xludf.DUMMYFUNCTION("""COMPUTED_VALUE"""),"UN") -> UN | F54: =IFERROR(__xludf.DUMMYFUNCTION("""COMPUTED_VALUE"""),"Bebestibles") -> Bebestibles | G54: =(C54)*D54 -> 19227 | H54: =G54*19% -> 3653.13 | I54: =G54+H54 -> 22880.13
A55: =IFERROR(__xludf.DUMMYFUNCTION("""COMPUTED_VALUE"""),"ti-ing-56e58a2b-7a4a-4ef8-8144-55c565857b78") -> ti-ing-56e58a2b-7a4a-4ef8-8144-55c565857b78 | B55: =IFERROR(__xludf.DUMMYFUNCTION("""COMPUTED_VALUE"""),"PE PORCION JUGO MANGO (EXTRA)") -> PE PORCION JUGO MANGO (EXTRA) | C55: 27 | D55: =IFERROR(__xludf.DUMMYFUNCTION("""COMPUTED_VALUE"""),356) -> 356 | E55: =IFERROR(__xludf.DUMMYFUNCTION("""COMPUTED_VALUE"""),"UN") -> UN | F55: =IFERROR(__xludf.DUMMYFUNCTION("""COMPUTED_VALUE"""),"Bebestibles") -> Bebestibles | G55: =(C55)*D55 -> 9612 | H55: =G55*19% -> 1826.28 | I55: =G55+H55 -> 11438.28
A56: =IFERROR(__xludf.DUMMYFUNCTION("""COMPUTED_VALUE"""),"ti-ing-5f2ea799-9832-4a2f-a15b-8d69a2a3faae") -> ti-ing-5f2ea799-9832-4a2f-a15b-8d69a2a3faae | B56: =IFERROR(__xludf.DUMMYFUNCTION("""COMPUTED_VALUE"""),"PE PORCION JUGO MARACUYA (EXTRA)") -> PE PORCION JUGO MARACUYA (EXTRA) | C56: 24 | D56: =IFERROR(__xludf.DUMMYFUNCTION("""COMPUTED_VALUE"""),858) -> 858 | E56: =IFERROR(__xludf.DUMMYFUNCTION("""COMPUTED_VALUE"""),"UN") -> UN | F56: =IFERROR(__xludf.DUMMYFUNCTION("""COMPUTED_VALUE"""),"Bebestibles") -> Bebestibles | G56: =(C56)*D56 -> 20592 | H56: =G56*19% -> 3912.48 | I56: =G56+H56 -> 24504.48
A57: =IFERROR(__xludf.DUMMYFUNCTION("""COMPUTED_VALUE"""),"ti-ing-7c21654a-bcfa-46bc-a077-bd6a00b453c5") -> ti-ing-7c21654a-bcfa-46bc-a077-bd6a00b453c5 | B57: =IFERROR(__xludf.DUMMYFUNCTION("""COMPUTED_VALUE"""),"PE PORCION JUGO MELON (EXTRA)") -> PE PORCION JUGO MELON (EXTRA) | C57: 5 | D57: =IFERROR(__xludf.DUMMYFUNCTION("""COMPUTED_VALUE"""),500) -> 500 | E57: =IFERROR(__xludf.DUMMYFUNCTION("""COMPUTED_VALUE"""),"UN") -> UN | F57: =IFERROR(__xludf.DUMMYFUNCTION("""COMPUTED_VALUE"""),"Bebestibles") -> Bebestibles | G57: =(C57)*D57 -> 2500 | H57: =G57*19% -> 475 | I57: =G57+H57 -> 2975
A58: =IFERROR(__xludf.DUMMYFUNCTION("""COMPUTED_VALUE"""),"ti-ing-f42d7ef4-1119-47d6-bfe4-33caeace0e4c") -> ti-ing-f42d7ef4-1119-47d6-bfe4-33caeace0e4c | B58: =IFERROR(__xludf.DUMMYFUNCTION("""COMPUTED_VALUE"""),"PE PORCION JUGO PIÑA (EXTRA)") -> PE PORCION JUGO PIÑA (EXTRA) | C58: 11 | D58: =IFERROR(__xludf.DUMMYFUNCTION("""COMPUTED_VALUE"""),444) -> 444 | E58: =IFERROR(__xludf.DUMMYFUNCTION("""COMPUTED_VALUE"""),"UN") -> UN | F58: =IFERROR(__xludf.DUMMYFUNCTION("""COMPUTED_VALUE"""),"Bebestibles") -> Bebestibles | G58: =(C58)*D58 -> 4884 | H58: =G58*19% -> 927.96 | I58: =G58+H58 -> 5811.96
A59: =IFERROR(__xludf.DUMMYFUNCTION("""COMPUTED_VALUE"""),"ti-ing-df343f29-7af3-4b51-8f4b-503bba75c5c6") -> ti-ing-df343f29-7af3-4b51-8f4b-503bba75c5c6 | B59: =IFERROR(__xludf.DUMMYFUNCTION("""COMPUTED_VALUE"""),"PE pulpa frambuesa mix") -> PE pulpa frambuesa mix | C59: 0 | D59: =IFERROR(__xludf.DUMMYFUNCTION("""COMPUTED_VALUE"""),259) -> 259 | E59: =IFERROR(__xludf.DUMMYFUNCTION("""COMPUTED_VALUE"""),"UN") -> UN | F59: =IFERROR(__xludf.DUMMYFUNCTION("""COMPUTED_VALUE"""),"Bebestibles") -> Bebestibles | G59: =(C59)*D59 -> 0 | H59: =G59*19% -> 0 | I59: =G59+H59 -> 0
A60: =IFERROR(__xludf.DUMMYFUNCTION("""COMPUTED_VALUE"""),"ti-ing-0fca9086-98f2-4171-92bd-66b245acee2c") -> ti-ing-0fca9086-98f2-4171-92bd-66b245acee2c | B60: =IFERROR(__xludf.DUMMYFUNCTION("""COMPUTED_VALUE"""),"PE pulpa frutilla mix") -> PE pulpa frutilla mix | C60: 0 | D60: =IFERROR(__xludf.DUMMYFUNCTION("""COMPUTED_VALUE"""),193) -> 193 | E60: =IFERROR(__xludf.DUMMYFUNCTION("""COMPUTED_VALUE"""),"UN") -> UN | F60: =IFERROR(__xludf.DUMMYFUNCTION("""COMPUTED_VALUE"""),"Bebestibles") -> Bebestibles | G60: =(C60)*D60 -> 0 | H60: =G60*19% -> 0 | I60: =G60+H60 -> 0
A61: =IFERROR(__xludf.DUMMYFUNCTION("""COMPUTED_VALUE"""),"ti-ing-177ceabf-271a-400b-97bf-bba4e34859a7") -> ti-ing-177ceabf-271a-400b-97bf-bba4e34859a7 | B61: =IFERROR(__xludf.DUMMYFUNCTION("""COMPUTED_VALUE"""),"PE pulpa mango mix") -> PE pulpa mango mix | C61: 0 | D61: =IFERROR(__xludf.DUMMYFUNCTION("""COMPUTED_VALUE"""),178) -> 178 | E61: =IFERROR(__xludf.DUMMYFUNCTION("""COMPUTED_VALUE"""),"UN") -> UN | F61: =IFERROR(__xludf.DUMMYFUNCTION("""COMPUTED_VALUE"""),"Bebestibles") -> Bebestibles | G61: =(C61)*D61 -> 0 | H61: =G61*19% -> 0 | I61: =G61+H61 -> 0
B62: =IFERROR(__xludf.DUMMYFUNCTION("""COMPUTED_VALUE"""),"Primaveral") -> Primaveral | C62: 25 | D62: =IFERROR(__xludf.DUMMYFUNCTION("""COMPUTED_VALUE"""),910) -> 910 | E62: =IFERROR(__xludf.DUMMYFUNCTION("""COMPUTED_VALUE"""),"UN") -> UN | F62: =IFERROR(__xludf.DUMMYFUNCTION("""COMPUTED_VALUE"""),"Bebestibles") -> Bebestibles | G62: =(C62)*D62 -> 22750 | H62: =G62*19% -> 4322.5 | I62: =G62+H62 -> 27072.5
A63: =IFERROR(__xludf.DUMMYFUNCTION("""COMPUTED_VALUE"""),"ti-ing-27365f0e-3bbd-48de-bc63-541a722a9716") -> ti-ing-27365f0e-3bbd-48de-bc63-541a722a9716 | B63: =IFERROR(__xludf.DUMMYFUNCTION("""COMPUTED_VALUE"""),"Pulpa Chirimoya") -> Pulpa Chirimoya | C63: 14 | D63: =IFERROR(__xludf.DUMMYFUNCTION("""COMPUTED_VALUE"""),5290) -> 5290 | E63: =IFERROR(__xludf.DUMMYFUNCTION("""COMPUTED_VALUE"""),"KG") -> KG | F63: =IFERROR(__xludf.DUMMYFUNCTION("""COMPUTED_VALUE"""),"Bebestibles") -> Bebestibles | G63: =(C63)*D63 -> 74060 | H63: =G63*19% -> 14071.4 | I63: =G63+H63 -> 88131.4
A64: =IFERROR(__xludf.DUMMYFUNCTION("""COMPUTED_VALUE"""),"ti-ing-c61601c6-808a-4073-be84-3536b4f328af") -> ti-ing-c61601c6-808a-4073-be84-3536b4f328af | B64: =IFERROR(__xludf.DUMMYFUNCTION("""COMPUTED_VALUE"""),"Pulpa Frambuesa") -> Pulpa Frambuesa | C64: 15 | D64: =IFERROR(__xludf.DUMMYFUNCTION("""COMPUTED_VALUE"""),6800) -> 6800 | E64: =IFERROR(__xludf.DUMMYFUNCTION("""COMPUTED_VALUE"""),"KG") -> KG | F64: =IFERROR(__xludf.DUMMYFUNCTION("""COMPUTED_VALUE"""),"Bebestibles") -> Bebestibles | G64: =(C64)*D64 -> 102000 | H64: =G64*19% -> 19380 | I64: =G64+H64 -> 121380
A65: =IFERROR(__xludf.DUMMYFUNCTION("""COMPUTED_VALUE"""),"ti-ing-0a6dd713-e7a7-4872-af86-42c45add6bdf") -> ti-ing-0a6dd713-e7a7-4872-af86-42c45add6bdf | B65: =IFERROR(__xludf.DUMMYFUNCTION("""COMPUTED_VALUE"""),"Pulpa Frutilla") -> Pulpa Frutilla | C65: 8 | D65: =IFERROR(__xludf.DUMMYFUNCTION("""COMPUTED_VALUE"""),2950) -> 2950 | E65: =IFERROR(__xludf.DUMMYFUNCTION("""COMPUTED_VALUE"""),"KG") -> KG | F65: =IFERROR(__xludf.DUMMYFUNCTION("""COMPUTED_VALUE"""),"Bebestibles") -> Bebestibles | G65: =(C65)*D65 -> 23600 | H65: =G65*19% -> 4484 | I65: =G65+H65 -> 28084
A66: =IFERROR(__xludf.DUMMYFUNCTION("""COMPUTED_VALUE"""),"ti-ing-cfdaf79a-6246-42a9-afab-7cba8ae515ca") -> ti-ing-cfdaf79a-6246-42a9-afab-7cba8ae515ca | B66: =IFERROR(__xludf.DUMMYFUNCTION("""COMPUTED_VALUE"""),"Pulpa Mango") -> Pulpa Mango | C66: 13 | D66: =IFERROR(__xludf.DUMMYFUNCTION("""COMPUTED_VALUE"""),4490) -> 4490 | E66: =IFERROR(__xludf.DUMMYFUNCTION("""COMPUTED_VALUE"""),"KG") -> KG | F66: =IFERROR(__xludf.DUMMYFUNCTION("""COMPUTED_VALUE"""),"Bebestibles") -> Bebestibles | G66: =(C66)*D66 -> 58370 | H66: =G66*19% -> 11090.3 | I66: =G66+H66 -> 69460.3
A67: =IFERROR(__xludf.DUMMYFUNCTION("""COMPUTED_VALUE"""),"ti-ing-836eb301-0b64-45eb-89be-be872a9297e4") -> ti-ing-836eb301-0b64-45eb-89be-be872a9297e4 | B67: =IFERROR(__xludf.DUMMYFUNCTION("""COMPUTED_VALUE"""),"Pulpa Maracuya S/Pepas") -> Pulpa Maracuya S/Pepas | C67: 2 | D67: =IFERROR(__xludf.DUMMYFUNCTION("""COMPUTED_VALUE"""),5990) -> 5990 | E67: =IFERROR(__xludf.DUMMYFUNCTION("""COMPUTED_VALUE"""),"KG") -> KG | F67: =IFERROR(__xludf.DUMMYFUNCTION("""COMPUTED_VALUE"""),"Bebestibles") -> Bebestibles | G67: =(C67)*D67 -> 11980 | H67: =G67*19% -> 2276.2 | I67: =G67+H67 -> 14256.2
A68: =IFERROR(__xludf.DUMMYFUNCTION("""COMPUTED_VALUE"""),"ti-ing-f5eb30b4-794d-42f5-a2dd-41746ad30690") -> ti-ing-f5eb30b4-794d-42f5-a2dd-41746ad30690 | B68: =IFERROR(__xludf.DUMMYFUNCTION("""COMPUTED_VALUE"""),"Pulpa Melon") -> Pulpa Melon | C68: 2 | D68: =IFERROR(__xludf.DUMMYFUNCTION("""COMPUTED_VALUE"""),3100) -> 3100 | E68: =IFERROR(__xludf.DUMMYFUNCTION("""COMPUTED_VALUE"""),"KG") -> KG | F68: =IFERROR(__xludf.DUMMYFUNCTION("""COMPUTED_VALUE"""),"Bebestibles") -> Bebestibles | G68: =(C68)*D68 -> 6200 | H68: =G68*19% -> 1178 | I68: =G68+H68 -> 7378
A69: =IFERROR(__xludf.DUMMYFUNCTION("""COMPUTED_VALUE"""),"ti-ing-f5eb30b4-794d-42f5-a2dd-41746ad30691") -> ti-ing-f5eb30b4-794d-42f5-a2dd-41746ad30691 | B69: =IFERROR(__xludf.DUMMYFUNCTION("""COMPUTED_VALUE"""),"Pulpa naranja") -> Pulpa naranja | C69: 18 | D69: =IFERROR(__xludf.DUMMYFUNCTION("""COMPUTED_VALUE"""),4715) -> 4715 | E69: =IFERROR(__xludf.DUMMYFUNCTION("""COMPUTED_VALUE"""),"KG") -> KG | F69: =IFERROR(__xludf.DUMMYFUNCTION("""COMPUTED_VALUE"""),"Bebestibles") -> Bebestibles | G69: =(C69)*D69 -> 84870 | H69: =G69*19% -> 16125.3 | I69: =G69+H69 -> 100995.3
A70: =IFERROR(__xludf.DUMMYFUNCTION("""COMPUTED_VALUE"""),"ti-ing-05169dad-82a2-4ad5-abca-f8039dfa9275") -> ti-ing-05169dad-82a2-4ad5-abca-f8039dfa9275 | B70: =IFERROR(__xludf.DUMMYFUNCTION("""COMPUTED_VALUE"""),"Pulpa Piña") -> Pulpa Piña | C70: 1 | D70: =IFERROR(__xludf.DUMMYFUNCTION("""COMPUTED_VALUE"""),3600) -> 3600 | E70: =IFERROR(__xludf.DUMMYFUNCTION("""COMPUTED_VALUE"""),"KG") -> KG | F70: =IFERROR(__xludf.DUMMYFUNCTION("""COMPUTED_VALUE"""),"Bebestibles") -> Bebestibles | G70: =(C70)*D70 -> 3600 | H70: =G70*19% -> 684 | I70: =G70+H70 -> 4284
A71: =IFERROR(__xludf.DUMMYFUNCTION("""COMPUTED_VALUE"""),"ti-ing-17dc3026-6b74-4df3-a8d6-9e28e708f104") -> ti-ing-17dc3026-6b74-4df3-a8d6-9e28e708f104 | B71: =IFERROR(__xludf.DUMMYFUNCTION("""COMPUTED_VALUE"""),"Sprite 350 cc") -> Sprite 350 cc | C71: 12 | D71: =IFERROR(__xludf.DUMMYFUNCTION("""COMPUTED_VALUE"""),606.5583) -> 606.5583 | E71: =IFERROR(__xludf.DUMMYFUNCTION("""COMPUTED_VALUE"""),"UN") -> UN | F71: =IFERROR(__xludf.DUMMYFUNCTION("""COMPUTED_VALUE"""),"Bebestibles") -> Bebestibles | G71: =(C71)*D71 -> 7278.6996 | H71: =G71*19% -> 1382.9529 | I71: =G71+H71 -> 8661.6525
A72: =IFERROR(__xludf.DUMMYFUNCTION("""COMPUTED_VALUE"""),"ti-ing-925cd36a-a250-4073-9075-f890c840ff54") -> ti-ing-925cd36a-a250-4073-9075-f890c840ff54 | B72: =IFERROR(__xludf.DUMMYFUNCTION("""COMPUTED_VALUE"""),"Sprite Zero 350 cc") -> Sprite Zero 350 cc | C72: 16 | D72: =IFERROR(__xludf.DUMMYFUNCTION("""COMPUTED_VALUE"""),606.5583) -> 606.5583 | E72: =IFERROR(__xludf.DUMMYFUNCTION("""COMPUTED_VALUE"""),"UN") -> UN | F72: =IFERROR(__xludf.DUMMYFUNCTION("""COMPUTED_VALUE"""),"Bebestibles") -> Bebestibles | G72: =(C72)*D72 -> 9704.9328 | H72: =G72*19% -> 1843.9372 | I72: =G72+H72 -> 11548.87
A73: =IFERROR(__xludf.DUMMYFUNCTION("""COMPUTED_VALUE"""),"ti-ing-f76fed7a-9b00-4997-8f9e-73bd5e249be8") -> ti-ing-f76fed7a-9b00-4997-8f9e-73bd5e249be8 | B73: =IFERROR(__xludf.DUMMYFUNCTION("""COMPUTED_VALUE"""),"Café Descafeinado 504 (caja)") -> Café Descafeinado 504 (caja) | C73: 1 | D73: =IFERROR(__xludf.DUMMYFUNCTION("""COMPUTED_VALUE"""),519.9) -> 519.9 | E73: =IFERROR(__xludf.DUMMYFUNCTION("""COMPUTED_VALUE"""),"un") -> un | F73: =IFERROR(__xludf.DUMMYFUNCTION("""COMPUTED_VALUE"""),"Cafetería") -> Cafetería | G73: =(C73)*D73 -> 519.9 | H73: =G73*19% -> 98.781 | I73: =G73+H73 -> 618.681
A74: =IFERROR(__xludf.DUMMYFUNCTION("""COMPUTED_VALUE"""),"ti-ing-7999dd71-66f3-480c-ac93-ff256e0b1f76") -> ti-ing-7999dd71-66f3-480c-ac93-ff256e0b1f76 | B74: =IFERROR(__xludf.DUMMYFUNCTION("""COMPUTED_VALUE"""),"Café grano 1k") -> Café grano 1k | C74: 0 | D74: =IFERROR(__xludf.DUMMYFUNCTION("""COMPUTED_VALUE"""),18705) -> 18705 | E74: =IFERROR(__xludf.DUMMYFUNCTION("""COMPUTED_VALUE"""),"KG") -> KG | F74: =IFERROR(__xludf.DUMMYFUNCTION("""COMPUTED_VALUE"""),"Cafetería") -> Cafetería | G74: =(C74)*D74 -> 0 | H74: =G74*19% -> 0 | I74: =G74+H74 -> 0
A75: =IFERROR(__xludf.DUMMYFUNCTION("""COMPUTED_VALUE"""),"ti-ing-73128f7c-be42-49de-8aba-c9a9a60678a0") -> ti-ing-73128f7c-be42-49de-8aba-c9a9a60678a0 | B75: =IFERROR(__xludf.DUMMYFUNCTION("""COMPUTED_VALUE"""),"Chai En Polvo 504 (bolsa 1,8 kg)") -> Chai En Polvo 504 (bolsa 1,8 kg) | C75: 4.47 | D75: =IFERROR(__xludf.DUMMYFUNCTION("""COMPUTED_VALUE"""),21250) -> 21250 | E75: =IFERROR(__xludf.DUMMYFUNCTION("""COMPUTED_VALUE"""),"Kg") -> Kg | F75: =IFERROR(__xludf.DUMMYFUNCTION("""COMPUTED_VALUE"""),"Cafetería") -> Cafetería | G75: =(C75)*D75 -> 94987.5 | H75: =G75*19% -> 18047.625 | I75: =G75+H75 -> 113035.12
A76: =IFERROR(__xludf.DUMMYFUNCTION("""COMPUTED_VALUE"""),"ti-ing-b9b128e7-f3d3-420f-8ded-36abfbbf64c9") -> ti-ing-b9b128e7-f3d3-420f-8ded-36abfbbf64c9 | B76: =IFERROR(__xludf.DUMMYFUNCTION("""COMPUTED_VALUE"""),"Chocolate en polvo 504 (bolsa 2 kg)") -> Chocolate en polvo 504 (bolsa 2 kg) | C76: 4.23 | D76: =IFERROR(__xludf.DUMMYFUNCTION("""COMPUTED_VALUE"""),13991.5) -> 13991.5 | E76: =IFERROR(__xludf.DUMMYFUNCTION("""COMPUTED_VALUE"""),"KG") -> KG | F76: =IFERROR(__xludf.DUMMYFUNCTION("""COMPUTED_VALUE"""),"Cafetería") -> Cafetería | G76: =(C76)*D76 -> 59184.045 | H76: =G76*19% -> 11244.969 | I76: =G76+H76 -> 70429.014
A77: =IFERROR(__xludf.DUMMYFUNCTION("""COMPUTED_VALUE"""),"ti-ing-60b67dd6-c83d-47fb-ac43-4a397918a54a") -> ti-ing-60b67dd6-c83d-47fb-ac43-4a397918a54a | B77: =IFERROR(__xludf.DUMMYFUNCTION("""COMPUTED_VALUE"""),"Chocolate Liquido") -> Chocolate Liquido | C77: 2 | D77: =IFERROR(__xludf.DUMMYFUNCTION("""COMPUTED_VALUE"""),3360) -> 3360 | E77: =IFERROR(__xludf.DUMMYFUNCTION("""COMPUTED_VALUE"""),"un") -> un | F77: =IFERROR(__xludf.DUMMYFUNCTION("""COMPUTED_VALUE"""),"Cafetería") -> Cafetería | G77: =(C77)*D77 -> 6720 | H77: =G77*19% -> 1276.8 | I77: =G77+H77 -> 7996.8
A78: =IFERROR(__xludf.DUMMYFUNCTION("""COMPUTED_VALUE"""),"ti-ing-7d8d02af-ef1d-4855-8b49-db888802881d") -> ti-ing-7d8d02af-ef1d-4855-8b49-db888802881d | B78: =IFERROR(__xludf.DUMMYFUNCTION("""COMPUTED_VALUE"""),"Mashmellows") -> Mashmellows | C78: 3 | D78: =IFERROR(__xludf.DUMMYFUNCTION("""COMPUTED_VALUE"""),1512.733) -> 1512.733 | E78: =IFERROR(__xludf.DUMMYFUNCTION("""COMPUTED_VALUE"""),"Kg") -> Kg | F78: =IFERROR(__xludf.DUMMYFUNCTION("""COMPUTED_VALUE"""),"Cafetería") -> Cafetería | G78: =(C78)*D78 -> 4538.199 | H78: =G78*19% -> 862.25781 | I78: =G78+H78 -> 5400.4568
B79: =IFERROR(__xludf.DUMMYFUNCTION("""COMPUTED_VALUE"""),"Matcha") -> Matcha | C79: 0.22 | D79: =IFERROR(__xludf.DUMMYFUNCTION("""COMPUTED_VALUE"""),133333) -> 133333 | E79: =IFERROR(__xludf.DUMMYFUNCTION("""COMPUTED_VALUE"""),"KG") -> KG | F79: =IFERROR(__xludf.DUMMYFUNCTION("""COMPUTED_VALUE"""),"Cafetería") -> Cafetería | G79: =(C79)*D79 -> 29333.26 | H79: =G79*19% -> 5573.3194 | I79: =G79+H79 -> 34906.579
B80: =IFERROR(__xludf.DUMMYFUNCTION("""COMPUTED_VALUE"""),"Metilcelulosa") -> Metilcelulosa | C80: 0.082 | D80: =IFERROR(__xludf.DUMMYFUNCTION("""COMPUTED_VALUE"""),14958) -> 14958 | E80: =IFERROR(__xludf.DUMMYFUNCTION("""COMPUTED_VALUE"""),"KG") -> KG | F80: =IFERROR(__xludf.DUMMYFUNCTION("""COMPUTED_VALUE"""),"Cafetería") -> Cafetería | G80: =(C80)*D80 -> 1226.556 | H80: =G80*19% -> 233.04564 | I80: =G80+H80 -> 1459.6016
A81: =IFERROR(__xludf.DUMMYFUNCTION("""COMPUTED_VALUE"""),"ti-ing-63ac2eac-77a4-4a08-942d-2708cdee1af2") -> ti-ing-63ac2eac-77a4-4a08-942d-2708cdee1af2 | B81: =IFERROR(__xludf.DUMMYFUNCTION("""COMPUTED_VALUE"""),"Syrup Esencia Amaretto 504 (750cc)") -> Syrup Esencia Amaretto 504 (750cc) | C81: 1 | D81: =IFERROR(__xludf.DUMMYFUNCTION("""COMPUTED_VALUE"""),14565.33) -> 14565.33 | E81: =IFERROR(__xludf.DUMMYFUNCTION("""COMPUTED_VALUE"""),"un") -> un | F81: =IFERROR(__xludf.DUMMYFUNCTION("""COMPUTED_VALUE"""),"Cafetería") -> Cafetería | G81: =(C81)*D81 -> 14565.33 | H81: =G81*19% -> 2767.4127 | I81: =G81+H81 -> 17332.743
A82: =IFERROR(__xludf.DUMMYFUNCTION("""COMPUTED_VALUE"""),"ti-ing-c849733f-e001-48f8-93bc-ba7bae902493") -> ti-ing-c849733f-e001-48f8-93bc-ba7bae902493 | B82: =IFERROR(__xludf.DUMMYFUNCTION("""COMPUTED_VALUE"""),"Syrup Esencia Avellana 504 (750cc)") -> Syrup Esencia Avellana 504 (750cc) | C82: 0.933 | D82: =IFERROR(__xludf.DUMMYFUNCTION("""COMPUTED_VALUE"""),14565.33) -> 14565.33 | E82: =IFERROR(__xludf.DUMMYFUNCTION("""COMPUTED_VALUE"""),"un") -> un | F82: =IFERROR(__xludf.DUMMYFUNCTION("""COMPUTED_VALUE"""),"Cafetería") -> Cafetería | G82: =(C82)*D82 -> 13589.453 | H82: =G82*19% -> 2581.996 | I82: =G82+H82 -> 16171.449
A83: =IFERROR(__xludf.DUMMYFUNCTION("""COMPUTED_VALUE"""),"ti-ing-5a1c804e-222c-4669-a220-bc3d876665b0") -> ti-ing-5a1c804e-222c-4669-a220-bc3d876665b0 | B83: =IFERROR(__xludf.DUMMYFUNCTION("""COMPUTED_VALUE"""),"Syrup Esencia Canela 504 (750cc)") -> Syrup Esencia Canela 504 (750cc) | C83: 0.6 | D83: =IFERROR(__xludf.DUMMYFUNCTION("""COMPUTED_VALUE"""),14565.33) -> 14565.33 | E83: =IFERROR(__xludf.DUMMYFUNCTION("""COMPUTED_VALUE"""),"un") -> un | F83: =IFERROR(__xludf.DUMMYFUNCTION("""COMPUTED_VALUE"""),"Cafetería") -> Cafetería | G83: =(C83)*D83 -> 8739.198 | H83: =G83*19% -> 1660.4476 | I83: =G83+H83 -> 10399.646
A84: =IFERROR(__xludf.DUMMYFUNCTION("""COMPUTED_VALUE"""),"ti-ing-2afee1a4-7742-432e-9582-e7f1946d3437") -> ti-ing-2afee1a4-7742-432e-9582-e7f1946d3437 | B84: =IFERROR(__xludf.DUMMYFUNCTION("""COMPUTED_VALUE"""),"Syrup Esencia Caramelo 504 (750cc)") -> Syrup Esencia Caramelo 504 (750cc) | C84: 0.53 | D84: =IFERROR(__xludf.DUMMYFUNCTION("""COMPUTED_VALUE"""),14565.33) -> 14565.33 | E84: =IFERROR(__xludf.DUMMYFUNCTION("""COMPUTED_VALUE"""),"UN") -> UN | F84: =IFERROR(__xludf.DUMMYFUNCTION("""COMPUTED_VALUE"""),"Cafetería") -> Cafetería | G84: =(C84)*D84 -> 7719.6249 | H84: =G84*19% -> 1466.7287 | I84: =G84+H84 -> 9186.3536
A85: =IFERROR(__xludf.DUMMYFUNCTION("""COMPUTED_VALUE"""),"ti-ing-19d34ff0-8607-4466-898f-87c0df45d86b") -> ti-ing-19d34ff0-8607-4466-898f-87c0df45d86b | B85: =IFERROR(__xludf.DUMMYFUNCTION("""COMPUTED_VALUE"""),"Syrup Esencia Chai 504 (750cc)") -> Syrup Esencia Chai 504 (750cc) | C85: 0.4 | D85: =IFERROR(__xludf.DUMMYFUNCTION("""COMPUTED_VALUE"""),16000) -> 16000 | E85: =IFERROR(__xludf.DUMMYFUNCTION("""COMPUTED_VALUE"""),"UN") -> UN | F85: =IFERROR(__xludf.DUMMYFUNCTION("""COMPUTED_VALUE"""),"Cafetería") -> Cafetería | G85: =(C85)*D85 -> 6400 | H85: =G85*19% -> 1216 | I85: =G85+H85 -> 7616
A86: =IFERROR(__xludf.DUMMYFUNCTION("""COMPUTED_VALUE"""),"ti-ing-6e43ce5e-9ab8-48be-8833-ad92e26a4c39") -> ti-ing-6e43ce5e-9ab8-48be-8833-ad92e26a4c39 | B86: =IFERROR(__xludf.DUMMYFUNCTION("""COMPUTED_VALUE"""),"Syrup Esencia coco 504 (750cc)") -> Syrup Esencia coco 504 (750cc) | C86: 0.8 | D86: =IFERROR(__xludf.DUMMYFUNCTION("""COMPUTED_VALUE"""),14565.33) -> 14565.33 | E86: =IFERROR(__xludf.DUMMYFUNCTION("""COMPUTED_VALUE"""),"UN") -> UN | F86: =IFERROR(__xludf.DUMMYFUNCTION("""COMPUTED_VALUE"""),"Cafetería") -> Cafetería | G86: =(C86)*D86 -> 11652.264 | H86: =G86*19% -> 2213.9302 | I86: =G86+H86 -> 13866.194
A87: =IFERROR(__xludf.DUMMYFUNCTION("""COMPUTED_VALUE"""),"ti-ing-b0ff34ea-0e7e-455b-90d0-99c07f16b527") -> ti-ing-b0ff34ea-0e7e-455b-90d0-99c07f16b527 | B87: =IFERROR(__xludf.DUMMYFUNCTION("""COMPUTED_VALUE"""),"Syrup Esencia Menta 504 (750cc)") -> Syrup Esencia Menta 504 (750cc) | C87: 0.53 | D87: =IFERROR(__xludf.DUMMYFUNCTION("""COMPUTED_VALUE"""),14565.33) -> 14565.33 | E87: =IFERROR(__xludf.DUMMYFUNCTION("""COMPUTED_VALUE"""),"UN") -> UN | F87: =IFERROR(__xludf.DUMMYFUNCTION("""COMPUTED_VALUE"""),"Cafetería") -> Cafetería | G87: =(C87)*D87 -> 7719.6249 | H87: =G87*19% -> 1466.7287 | I87: =G87+H87 -> 9186.3536
A88: =IFERROR(__xludf.DUMMYFUNCTION("""COMPUTED_VALUE"""),"ti-ing-6e0beb61-027c-4b38-9367-426237c4b1f2") -> ti-ing-6e0beb61-027c-4b38-9367-426237c4b1f2 | B88: =IFERROR(__xludf.DUMMYFUNCTION("""COMPUTED_VALUE"""),"Syrup Esencia Vainilla 504 (750cc)") -> Syrup Esencia Vainilla 504 (750cc) | C88: 1 | D88: =IFERROR(__xludf.DUMMYFUNCTION("""COMPUTED_VALUE"""),14565.33) -> 14565.33 | E88: =IFERROR(__xludf.DUMMYFUNCTION("""COMPUTED_VALUE"""),"UN") -> UN | F88: =IFERROR(__xludf.DUMMYFUNCTION("""COMPUTED_VALUE"""),"Cafetería") -> Cafetería | G88: =(C88)*D88 -> 14565.33 | H88: =G88*19% -> 2767.4127 | I88: =G88+H88 -> 17332.743
A89: =IFERROR(__xludf.DUMMYFUNCTION("""COMPUTED_VALUE"""),"ti-ing-73f124ed-8131-43ba-8640-d0cb789b4e9e") -> ti-ing-73f124ed-8131-43ba-8640-d0cb789b4e9e | B89: =IFERROR(__xludf.DUMMYFUNCTION("""COMPUTED_VALUE"""),"Balines para sifon BestWhip") -> Balines para sifon BestWhip | C89: 11 | D89: =IFERROR(__xludf.DUMMYFUNCTION("""COMPUTED_VALUE"""),579) -> 579 | E89: =IFERROR(__xludf.DUMMYFUNCTION("""COMPUTED_VALUE"""),"UN") -> UN | F89: =IFERROR(__xludf.DUMMYFUNCTION("""COMPUTED_VALUE"""),"Desechables") -> Desechables | G89: =(C89)*D89 -> 6369 | H89: =G89*19% -> 1210.11 | I89: =G89+H89 -> 7579.11
A90: =IFERROR(__xludf.DUMMYFUNCTION("""COMPUTED_VALUE"""),"ti-ing-505df4ad-6b27-4623-b751-cef96371da79") -> ti-ing-505df4ad-6b27-4623-b751-cef96371da79 | B90: =IFERROR(__xludf.DUMMYFUNCTION("""COMPUTED_VALUE"""),"Bandeja rectangular n4 carton empanadas") -> Bandeja rectangular n4 carton empanadas | C90: 200 | D90: =IFERROR(__xludf.DUMMYFUNCTION("""COMPUTED_VALUE"""),27.70396) -> 27.70396 | E90: =IFERROR(__xludf.DUMMYFUNCTION("""COMPUTED_VALUE"""),"UN") -> UN | F90: =IFERROR(__xludf.DUMMYFUNCTION("""COMPUTED_VALUE"""),"Desechables") -> Desechables | G90: =(C90)*D90 -> 5540.792 | H90: =G90*19% -> 1052.7505 | I90: =G90+H90 -> 6593.5425
A91: =IFERROR(__xludf.DUMMYFUNCTION("""COMPUTED_VALUE"""),"ti-ing-364ff0c9-e139-4020-bd12-d99eae1a49cd") -> ti-ing-364ff0c9-e139-4020-bd12-d99eae1a49cd | B91: =IFERROR(__xludf.DUMMYFUNCTION("""COMPUTED_VALUE"""),"Bolsa Celofan 8x20 cubiertos") -> Bolsa Celofan 8x20 cubiertos | C91: 100 | D91: =IFERROR(__xludf.DUMMYFUNCTION("""COMPUTED_VALUE"""),20.97) -> 20.97 | E91: =IFERROR(__xludf.DUMMYFUNCTION("""COMPUTED_VALUE"""),"un") -> un | F91: =IFERROR(__xludf.DUMMYFUNCTION("""COMPUTED_VALUE"""),"Desechables") -> Desechables | G91: =(C91)*D91 -> 2097 | H91: =G91*19% -> 398.43 | I91: =G91+H91 -> 2495.43
A92: =IFERROR(__xludf.DUMMYFUNCTION("""COMPUTED_VALUE"""),"ti-ing-87d71194-0848-4d96-bf1e-88911a7b1aca") -> ti-ing-87d71194-0848-4d96-bf1e-88911a7b1aca | B92: =IFERROR(__xludf.DUMMYFUNCTION("""COMPUTED_VALUE"""),"Bolsa De Te Vacia") -> Bolsa De Te Vacia | C92: 189 | D92: =IFERROR(__xludf.DUMMYFUNCTION("""COMPUTED_VALUE"""),6) -> 6 | E92: =IFERROR(__xludf.DUMMYFUNCTION("""COMPUTED_VALUE"""),"UN") -> UN | F92: =IFERROR(__xludf.DUMMYFUNCTION("""COMPUTED_VALUE"""),"Desechables") -> Desechables | G92: =(C92)*D92 -> 1134 | H92: =G92*19% -> 215.46 | I92: =G92+H92 -> 1349.46
A93: =IFERROR(__xludf.DUMMYFUNCTION("""COMPUTED_VALUE"""),"ti-ing-022d8136-e142-4e65-9ece-9de98d9f28b4") -> ti-ing-022d8136-e142-4e65-9ece-9de98d9f28b4 | B93: =IFERROR(__xludf.DUMMYFUNCTION("""COMPUTED_VALUE"""),"BOLSA KRAFT CON TROQUEL 28X28X15 (1X500)") -> BOLSA KRAFT CON TROQUEL 28X28X15 (1X500) | C93: 80 | D93: =IFERROR(__xludf.DUMMYFUNCTION("""COMPUTED_VALUE"""),101.162) -> 101.162 | E93: =IFERROR(__xludf.DUMMYFUNCTION("""COMPUTED_VALUE"""),"UN") -> UN | F93: =IFERROR(__xludf.DUMMYFUNCTION("""COMPUTED_VALUE"""),"Desechables") -> Desechables | G93: =(C93)*D93 -> 8092.96 | H93: =G93*19% -> 1537.6624 | I93: =G93+H93 -> 9630.6224
A94: =IFERROR(__xludf.DUMMYFUNCTION("""COMPUTED_VALUE"""),"ti-ing-171a7412-fad1-4c6f-b2ed-c117f284a505") -> ti-ing-171a7412-fad1-4c6f-b2ed-c117f284a505 | B94: =IFERROR(__xludf.DUMMYFUNCTION("""COMPUTED_VALUE"""),"BOLSA KRAFT CON TROQUEL 32X32X18 (1X200)") -> BOLSA KRAFT CON TROQUEL 32X32X18 (1X200) | C94: 22 | D94: =IFERROR(__xludf.DUMMYFUNCTION("""COMPUTED_VALUE"""),140.49) -> 140.49 | E94: =IFERROR(__xludf.DUMMYFUNCTION("""COMPUTED_VALUE"""),"UN") -> UN | F94: =IFERROR(__xludf.DUMMYFUNCTION("""COMPUTED_VALUE"""),"Desechables") -> Desechables | G94: =(C94)*D94 -> 3090.78 | H94: =G94*19% -> 587.2482 | I94: =G94+H94 -> 3678.0282
A95: =IFERROR(__xludf.DUMMYFUNCTION("""COMPUTED_VALUE"""),"ti-ing-3f369fe5-7a8e-404f-b4c8-6069d9081623") -> ti-ing-3f369fe5-7a8e-404f-b4c8-6069d9081623 | B95: =IFERROR(__xludf.DUMMYFUNCTION("""COMPUTED_VALUE"""),"BOLSAS PORCIONADORAS DE PULPA (5 kilos)") -> BOLSAS PORCIONADORAS DE PULPA (5 kilos) | C95: 0.12 | D95: =IFERROR(__xludf.DUMMYFUNCTION("""COMPUTED_VALUE"""),17850) -> 17850 | E95: =IFERROR(__xludf.DUMMYFUNCTION("""COMPUTED_VALUE"""),"UN") -> UN | F95: =IFERROR(__xludf.DUMMYFUNCTION("""COMPUTED_VALUE"""),"Desechables") -> Desechables | G95: =(C95)*D95 -> 2142 | H95: =G95*19% -> 406.98 | I95: =G95+H95 -> 2548.98
A96: =IFERROR(__xludf.DUMMYFUNCTION("""COMPUTED_VALUE"""),"ti-ing-657d0c90-aee6-466b-953a-6144f3a6e8dd") -> ti-ing-657d0c90-aee6-466b-953a-6144f3a6e8dd | B96: =IFERROR(__xludf.DUMMYFUNCTION("""COMPUTED_VALUE"""),"BOMBILLAS (Unidad)") -> BOMBILLAS (Unidad) | C96: 350 | D96: =IFERROR(__xludf.DUMMYFUNCTION("""COMPUTED_VALUE"""),8.03519765) -> 8.0351977 | E96: =IFERROR(__xludf.DUMMYFUNCTION("""COMPUTED_VALUE"""),"UN") -> UN | F96: =IFERROR(__xludf.DUMMYFUNCTION("""COMPUTED_VALUE"""),"Desechables") -> Desechables | G96: =(C96)*D96 -> 2812.3192 | H96: =G96*19% -> 534.34064 | I96: =G96+H96 -> 3346.6598
